Workbook

Sheet raw
A1: Nom | B1: Marque | C1: Groupe(s) / Société(s) cosmétique(s) | D1: Gamme | E1: Catégorie(s) cosmétique(s) | F1: Zone(s) d'application | G1: Type(s) de produit - Formulation(s) / Galénique(s) | H1: Cible(s) cosmétique(s) | I1: Conseils d'utilisation | J1: Ingrédients | K1: Article(s) de conditionnement / Packaging | L1: Contenance | M1: Made in | N1: Code EAN | O1: Inclusao
A2: DOUBLE WEAR - TEINT LONGUE TENUE POUDRE MAT | B2: ESTÉE LAUDER | C2: THE ESTÉE LAUDER COS. | D2: DOUBLE WEAR | E2: MAQUILLAGE | F2: VISAGE | G2: FOND DE TEINT,POUDRE | H2: TOUTES CARNATIONS | I2: Personnalisez votre couvrance avec l’applicateur double face : - Utilisez le côté éponge pour une application couvrante du fond de teint poudre sur l’ensemble du visage. - Utilisez le côté velours pour une couvrance plus douce ou ciblée. | J2: INCI TEINTE 3N1 IVORY BEIGE : SYNTHETIC FLUORPHLOGOPITE,ZINC STEARATE,BORON NITRIDE,SILICA,ALUMINA,POLYGLYCERYL-3 DIISOSTEARATE,LAUROYL LYSINE,BUTYLENE GLYCOL DICAPRYLATE/DICAPRATE,MAGNESIUM CARBONATE,TRIETHOXYCAPRYLYLSILANE,TOCOPHEROL,CAPRYLIC/CAPRIC TRIGLYCERIDE,CAPRYLYL GLYCOL,ETHYLHEXYLGLYCERIN,DIMER DILINOLEYL DIMER DILINOLEATE,+/- (MAY CONTAIN),MICA,TITANIUM DIOXIDE (CI 77891),IRON OXIDES (CI 77491),IRON OXIDES (CI 77492),IRON OXIDES (CI 77499),ALUMINUM POWDER (CI 77000),BISMUTH OXYCHLORIDE (CI 77163),BRONZE POWDER (CI 77400),CHROMIUM HYDROXIDE GREEN (CI 77289),CHROMIUM OXIDE GREENS (CI 77288),COPPER POWDER (CI 77400),FERRIC AMMONIUM FERROCYANIDE (CI 77510),FERRIC FERROCYANIDE (CI 77510),MANGANESE VIOLET (CI 77742),ULTRAMARINES (CI 77007),BLUE 1 LAKE (CI 42090),YELLOW 5 LAKE (CI 19140) | K2: BOÎTIER,RECHARGEABLE | L2: 11 g | M2: ITALIE | N2: 0887167661042 | O2: 1
A3: ALL HOURS - HYPER LUMINIZE - POUDRE ILLUMINATRICE VERSATILE | B3: YVES SAINT LAURENT | C3: L'ORÉAL | D3: ALL HOURS | E3: MAQUILLAGE | F3: VISAGE | G3: ENLUMINEUR,POUDRE | H3: TOUS TYPES DE PEAUX | I3: Appliquez All Hours Hyper Luminize sur les points saillants du visage : pommettes, arête du nez, arc de Cupidon et coin interne de l'œil. Estompez délicatement au doigt ou au pinceau. | J3: INCI TEINTE LUMINIZE 03 : SYNTHETIC FLUORPHLOGOPITE,C12-15 ALKYL BENZOATE,DIMETHICONE,CI 77891/TITANIUM DIOXIDE,MICA,CALCIUM ALUMINUM BOROSILICATE,TALC,HYDROGENATED POLYISOBUTENE,GLASS BEADS,BORON NITRIDE,MAGNESIUM STEARATE,CI 77491/IRON OXIDES,SILICA,HYDROGENATED STYRENE/BUTADIENE COPOLYMER,CAPRYLYL GLYCOL,NIACINAMIDE,SODIUM HYALURONATE,CAPRYLIC/CAPRIC TRIGLYCERIDE,SORBITAN ISOSTEARATE,ISODODECANE,METHICONE,CI 75470/CARMINE,TIN OXIDE,CITRUS LIMON PEEL EXTRACT/LEMON PEEL EXTRACT,TRIS-BHT MESITYLENE,TOCOPHEROL | K3: BOÎTIER | L3: 5 g | M3: FRANCE | N3: 3614274197044 | O3: 1
A4: BLUSH POUDRE | B4: LE ROUGE FRANÇAIS | C4: LE ROUGE FRANÇAIS | E4: MAQUILLAGE | F4: JOUES | G4: FARD À JOUES/BLUSH,POUDRE | H4: TOUTES CARNATIONS | I4: Le blush poudre s’applique après avoir préparé et unifié la base teint. À l’aide du pinceau kabuki intégré, prélevez une petite quantité de poudre en tapotant pour contrôler sa quantité. Retirez l’excédent et appliquez par mouvements circulaires sur les zones bombées de votre visage, comme les pommettes. Pour intensifier le résultat, répétez l’application par légères touches jusqu’à obtenir le fini souhaité, naturel ou sophistiqué. | J4: TALC,TAPIOCA STARCH*,CI 77007 (ULTRAMARINES),CI 77947 (ZINC OXIDE),KAOLIN,MICA,RUBIA TINCTORUM ROOT*,COCO-CAPRYLATE/CAPRATE,SQUALANE,GLYCERYL CAPRYLATE,BUTYROSPERMUM PARKII (SHEA) BUTTER*,SIMMONDSIA CHINENSIS (JOJOBA) SEED OIL*,ZINC STEARATE,TOCOPHEROL,ARGANIA SPINOSA KERNEL OIL*,GLYCERYL UNDECYLENATE,HELIANTHUS ANNUUS (SUNFLOWER) SEED OIL | K4: BOÎTIER | L4: 9 g | M4: FRANCE | O4: 1
A5: PROTOCOLE ANTI-IMPERFECTIONS - LE STOP-BOUTONS | B5: LIERAC | C5: LABORATOIRE NATIVE | D5: PROTOCOLE | E5: SOIN VISAGE | F5: VISAGE | G5: SOIN NUIT,POUDRE | H5: PEAUX NORMALES,PEAUX MIXTES À GRASSES,PEAUX MIXTES,PEAUX GRASSES | I5: Appliquer le soir. Ne pas agiter. Plonger un coton-tige dans le flacon jusqu'à la poudre puis appliquer sur les imperfections ciblées. Eviter le contour des yeux. Pour un protocole complet, utiliser en complément la ② Solution long terme : Le Peeling. | J5: ALCOHOL DENAT.,AQUA/WATER/EAU,ZINC OXIDE,CALAMINE,TALC,GLYCERIN,PROPANEDIOL,CI 77891/TITANIUM DIOXIDE,ZINC GLUCONATE,CAMPHOR,POTASSIUM AZELOYL DIGLYCINATE,SALICYLIC ACID,MENTHOL | K5: FLACON | L5: 15 ml | M5: FRANCE | N5: 3701436926229 | O5: 0
A6: LES TAROTS DE CHANEL - POUDRE BLUSH MATE | B6: CHANEL | C6: GROUPE CHANEL | D6: ÉDITION LIMITÉE 2024 | E6: MAQUILLAGE | F6: JOUES | G6: FARD À JOUES/BLUSH,POUDRE | H6: TOUTES CARNATIONS | I6: Appliquer la Création Exclusive LES TAROTS DE CHANEL sur les pommettes à l'aide du pinceau inclus pour apporter de la couleur au teint. Appliquer une touche légère pour un maquillage naturel. Ajouter une seconde touche pour intensifier le résultat. | J6: INCI TEINTE BLOOD ORANGE : SYNTHETIC FLUORPHLOGOPITE,ZINC STEARATE,SQUALANE,CAPRYLYL GLYCOL,ETHYLHEXYLGLYCERIN,ALUMINUM HYDROXIDE,AQUA (WATER),ALCOHOL,GLYCERIN,TOCOPHEROL,POLYSORBATE 80,+/- (MAY CONTAIN),CI 12085 (RED 36),CI 15850 (RED 6),CI 15850 (RED 7 LAKE),CI 15880 (RED 34),CI 15985 (YELLOW 6 LAKE),CI 17200 (RED 33 LAKE),CI 19140 (YELLOW 5 LAKE),CI 42090 (BLUE 1 LAKE),CI 42090 (BLUE 1),CI 45380 (RED 22 LAKE),CI 45410 (RED 28 LAKE),CI 45410 (RED 28),CI 73360 (RED 30 LAKE),CI 77007 (ULTRAMARINES),CI 77163 (BISMUTH OXYCHLORIDE),CI 77491, CI 77492, CI 77499 (IRON OXIDES),CI 77510 (FERRIC FERROCYANIDE),CI 77742 (MANGANESE VIOLET),CI 77891 (TITANIUM DIOXIDE),MICA | K6: BOÎTIER | L6: 14 g | M6: ITALIE | N6: 3145891517286 | O6: 1
A7: TEINT IDOLE ULTRA WEAR - C.E. SKIN TRANSFORMING HIGHLIGHTER | B7: LANCÔME | C7: L'ORÉAL | D7: TEINT IDOLE ULTRA WEAR | E7: MAQUILLAGE | F7: VISAGE | G7: ENLUMINEUR,POUDRE | H7: TOUS TYPES DE PEAUX,TOUTES CARNATIONS | I7: Appliquer Advance Génifique et masser vers le haut du visage pour une peau instantanément hydratée. Appliquer le fond de teint Teint Idole Ultra Wear pour une couverture parfaite. Appliquer ensuite un correcteur pour un effet lumineux et lifté. Bronzez instantanément votre peau avec le nouveau Teint Idole Ultra Wear C.E. Skin Transforming Bronzer. Utilisez un pinceau large et appliquez-le par mouvements circulaires là où le soleil se pose naturellement sur la peau (joues, nez, tempes et menton). Highlightez les zones naturelles de lumière avec le nouveau Teint Idole Ultra Wear C.E. Skin Transforming Highlighter. Utilisez un pinceau large et appliquez-le là où la lumière illumine votre visage (haut des joues, nez, menton). | J7: INCI TEINTE 01 LIGHT GLOW : TALC,CAPRYLIC/CAPRIC TRIGLYCERIDE,DIMETHICONE,ZINC STEARATE,SILICA,ZEA MAYS STARCH/CORN STARCH,PUNICA GRANATUM PERICARP EXTRACT,MORINGA OLEIFERA SEED OIL,ALARIA ESCULENTA EXTRACT,ISODODECANE,DIMETHICONE/VINYL DIMETHICONE CROSSPOLYMER,DIMETHICONOL,SILICA [NANO]/SILICA,TRIMETHYLSILOXYSILICATE,ASCORBYL TETRAISOPALMITATE,CAPRYLYL GLYCOL,ETHYLHEXYLGLYCERIN,TOCOPHEROL,POTASSIUM SORBATE,PARFUM/FRAGRANCE,LINALOOL,LIMONENE,+/- (MAY CONTAIN),MICA,CI 77491/IRON OXIDES,CI 77492/IRON OXIDES,CI 77499/IRON OXIDES,CI 77891/TITANIUM DIOXIDE | K7: BOÎTIER | L7: 10 g | M7: ITALIE | N7: 3614274110470 | O7: 1
A8: LES BEIGES - POUDRE BELLE MINE ENSOLEILLÉE 2024 | B8: CHANEL | C8: GROUPE CHANEL | E8: MAQUILLAGE | F8: VISAGE,COU,BUSTE/DÉCOLLETÉ | G8: ENLUMINEUR,POUDRE | H8: TOUTES CARNATIONS,TOUS TYPES DE PEAUX | I8: Pour une application simple et intuitive, prélever les trois poudres en un seul geste avec le PINCEAU POUDRE N°106. Appliquer sur les pommettes et à l’envi sur le front, les tempes, le nez et le menton pour réchauffer l’ensemble du visage. Pour une application plus structurée, utiliser le PINCEAU POUDRE N°106 pour appliquer les différents tons de LES BEIGES POUDRE BELLE MINE ENSOLEILLÉE. - Appliquer la poudre bronzante sur les pommettes en commençant par l'extérieur du visage et en terminant par le milieu de la joue, en effectuant des mouvements circulaires. Cette teinte peut également être appliquée sur le front, les tempes, le nez et le menton pour donner plus de chaleur à l'ensemble du visage. - Appliquer le blush en l’étirant des pommettes vers l’extérieur pour rehausser les pommettes. - Appliquer l’highlighter sur le haut des pommettes pour rehausser le teint et apporter une touche supplémentaire de lumière. | J8: INCI HARMONIE DEEP ROSE GOLD - POUDRE BRONZANTE : SYNTHETIC FLUORPHLOGOPITE,LAUROYL LYSINE,ZINC STEARATE,BORON NITRIDE,OCTYLDODECYL STEAROYL STEARATE,ZEA MAYS (CORN) STARCH,OCTYLDODECANOL,JASMINUM GRANDIFLORUM (JASMINE) FLOWER EXTRACT,1,2-HEXANEDIOL,CAPRYLYL GLYCOL,PARFUM (FRAGRANCE),ETHYLHEXYL PALMITATE,KAOLIN,TOCOPHERYL ACETATE,SILICA,+/- (MAY CONTAIN),CI 12085 (RED 36),CI 15850 (RED 6),CI 15850 (RED 7 LAKE),CI 15880 (RED 34),CI 15985 (YELLOW 6 LAKE),CI 17200 (RED 33 LAKE),CI 19140 (YELLOW 5 LAKE),CI 42090 (BLUE 1 LAKE),CI 45380 (RED 22 LAKE),CI 45410 (RED 28 LAKE),CI 73360 (RED 30 LAKE),CI 77007 (ULTRAMARINES),CI 77163 (BISMUTH OXYCHLORIDE),CI 77491, CI 77492, CI 77499 (IRON OXIDES),CI 77510 (FERRIC FERROCYANIDE),CI 77742 (MANGANESE VIOLET),CI 77891 (TITANIUM DIOXIDE),MICA | K8: BOÎTIER | L8: 15 g | M8: ITALIE | N8: 3145891863703 | O8: 1
A9: OMBRE ESSENTIELLE - OMBRE À PAUPIÈRES LONGUE TENUE MULTI-USAGE | B9: CHANEL | C9: GROUPE CHANEL | E9: MAQUILLAGE | F9: PAUPIÈRES | G9: FARD À PAUPIÈRES,COMPACT,POUDRE | H9: CONVIENT AUX PORTEURS DE LENTILLES | I9: Avec OMBRE ESSENTIELLE, affirmer son look en jouant sur 3 applications différentes, à porter seules ou en accumulation : - Ombrer l’intégralité des paupières d’une couleur intense et lumineuse. - Accentuer le regard d’un simple trait d’eye-liner aussi graphique que subtil. - Intensifier les sourcils d’une pointe de couleur audacieuse pour un look singulier. Humidifier légèrement le pinceau eye-liner biseauté afin d’obtenir un fini précis et une couleur intensifiée. | J9: INCI TEINTE 226 - ROUGE COSMOS : SYNTHETIC FLUORPHLOGOPITE,OCTYLDODECYL STEAROYL STEARATE,DIMETHICONE,POLYBUTENE,TRIMETHYLSILOXYSILICATE,CELLULOSE,HYDROGEN DIMETHICONE,CAPRYLYL GLYCOL,MAGNESIUM STEARATE,POTASSIUM SORBATE,SILICA,CHLORPHENESIN,TOCOPHERYL ACETATE,DIMETHICONE CROSSPOLYMER,SALVIA HISPANICA SEED OIL,TOCOPHEROL,+/- (MAY CONTAIN),CI 75470 (CARMINE),CI 77000 (ALUMINUM POWDER),CI 77007 (ULTRAMARINES),CI 77163 (BISMUTH OXYCHLORIDE),CI 77288 (CHROMIUM OXIDE GREENS),CI 77491, CI 77492, CI 77499 (IRON OXIDES),CI 77510 (FERRIC AMMONIUM FERROCYANIDE),CI 77510 (FERRIC FERROCYANIDE),CI 77742 (MANGANESE VIOLET),CI 77891 (TITANIUM DIOXIDE),MICA | K9: BOÎTIER | L9: 1,9 g | M9: FRANCE | N9: 3145891812268 | O9: 1
A10: MÉTÉORITES - PERLES DE POUDRE RÉVÉLATRICES DE LUMIÈRE - NOUVELLE FORMULE 2024 | B10: GUERLAIN | C10: LVMH | D10: MÉTÉORITES | E10: MAQUILLAGE | F10: VISAGE | G10: ENLUMINEUR,PERLES,POUDRE | H10: TOUTES CARNATIONS | I10: Utiliser le pinceau Météorites pour appliquer uniformément sur l’ensemble du visage, pour fixer le maquillage et améliorer sa tenue. Pour un éclat boosté, illuminer les parties bombées : dessiner un G du centre du front vers les tempes, les pommettes et le haut du nez en redescendant jusqu’à la pointe du menton. | J10: INCI TEINTE 04 AMBER/AMBRE : MICA,DISTARCH PHOSPHATE,SILICA,MAGNESIUM MYRISTATE,SYNTHETIC FLUORPHLOGOPITE,CELLULOSE,MAGNESIUM CARBONATE HYDROXIDE,CALCIUM SODIUM BOROSILICATE,HYDROXYPROPYL STARCH,CAPRYLYL GLYCOL,ETHYLHEXYLGLYCERIN,PARFUM (FRAGRANCE),SODIUM DEHYDROACETATE,CALCIUM ALUMINUM BOROSILICATE,SORBIC ACID,TIN OXIDE,TOCOPHEROL,+/- (MAY CONTAIN),CI 77891 (TITANIUM DIOXIDE),CI 77163 (BISMUTH OXYCHLORIDE),CI 77491, CI 77492, CI 77499 (IRON OXIDES),CI 77288 (CHROMIUM OXIDE GREENS),CI 73360 (RED 30 LAKE),CI 77007 (ULTRAMARINES) | K10: BOÎTIER | L10: 25 g | M10: FRANCE | N10: 3346470438781 | O10: 1
A11: THE POREfessional WOW POLISH | B11: BENEFIT | C11: LVMH | D11: THE POREfessional | E11: SOIN VISAGE | F11: VISAGE | G11: GOMMAGE,POUDRE | H11: TOUS TYPES DE PEAUX | I11: Saupoudrez dans la paume humide et frottez pour faire mousser. Massez sur le visage en évitant le contour des yeux, puis rincez. Utilisez 1 à 2 fois par semaine après le nettoyage. Mélangez avec la baguette Wow (incluse) pour préserver une poudre uniforme. | J11: SODIUM COCOYL ISETHIONATE,SODIUM METHYL COCOYL TAURATE,KAOLIN,TAPIOCA STARCH,SODIUM CHLORIDE,ZEA MAYS (CORN) STARCH,PERLITE,HYDROXYPROPYL METHYLCELLULOSE,SQUALANE,GLUCONOLACTONE,MICA,GLYCERYL CAPRYLATE,PENTYLENE GLYCOL,COCOS NUCIFERA (COCONUT) FRUIT EXTRACT,LACTIC ACID,CI 77742 (MANGANESE VIOLET),DEHYDROACETIC ACID,AQUA (WATER),DIMETHICONE,BISABOLOL,GLYCERYL UNDECYLENATE,PARFUM (FRAGRANCE),MALTODEXTRIN,SODIUM GLUCONATE,COCAMIDOPROPYL BETAINE,AVENA SATIVA (OAT) KERNEL FLOUR,FARNESOL,CI 42090 (BLUE 1 LAKE),CI 19140 (YELLOW 5 LAKE),PENTAERYTHRITYL TETRA-DI-T-BUTYL HYDROXYHYDROCINNAMATE,TOCOPHEROL | K11: FLACON | L11: 45 g | N11: 0602004153746 | O11: 0
A12: ARTIST EYESHADOW - NOUVELLE FORMULE 2024 | B12: MAKE UP FOR EVER | C12: LVMH | E12: MAQUILLAGE | F12: PAUPIÈRES | G12: FARD À PAUPIÈRES,POUDRE | H12: TOUTES CARNATIONS | I12: 1/ Prélever la matière avec le côté plat du pinceau #248. 2/ Appliquer l'ombre à paupières sur la zone souhaitée en tapotant délicatement puis en effectuant des mouvements de balayage avec la partie plate du pinceau. 3/ Avec le côté rond du pinceau #248, estomper avec de petits mouvements circulaires, puis d'avant en arrière. | J12: INCI TEINTE 100 - WHATEVER BLACK : SYNTHETIC FLUORPHLOGOPITE,DIMETHICONE,ZINC STEARATE,CAPRYLYL GLYCOL,PENTYLENE GLYCOL,ETHYLHEXYLGLYCERIN,SILICA,DIISOSTEARYL MALATE,OCTYLDODECYL STEAROYL STEARATE,SODIUM DEHYDROACETATE,KAOLIN,TOCOPHERYL ACETATE,SORBITAN SESQUIOLEATE,TOCOPHEROL,+/- (MAY CONTAIN),CI 77499 (IRON OXIDES),CI 77266 [NANO] (BLACK 2),CI 77007 (ULTRAMARINES) | K12: BOÎTIER | L12: 5 g | O12: 1
A13: POUDRE-MOUSSE NETTOYANTE | B13: COTTAN | C13: Beauty Brands Studio | E13: SOIN VISAGE | F13: VISAGE | G13: DÉMAQUILLANT/NETTOYANT,POUDRE | H13: TOUS TYPES DE PEAUX,CONVIENT AUX PEAUX SENSIBLES/RÉACTIVES | I13: Déposez de la poudre et de l'eau dans le creux de votre main, puis frictionnez afin d'obtenir une mousse à appliquer sur votre visage. Lavez votre visage à votre habitude avant de rincer abondamment. Évitez le contact avec les yeux. | J13: ZEA MAYS STARCH,DISODIUM COCOYL GLUTAMATE,SODIUM COCOYL GLUTAMATE,ORYZA SATIVA (RICE) POWDER,PARFUM (FRAGRANCE),PAEONIA OFFICINALIS ROOT EXTRACT | K13: FLACON SALIÈRE | L13: 30 g | M13: FRANCE | N13: 3760262407050 | O13: 0
A14: ALWAYS FABULOUS - FOND DE TEINT POUDRE SPF 20 | B14: BOURJOIS | C14: COTY GROUP INC | D14: ALWAYS FABULOUS | E14: MAQUILLAGE | F14: VISAGE | G14: FOND DE TEINT,POUDRE | H14: TOUS TYPES DE PEAUX,TOUTES CARNATIONS | I14: Appliquez d'abord la poudre matifiante sur la zone T, puis sur l'ensemble du visage si nécessaire, pour un teint matifié. | J14: MICA,ZINC OXIDE,KAOLIN,ZINC STEARATE,DIMETHICONE,BUTYLOCTYL SALICYLATE,BORON NITRIDE,TRIMETHYLSILOXYSILICATE,SACCHAROMYCES FERMENT,SILICA,TRIETHOXYCAPRYLYLSILANE,1,2-HEXANEDIOL,CAPRYLYL GLYCOL,SODIUM BENZOATE,METHICONE,ALUMINA,LAUROYL LYSINE,PARFUM/FRAGRANCE,SODIUM HYALURONATE,HYDROGEN DIMETHICONE,DIMETHYLMETHOXY CHROMANOL,BENZYL SALICYLATE,+/- (MAY CONTAIN),TITANIUM DIOXIDE (CI 77891),IRON OXIDES (CI 77491, CI 77492, CI 77499) | K14: BOÎTIER | L14: 10 g | O14: 1
A15: OMBRE D'HERMÈS - PALETTE DE COULEURS QUATUOR OMBRES POUR LES YEUX | B15: HERMÈS | C15: HERMÈS INTERNATIONAL | D15: LE REGARD | E15: MAQUILLAGE | F15: PAUPIÈRES | G15: FARD À PAUPIÈRES,POUDRE | H15: TOUS TYPES DE PEAUX | I15: Appliquer et estomper sur les paupières à l'aide de votre pinceau préféré. Si vous le souhaitez, mouillez légèrement le pinceau avant l'application pour amplifier l'intensité et la précision de la couleur. | J15: OMBRES MORDORÉES - LIGHT ACCENT & NEUTRAL BASE (IRISÉ/IRIDESCENT) INGREDIENTS : MICA,CALCIUM SODIUM BOROSILICATE,CAPRYLIC/CAPRIC TRIGLYCERIDE,OCTYLDODECYL STEAROYL STEARATE,ZINC STEARATE,METHYLPROPANEDIOL,PHENOXYETHANOL,CAPRYLYL GLYCOL,SODIUM DEHYDROACETATE,TIN OXIDE,PHENYLPROPANOL,CELLULOSE,MAGNESIUM STEARATE,MORUS ALBA BARK EXTRACT,+/- (MAY CONTAIN),CI 77891 (TITANIUM DIOXIDE),CI 77163 (BISMUTH OXYCHLORIDE),CI 77492/CI 77491/CI 77499 (IRON OXIDES),CI 19140 (YELLOW 5 LAKE) | K15: BOÎTIER,RECHARGEABLE | L15: 3 g | M15: ITALIE | N15: 3346130411314 | O15: 1
A16: SKIN PROUD - GLOW DUST - EXFOLIATING POWDER CLEANSER | B16: I AM PROUD | C16: LOTTIE LONDON LIMITED | D16: SKIN PROUD | E16: SOIN VISAGE | F16: VISAGE | G16: DÉMAQUILLANT/NETTOYANT,POUDRE | H16: TOUS TYPES DE PEAUX | I16: Pour half a teaspoon of powder into wet hands, add a small amount of water and rub together to create a milky lather. Massage into face, avoiding the eye area, and rinse off. Use 2-3 times a week. Top Tip: combine with your cleanser to add extra exfoliation. | J16: MANNITOL,MICROCRYSTALLINE CELLULOSE,SODIUM COCOYL ISETHIONATE,3-O-ETHYL ASCORBIC ACID,BUTYLENE GLYCOL,CELLULOSE GUM,LEUCONOSTOC/RADISH ROOT FERMENT FILTRATE,PEG-40 HYDROGENATED CASTOR OIL,COCONUT ACID,BROMELAIN,CAMELLIA SINENSIS LEAF EXTRACT,HYDROXYPROPYL METHYLCELLULOSE,AQUA (WATER, EAU),MORINGA OLEIFERA SEED EXTRACT,SODIUM ISETHIONATE,GLUCONOLACTONE,SIMMONDSIA CHINENSIS (JOJOBA) SEED OIL,TOCOPHERYL ACETATE,MACADAMIA INTEGRIFOLIA SEED OIL,GLYCINE SOJA (SOYBEAN) OIL,GLYCERIN,FERULIC ACID,1,6-HEXAMETHYLENE DIISOCYANATE,GLYCYRRHIZA GLABRA (LICORICE) ROOT EXTRACT,PHENOXYETHANOL,POTASSIUM SORBATE,SODIUM BENZOATE,DISODIUM PHOSPHATE,CITRIC ACID,TOCOPHEROL | K16: FLACON SALIÈRE,CAPSULE SERVICE | L16: 40 g | M16: AUSTRALIE | N16: 5056183607869 | O16: 0
A17: BOUQUET FLORAL - POUDRE EXFOLIANTE DOUCEUR | B17: MELVITA | C17: GROUPE L'OCCITANE | D17: BOUQUET FLORAL | E17: SOIN VISAGE | F17: VISAGE | G17: GOMMAGE,POUDRE,ANHYDRE | H17: TOUS TYPES DE PEAUX | I17: Melvita recommande d'utiliser sa poudre exfoliante douceur à raison de 2 fois par semaine, de préférence le soir. Mélangez dans la main humide 1 cuillère à café de poudre puis 1 cuillère à café d'eau. Massez ce mélange sur le visage préalablement mouillé, en évitant la zone du contour des yeux, et rincez abondamment. Pour une exfoliation plus intense, laissez poser 30 à 60 secondes. | J17: ZEA MAYS (CORN) STARCH*,GLUCOSE,SODIUM COCOYL GLUTAMATE,LACTOBACILLUS/PUNICA GRANATUM FRUIT FERMENT EXTRACT,HIBISCUS SABDARIFFA FLOWER EXTRACT,MALTODEXTRIN,CAMELLIA SINENSIS LEAF EXTRACT,HYDROLYZED GARDENIA FLORIDA EXTRACT,MAGNESIUM HYDROXIDE,PARFUM/FRAGRANCE,LINALOOL,LIMONENE,CITRONELLOL,GERANIOL | K17: FLACON,CAPSULE SERVICE | L17: 30 g | M17: FRANCE | N17: 3284410049812 | O17: 0
A18: POUDRE DE LAIT EXFOLIANTE | B18: EMBRYOLISSE | C18: LABORATOIRES EMBRYOLISSE | E18: SOIN VISAGE | F18: VISAGE | G18: GOMMAGE,POUDRE,LAIT | H18: TOUS TYPES DE PEAUX | I18: Pour une exfoliation moussante : Mélanger dans le creux de la main une petite quantité de poudre et quelques gouttes d'eau, masser le visage puis rincer à l'eau. 2 ou 3 fois par semaine. Eviter le contact avec les yeux. En cas de contact, rincer abondamment à l'eau claire. Vous pouvez également associer la Poudre de Lait Exfoliante à d’autres soins Embryolisse, comme le Lait-Crème Concentré ou l'Eau Active, pour une utilisation personnalisée qui répond aux besoins de chaque peau. | J18: ORYZA SATIVA (RICE) STARCH,ZEA MAYS (CORN) STARCH,SODIUM LAUROYL GLUTAMATE,COCOS NUCIFERA FRUIT POWDER,COCOS NUCIFERA (COCONUT) SHELL POWDER,CITRIC ACID,CALCIUM CARBONATE,SODIUM BICARBONATE,MALTODEXTRIN,PARFUM (FRAGRANCE),COCOS NUCIFERA (COCONUT) FRUIT EXTRACT | K18: FLACON,CAPSULE SERVICE | L18: 40 g | M18: FRANCE | N18: 3350900002572 | O18: 0
A19: GOOF PROOF BROW POWDER - EASY BROW FILLING POWDER | B19: BENEFIT | C19: LVMH | E19: MAQUILLAGE | F19: SOURCILS | G19: POUDRE,COMPACT | I19: Apply with an angled brush to outline brows, shape and define. Use light strokes to fill in sparse brow areas and layer to build color. Blend with spoolie. | J19: 4 WARM DEEP BROWN INGREDIENTS LISTING : MICA,SYNTHETIC FLUORPHLOGOPITE,DIMETHICONE,TRIMETHYLSILOXYSILICATE,MICROCRYSTALLINE CELLULOSE,KAOLIN,MAGNESIUM STEARATE,TRIETHOXYCAPRYLYLSILANE,MAGNESIUM MYRISTATE,RICINUS COMMUNIS (CASTOR) SEED OIL,PHENOXYETHANOL,SORBIC ACID,CAPRYLYL GLYCOL,TOCOPHEROL,HELIANTHUS ANNUUS (SUNFLOWER) SEED OIL,+/- (MAY CONTAIN),CI 77491, CI 77492, CI 77499 (IRON OXIDES),CI 77891 (TITANIUM DIOXIDE),CI 19140 (YELLOW 5 LAKE),CI 42090 (BLUE 1 LAKE),CI 77007 (ULTRAMARINES),CI 77742 (MANGANESE VIOLET) | K19: BOÎTIER | L19: 1,9 g | M19: FRANCE | N19: 0602004140357 | O19: 1
A20: SKIN PERFECTO - CRÈME COMPACTE SPF 30/PA++ - NOUVELLE FORMULE 2023 | B20: GIVENCHY | C20: LVMH | D20: SKIN PERFECTO | E20: MAQUILLAGE | F20: VISAGE | G20: SOIN,CRÈME/ÉMULSION,COMPACT | H20: TOUS TYPES DE PEAUX | I20: Utilisez la Crème Compacte à la place de votre crème habituelle, après le Sérum Éclat Multi-Vitaminé Skin Perfecto ou en retouches à tout moment de la journée pour donner un boost d'éclat à votre peau. ÉTAPE 1 Prélevez délicatement la crème avec l'applicateur. ÉTAPE 2 Lissez sur l'ensemble du visage en effectuant des mouvements ascendants. ÉTAPE 3 Répartissez uniformément en pressant jusqu'à absorption. ÉTAPE 4 Retouchez tout au long de la journée en tapotant légèrement pour une touche d'éclat instantanée. LE CONSEIL PROFESSIONNEL Appliquez une deuxième couche de crème compacte à l'endroit où vous appliqueriez votre highlighter (pommettes). | J20: AQUA (WATER),DIBUTYL ADIPATE,GLYCERIN,ZINC OXIDE,DICAPRYLYL CARBONATE,CANDELILLA CERA (EUPHORBIA CERIFERA (CANDELILLA) WAX),BUTYLENE GLYCOL,ETHYLHEXYL SALICYLATE,PHENYL TRIMETHICONE,DIMETHICONE,BIS-ETHYLHEXYLOXYPHENOL METHOXYPHENYL TRIAZINE,ETHYLHEXYL TRIAZONE,MICA,CI 77891 (TITANIUM DIOXIDE),CETYL PEG/PPG-10/1 DIMETHICONE,CERA CARNAUBA (COPERNICA CERIFERA (CARNAUBA) WAX),SYNTHETIC FLUORPHLOGOPITE,C30-45 ALKYL METHICONE,C30-45 OLEFIN,CAPRYLYL GLYCOL,MYRISTYL MYRISTATE,SORBITAN SESQUIOLEATE,ETHYLHEXYLGLYCERIN,PARFUM (FRAGRANCE),DIMETHICONE/PEG-10/15 CROSSPOLYMER,ASCORBYL GLUCOSIDE,HYDROXYACETOPHENONE,CHLORPHENESIN,TOCOPHERYL ACETATE,SILICA,CITRUS PARADISI (GRAPEFRUIT) FRUIT EXTRACT,TRIETHOXYCAPRYLYLSILANE,SCHINUS TEREBINTHIFOLIUS SEED EXTRACT,XANTHAN GUM,HYDROGEN DIMETHICONE,CITRIC ACID,CI 77491 (IRON OXIDES),DIPROPYLENE GLYCOL,SODIUM CITRATE,TOCOPHEROL,PENTAERYTHRITYL TETRA-DI-T-BUTYL HYDROXYHYDROCINNAMATE | K20: BOÎTIER | L20: 12 g | M20: FRANCE | N20: 3274872444249 | O20: 0
A21: REUSABLE FOAMING CLEANSER STARTER KIT, BOTTLE & REFILL PACK | B21: NEUTROGENA | C21: JOHNSON & JOHNSON | E21: SOIN VISAGE | F21: VISAGE | G21: DÉMAQUILLANT/NETTOYANT,POUDRE | H21: TOUS TYPES DE PEAUX,CONVIENT AUX PEAUX SENSIBLES/RÉACTIVES | I21: DIRECTION TO MIX: FILL UP Remove pump. Fill the bottle to the indented fill line with 7.5 fl oz (221 mL) of warm, drinking quality water. POUR IN Cut open the packet along the dotted line and insert the mouth of it into the bottle (avoiding contact with water). To minimize dust, tap gently to empty the packet. Reattach pump. SHAKE Shake bottle for 10 seconds and wait for 1 minute before the first use. When finished, wash bottle according to carton instructions and fill with another concentrate refill! DIRECTION FOR USE: Wet face. Pump cleanser into hands. Massage face gently. Rinse. No need to shake. | J21: SODIUM METHYL COCOYL TAURATE,SODIUM COCOYL ISETHIONATE,SODIUM BENZOATE,MAGNESIUM SULFATE,CITRIC ACID,DISODIUM EDTA,ASCORBIC ACID | K21: EMBALLAGE SACHET/CARTON,FLACON MOUSSEUR,RECHARGEABLE | L21: 221 ml | M21: CANADA | O21: 0
A22: TERRACOTTA LUMINIZER - LA POUDRE ENLUMINEUR | B22: GUERLAIN | C22: LVMH | D22: TERRACOTTA | E22: MAQUILLAGE | F22: VISAGE | G22: ENLUMINEUR,POUDRE | H22: TOUTES CARNATIONS | I22: La poudre enlumineur Terracotta Luminizer peut s’utiliser sur le fond de teint ou la peau nue. Appliquer en touches sur le haut des pommettes, l’arête du nez et l’arc de Cupidon, pour un maquillage sensuel, éclatant et scintillant. Étirer sous l’arcade sourcilière, ou en ombre à paupières, pour un regard subtilement illuminé. | J22: MICA,CAPRYLIC/CAPRIC TRIGLYCERIDE,SILICA,ALUMINA,C13-15 ALKANE,COCO-CAPRYLATE/CAPRATE,POLYGLYCERYL-3 POLYRICINOLEATE,POLYGLYCERYL-4 CAPRATE,BUTYLENE GLYCOL,TRIHEPTANOIN,GLYCERIN,C9-12 ALKANE,PARFUM (FRAGRANCE),DILINOLEIC ACID/BUTANEDIOL COPOLYMER,CAPRYLYL GLYCOL,ETHYLHEXYLGLYCERIN,TRIETHOXYCAPRYLYLSILANE,1,2-HEXANEDIOL,LAUROYL LYSINE,POLYGLYCERYL-3 DIISOSTEARATE,GELLAN GUM,CALCIUM CHLORIDE,CASTOR OIL/IPDI COPOLYMER,ARGANIA SPINOSA KERNEL OIL,TOCOPHEROL,+/- (MAY CONTAIN),CI 77891 (TITANIUM DIOXIDE),CI 77163 (BISMUTH OXYCHLORIDE),CI 77491, CI 77492 (IRON OXIDES) | K22: BOÎTIER | L22: 7 g | M22: FRANCE | N22: 3346470435667 | O22: 1
A23: RARE EARTH DEEP PORE-MINIMIZING & POLISHING POWDER CLEANSER | B23: KIEHL'S | C23: L'ORÉAL | E23: SOIN VISAGE | F23: VISAGE | G23: DÉMAQUILLANT/NETTOYANT,POUDRE | H23: PEAUX NORMALES À GRASSES,PEAUX NORMALES,PEAUX GRASSES | I23: Gently shake before use. For use as a daily cleanser, apply a dime sized amount directly onto wet hands and work into a light foam, then apply onto damp facial skin in circular motions. Rinse thoroughly with water. Recommended as a daily cleanser twice a day. For a more intensive facial scrub, apply just a few drops of water to a dime sized amount of the powder cleanser to create a thicker paste. Rinse thoroughly with water after use. Recommended as a facial scrub 1–2 times a week. Explore our other pore minimizing formulas like our purifying clay mask, pore minimizing cleanser and pore minimizing toner. | J23: ZEA MAYS STARCH/CORN STARCH,DISODIUM LAURYL SULFOSUCCINATE,SODIUM LAUROYL GLUTAMATE,POTASSIUM COCOYL GLYCINATE,KAOLIN,POTASSIUM CHLORIDE,CELLULOSE,MICROCRYSTALLINE CELLULOSE,PERLITE,ALUMINUM STARCH OCTENYLSUCCINATE,MAGNESIUM STEARATE,TARTARIC ACID,AQUA/WATER,COCAMIDOPROPYL BETAINE,ALOE BARBADENSIS LEAF JUICE POWDER,ALLANTOIN,SODIUM CHLORIDE | K23: FLACON,CAPSULE SERVICE | L23: 100 g | M23: USA | N23: 3605972787231 | O23: 0
A24: HD SKIN - POWDER FOUNDATION - FOND DE TEINT POUDRE FLOUTTEUR IMPERCEPTIBLE 24H | B24: MAKE UP FOR EVER | C24: LVMH | D24: HD SKIN | E24: MAQUILLAGE | F24: VISAGE | G24: FOND DE TEINT,POUDRE,COMPACT | H24: TOUS TYPES DE PEAUX,TOUTES CARNATIONS | I24: Pour un véritable effet seconde peau : utilisez le HD SKIN POWDER FOUNDATION seul comme un fond de teint poudre en choisissant l'une de ces 2 alternatives : 1. Appliquez avec le côté doux de l'éponge, du centre du visage vers l'extérieur en tamponnant. 2. Pour un look plus naturel, appliquez le fond de teint avec l'autre côté de l'éponge, en étalant la matière. Pour un fini plus naturel ou une retouche : utilisez le pinceau n°128 sur l'ensemble du visage. Conseils de pro : 1. Il peut être utilisé en tant que primer sur les paupières grasses. 2. Il peut être utilisé pour les retouches avec le pinceau #128 pour estomper et couvrir uniquement les endroits nécessaires. 3. Il peut être utilisé avec un pinceau par dessus un fond de teint liquide pour fixer votre maquillage. | J24: INCI TEINTE CLAIRE - NUDE - BEIGE SOUS TON NEUTRE 2N22 : SYNTHETIC FLUORPHLOGOPITE,BORON NITRIDE,PENTAERYTHRITYL TETRAISOSTEARATE,SILICA,POLYMETHYL METHACRYLATE,ALUMINA,ZINC LAURATE,METHICONE,DIMETHICONE,CAPRYLYL GLYCOL,ETHYLHEXYLGLYCERIN,SODIUM DEHYDROACETATE,ALUMINUM HYDROXIDE,HYDROGEN DIMETHICONE,TOCOPHEROL,+/- (MAY CONTAIN),CI 77491, CI 77492, CI 77499 (IRON OXIDES),CI 77891 (TITANIUM DIOXIDE),CI 77163 (BISMUTH OXYCHLORIDE) | K24: BOÎTIER | L24: 11 g | M24: FRANCE | O24: 1
A25: FOND DE TEINT POUDRE SOIN SPF | B25: AIME | C25: AIME INC. SAS | E25: MAQUILLAGE | F25: VISAGE | G25: FOND DE TEINT,POUDRE | H25: TOUTES CARNATIONS,TOUS TYPES DE PEAUX,CONVIENT AUX PEAUX SENSIBLES/RÉACTIVES | I25: Appliquez votre Fond de Teint Poudre Soin sur une peau sèche et hydratée avec notre Pinceau Visage en réalisant des mouvements circulaires depuis le centre du visage. Répétez selon la couvrance souhaitée. | J25: MICA,ZINC STEARATE,TITANIUM DIOXIDE,LAUROYL LYSINE,SILICA,BORON NITRIDE,COCO-CAPRYLATE/CAPRATE,KAOLIN,OCTYLDODECYL STEAROYL STEARATE,OCTYLDODECYL PCA,CETYL ALCOHOL,TOCOPHERYL ACETATE,GLYCERYL CAPRYLATE,PENTYLENE GLYCOL,TIN OXIDE,SQUALANE,BISABOLOL,MAGNOLIA OFFICINALIS BARK EXTRACT,RICINUS COMMUNIS SEED OIL,HYDROLYZED SODIUM HYALURONATE,ALPHA-GLUCAN OLIGOSACCHARIDE,SODIUM HYALURONATE,HYDROGENATED CASTOR OIL,ZINGIBER OFFICINALE ROOT EXTRACT,+/- (MAY CONTAIN),CI 77891 (TITANIUM DIOXIDE),CI 19140 (YELLOW 5 LAKE),CI 77491 (IRON OXIDES),CI 77492 (IRON OXIDES),CI 77499 (IRON OXIDES) | K25: BOÎTIER | L25: 7 g | M25: FRANCE | O25: 1
A26: PURE C INTENSIVE TREATMENT - 800 MG VITAMIN C + 1,25% HA4 HYALURONIC ACID | B26: FaceD | C26: HCS | high cosmetic solution s.r.l. | E26: SOIN VISAGE | F26: VISAGE | G26: SOIN,FLUIDE/LIQUIDE,POUDRE | H26: TOUS TYPES DE PEAUX,CONVIENT AUX PEAUX SENSIBLES/RÉACTIVES | I26: Activate the treatment by pressing the tank cap containing vitamin C, so that it is released into the bottle. Shake the bottle vigorously for a few seconds to dissolve the vitamin C. Replace the cap with the reusable dropper. | J26: AQUA (WATER),ASCORBIC ACID,GLYCERIN,NIACINAMIDE,SODIUM HYALURONATE,PANTHENOL,SODIUM HYALURONATE CROSSPOLYMER,HYALURONIC ACID,PENTYLENE GLYCOL,DISODIUM EDTA,PHENOXYETHANOL,ETHYLHEXYLGLYCERIN | K26: FLACON,PIPETTE | L26: 4 x 4 ml | M26: ITALIE | O26: 0
A27: MY CLARINS CLEAR-OUT - LOTION CIBLÉE IMPERFECTIONS | B27: CLARINS | C27: GROUPE CLARINS | D27: MY CLARINS | E27: SOIN VISAGE | F27: VISAGE | G27: SOIN,LOTION,BI-PHASE,POUDRE | H27: TOUS TYPES DE PEAUX | I27: Insérez un coton tige directement dans la solution, sans la mélanger, afin de prélever un peu de poudre qui contient les actifs pour lutter contre les imperfections et appliquez-la sur le(s) bouton(s). | J27: AQUA/WATER/EAU,ALCOHOL,CI 77947/ZINC OXIDE,ISOPROPYL ALCOHOL,VACCINIUM MYRTILLUS FRUIT EXTRACT,GLYCERIN,SALICYLIC ACID,SACCHARUM OFFICINARUM (SUGAR CANE) EXTRACT,ZINC GLUCONATE,BUTYLENE GLYCOL,CITRUS AURANTIUM DULCIS (ORANGE) FRUIT EXTRACT,CITRUS LIMON (LEMON) FRUIT EXTRACT,SODIUM HYDROXIDE,T-BUTYL ALCOHOL,ACER SACCHARUM (SUGAR MAPLE) EXTRACT,SPIRAEA ULMARIA EXTRACT,DENATONIUM BENZOATE,CI 14700/RED 4 | K27: FLACON | L27: 13 ml | M27: FRANCE | N27: 3666057078415 | O27: 0
A28: MASQUE EXFOLIANT ENZYMATIQUE | B28: SISLEY | C28: GROUPE SISLEY | E28: SOIN VISAGE | F28: VISAGE | G28: MASQUE,PEELING,POUDRE | H28: TOUS TYPES DE PEAUX,CONVIENT AUX PEAUX SENSIBLES/RÉACTIVES | I28: Déposer l’équivalent d’une cuillère à café de poudre au creux de la main et mélanger du bout des doigts avec une petite quantité d’eau jusqu’à l’obtention d’une crème moussante. Appliquer en couche fine sur l’ensemble du visage et du cou, en évitant le contour des yeux. Laisser poser 1 minute maximum, puis rincer soigneusement à l’eau. Eviter le contact avec les yeux. Poursuivre par l’application du rituel de soins quotidiens suivants. | J28: HYDROXYPROPYL STARCH PHOSPHATE,CELLULOSE,SODIUM COCOYL GLYCINATE,AQUA/WATER/EAU,SILICA,SODIUM METHYL COCOYL TAURATE,NIACINAMIDE,MALTODEXTRIN,TITANIUM DIOXIDE (CI 77891),XANTHAN GUM,PAPAIN,LAVANDULA ANGUSTIFOLIA (LAVENDER) OIL,THYMUS MASTICHINA FLOWER OIL,SODIUM SURFACTIN,GUAR HYDROXYPROPYLTRIMONIUM CHLORIDE,HYDROGENATED LECITHIN,LINALOOL,LIMONENE | K28: FLACON,CAPSULE SERVICE | L28: 40 g | M28: FRANCE | N28: 3473311524355 | O28: 0
A29: RETINOL FAST RELEASE WRINKLE-REDUCING NIGHT SERUM | B29: KIEHL'S | C29: L'ORÉAL | D29: DERMATOLOGIST SOLUTIONS | E29: SOIN VISAGE | F29: VISAGE | G29: SOIN NUIT,SÉRUM,POUDRE | H29: TOUS TYPES DE PEAUX | I29: Pour l'activer : - Retournez le flacon, retirez le bouchon inférieur et mettez-le de côté. - Ouvrez la pochette, faites tourner la capsule de rétinol sur le fond du flacon. - Appuyez sur le bouton de la capsule pour libérer la poudre de rétinol pur. - Secouez vigoureusement pour que le produit soit entièrement mélangé au sérum. - Retirez et jetez la capsule, remplacez-la par le bouchon d'origine. Appliquer : - Appliquez une fois par jour, le soir. - Appuyez sur le bouton noir 2 à 3 fois pour obtenir une goutte de la taille d'un petit pois. - Appliquez délicatement sur une peau propre et sèche. - Complétez votre routine de soins de nuit avec notre crème anti-âge pour des bienfaits optimaux sur la jeunesse de votre peau. Le matin, utilisez notre correcteur de taches brunes et notre écran solaire pour le visage avec FPS 50 pour une peau plus claire. | J29: AQUA/WATER,GLYCERIN,PROPANEDIOL,BUTYLENE GLYCOL,GLYCERETH-26,PANTHENOL,1,2-HEXANEDIOL,POLYGLYCERIN-3,C12-14 PARETH-12,PHENOXYETHANOL,CAPRYLYL GLYCOL,AMMONIUM ACRYLOYLDIMETHYLTAURATE/VP COPOLYMER,BETAINE,XANTHAN GUM,ETHYLHEXYLGLYCERIN,ADENOSINE,CARBOMER,GLYCERYL ACRYLATE/ACRYLIC ACID COPOLYMER,TROMETHAMINE,GLYCERETH-25 PCA ISOSTEARATE,T-BUTYL ALCOHOL,TOCOPHEROL | K29: FLACON,EMBALLAGE SACHET/CARTON | L29: 28 ml|1 g | M29: CORÉE | O29: 0
A30: TERRACOTTA BLOOMING BEE - LA POUDRE ÉCLAT BONNE MINE - ÉDITION LIMITÉE | B30: GUERLAIN | C30: LVMH | D30: TERRACOTTA - ÉDITION LIMITÉE | E30: MAQUILLAGE | F30: VISAGE,COU | G30: ENLUMINEUR,POUDRE | H30: TOUTES CARNATIONS | I30: LE MOT DE VIOLETTE, DIRECTRICE DE LA CRÉATION DU MAQUILLAGE GUERLAIN : « MON SECRET POUR UN EFFET SUN-KISSED IRRÉSISTIBLE ? APPLIQUER LA TERRACOTTA SUR LES ZONES LES PLUS BOMBÉES COMME LES POMMETTES, L’ARÊTE DU NEZ ET LE HAUT DU FRONT POUR APPORTER PLUS DE STRUCTURE AU VISAGE TOUT EN RÉCHAUFFANT DÉLICATEMENT LE TEINT. » | J30: MICA,SILICA,LAUROYL LYSINE,ZINC STEARATE,BIS-BEHENYL/ISOSTEARYL/PHYTOSTERYL DIMER DILINOLEYL DIMER DILINOLEATE,OCTYLDODECYL STEAROYL STEARATE,DICAPRYLYL ETHER,CELLULOSE,CALCIUM SODIUM BOROSILICATE,DIMER DILINOLEYL DIMER DILINOLEATE,PARFUM (FRAGRANCE),CAPRYLYL GLYCOL,ETHYLHEXYLGLYCERIN,SODIUM DEHYDROACETATE,PENTYLENE GLYCOL,AQUA (WATER),BUTYLENE GLYCOL,PROPANEDIOL,MEL (HONEY),GLYCERIN,TOCOPHEROL,BUTYROSPERMUM PARKII SEEDCAKE EXTRACT,TIN OXIDE,+/- (MAY CONTAIN),CI 77891 (TITANIUM DIOXIDE),CI 77163 (BISMUTH OXYCHLORIDE),CI 77491, CI 77492, CI 77499 (IRON OXIDES),CI 73360 (RED 30 LAKE) | K30: BOÎTIER | L30: 10 g | M30: FRANCE | O30: 1
A31: PROBIOTIC EXFOLIATING POWDER FACE + SCALP | B31: BOSCIA | C31: boscia LLC | E31: CAPILLAIRE,SOIN VISAGE | F31: VISAGE,CUIR CHEVELU | G31: GOMMAGE,POUDRE | H31: TOUS TYPES DE CHEVEUX,CONVIENT AUX CHEVEUX COLORÉS | I31: Use up to 4x a week, or as needed. Face - Start with wet hands and face. Work a dime-sized amount of powder into hands to create a lather. Apply and gently massage face in a circular motion for 10 to 20 seconds. Scalp - Start with wet, unwashed hair. Work a quarter-sized amount of powder into wet hands to create a lather. Slide through hair using fingertips to massage into scalp. Leave on scalp for 3-5 minutes for further relief. Rinse and follow with shampoo/conditioner, as needed. Warning: For external use only. Use only as directed. Avoid contact with eyes. | J31: TAPIOCA STARCH,SODIUM COCOYL ISETHIONATE,ILLITE,SODIUM LAUROYL GLUTAMATE,POTASSIUM COCOYL GLYCINATE,WATER/AQUA/EAU,ORYZA SATIVA (RICE) GERM POWDER,KAOLIN,POTASSIUM CHLORIDE,MONTMORILLONITE,CHARCOAL POWDER,SALICYLIC ACID,CITRUS GRANDIS (GRAPEFRUIT) PEEL OIL,NIACINAMIDE,EUCALYPTUS GLOBULUS LEAF OIL,MALTODEXTRIN,COCONUT ACID,POTASSIUM COCOATE,SODIUM HYALURONATE,SODIUM STARCH OCTENYLSUCCINATE,CALCIUM PANTOTHENATE,SODIUM PHYTATE,ETHYLHEXYLGLYCERIN,SODIUM ASCORBYL PHOSPHATE,PYRIDOXINE HCL,TOCOPHERYL ACETATE,LACTOBACILLUS FERMENT,SILICA,GLYCERIN,TOCOPHEROL,CAMELLIA SINENSIS LEAF EXTRACT | K31: FLACON,CAPSULE SERVICE,RECHARGEABLE | L31: 60 g | M31: USA | O31: 0
A32: OH MY CREAM SKINCARE - BLUSH | B32: OH MY CREAM | C32: SAS OH MY CREAM | D32: OH MY CREAM SKINCARE | E32: MAQUILLAGE | F32: JOUES | G32: FARD À JOUES/BLUSH,POUDRE | H32: TOUS TYPES DE PEAUX | I32: À l’aide du Pinceau Blush, déposer la poudre sur le bombé des pommettes et estomper vers les tempes. Intensifier la couleur si nécessaire. | J32: INCI TEINTE "ROSE" : MICA,ZINC STEARATE,C12-15 ALKYL BENZOATE,LAUROYL LYSINE,SODIUM STARCH OCTENYLSUCCINATE,OCTYLDODECYL STEAROYL STEARATE,SILICA,CAPRYLIC/CAPRIC TRIGLYCERIDE,ETHYLHEXYLGLYCERIN,COCO-CAPRYLATE/CAPRATE,CALCIUM CARBONATE,TOCOPHERYL ACETATE,CARTHAMUS TINCTORIUS SEED OIL,ALOE BARBADENSIS LEAF EXTRACT,MAGNESIUM STEARATE,TOCOPHEROL,+/- (MAY CONTAIN),CI 45410 (RED 28 LAKE),CI 15850 (RED 6),CI 77492 (IRON OXIDES),CI 77491 (IRON OXIDES),CI 42090 (BLUE 1 LAKE),CI 77499 (IRON OXIDES) | K32: BOÎTIER | L32: 4 g | M32: FRANCE | O32: 1
A33: MAGIC POWDERS - NETTOYANT VISAGE - EXFOLIANT QUOTIDIEN EN POUDRE | B33: WAAM | C33: DIECE SAS | D33: MAGIC POWDERS | E33: SOIN VISAGE | F33: VISAGE | G33: DÉMAQUILLANT/NETTOYANT,POUDRE,ANHYDRE | H33: TOUS TYPES DE PEAUX | I33: 1. Verser une noisette dans votre main. 2. Ajouter quelques gouttes d'eau. 3. Masser votre visage pour le nettoyer. De très légers grains peuvent se faire ressentir pour une action micro-exfoliante. 4. Rincer. | J33: SODIUM COCOYL GLUTAMATE,ZEA MAYS (CORN) STARCH*,MICROCRYSTALLINE CELLULOSE,ORYZA SATIVA (RICE) POWDER*,ALTHAEA OFFICINALIS ROOT*,ZINC PCA,PARFUM (FRAGRANCE),ALOE BARBADENSIS LEAF POWDER* | K33: FLACON SALIÈRE,RECHARGEABLE | L33: 50 g | M33: FRANCE | N33: 3700851107589 | O33: 0
A34: [ L'APPEL DE LA FORÊT ] - LA POUDRE MAGIQUE ÉCLAT & JEUNESSE | B34: GARANCIA | C34: GARANCIA, INC | D34: [ L'APPEL DE LA FORÊT ] | E34: SOIN VISAGE | F34: VISAGE,COU | G34: SOIN,POUDRE | H34: TOUS TYPES DE PEAUX | I34: Déposez une cuillère doseuse de poudre remplie à ras dans le creux de votre main puis ajoutez 5 à 7 gouttes du sérum double phase L'APPEL DE LA FORÊT booster de vitamine C (pour augmenter de +50% son pouvoir antioxydant). Mixez le tout avec votre doigt, la poudre fond littéralement. Appliquez matin et soir sur le visage. | J34: DIATOMACEOUS EARTH,ASCORBIC ACID,MICROCRYSTALLINE CELLULOSE,GLYCERIN,INULIN,PINUS STROBUS BARK EXTRACT,NICOTIANA BENTHAMIANA HEXAPEPTIDE-40 SH-POLYPEPTIDE-47,MALTODEXTRIN,AQUA (WATER/EAU),PENTYLENE GLYCOL | K34: POT | L34: 6 g | M34: FRANCE | N34: 3700928802409 | O34: 0
A35: POUDRE COMPACTE CERTIFIÉ BIO ET VÉGAN | B35: JCH RESPECT | C35: SARL JCH International | E35: MAQUILLAGE | F35: VISAGE,COU | G35: POUDRE,COMPACT | H35: TOUTES CARNATIONS | I35: Après votre BB crème ou seule après votre crème de jour, prélevez votre poudre à l’aide votre pinceau poudre, tapotez légèrement votre pinceau pour enlever l’excèdent, avant de l’appliquer sur votre visage. Commencez par le front puis sur les joues en balayant toujours de l’intérieur vers l’extérieur. N’oubliez pas votre cou. | J35: MICA,ZEA MAYS STARCH/ZEA MAYS (CORN) STARCH*,ZINC STEARATE,OCTYLDODECANOL,SQUALANE,BENZYL ALCOHOL,LECITHIN,LIMONENE,PRUNUS AMYGDALUS DULCIS OIL*,BUTYROSPERMUM PARKII BUTTER*,PARFUM (FRAGRANCE),DEHYDROACETIC ACID,TOCOPHEROL,ASCORBYL PALMITATE,CITRUS AURANTIUM DULCIS PEEL OIL*,CITRIC ACID,LINALOOL,+/- (MAY CONTAIN),CI 77891 (TITANIUM DIOXIDE),CI 77492 (IRON OXIDES),CI 77491 (IRON OXIDES),CI 77499 (IRON OXIDES) | K35: BOÎTIER | L35: 9 g | M35: ITALIE | O35: 1
A36: ILLUMINATEUR CERTIFIÉ BIO ET VÉGAN | B36: JCH RESPECT | C36: SARL JCH International | E36: MAQUILLAGE | F36: VISAGE | G36: ENLUMINEUR,POUDRE | H36: TOUTES CARNATIONS | I36: Il s’applique en touche finale sur les parties bombées du visage. Débutez par les yeux, afin d’agrandir votre regard, déposez une touche d’illuminateur au niveau de l’arcade sourcilière, juste en dessous du sourcil et terminez par le coin interne de l’œil. Passez ensuite aux pommettes, balayez légèrement sur le haut de vos pommettes de l’intérieur vers l’extérieurs. Vous pouvez si vous souhaitez affiner votre nez, tracer une ligne le long de son arête. Appliquez une légère touche d’illuminateur dans le creux qui se situe entre votre lèvre supérieure et votre nez (l’arc de cupidon). | J36: MICA,ZEA MAYS STARCH/ZEA MAYS (CORN) STARCH*,CI 77891 (TITANIUM DIOXIDE),SQUALANE,CAPRYLIC/CAPRIC TRIGLYCERIDE,OCTYLDODECANOL,ZINC STEARATE,CI 77491 (IRON OXIDES),BENZYL ALCOHOL,LIMONENE,LECITHIN,PRUNUS AMYGDALUS DULCIS OIL*,BUTYROSPERMUM PARKII BUTTER*,PARFUM (FRAGRANCE),DEHYDROACETIC ACID,TOCOPHEROL,ASCORBYL PALMITATE,CITRUS AURANTIUM DULCIS PEEL OIL*,CITRIC ACID,LINALOOL | K36: BOÎTIER | L36: 9 g | M36: ITALIE | O36: 1
A37: SUPERIOR SERUM - CALM REVIVAL GREEN TEA RESVERATROL POWDER | B37: EXPONENT | C37: Exponent Beauty, Inc. | E37: SOIN VISAGE | F37: VISAGE | G37: SOIN,POUDRE | H37: TOUS TYPES DE PEAUX,CONVIENT AUX PEAUX SENSIBLES/RÉACTIVES | I37: UTILISATION - AVEC Calm Revival peut être utilisé le matin ou le soir. Appliquer sur une peau humide et propre et recouvrir d'une crème hydratante ou d'un SPF. - COMMENT Votre sérum est activé lorsqu'il est entièrement dissous, généralement dans les 8 secondes qui suivent la combinaison de la poudre active et de l'hydratant. - UN MÉLANGE FACILE Les poudres actives peuvent être utilisées de manière interchangeable dans notre activateur avec le même hydratant, ce qui vous permet de combiner facilement votre routine matin et soir. - UNE NOTE SUR LE NETTOYAGE Le resvératrol s'oxyde rapidement. Si vous laissez des résidus dans votre bol, il commencera à brunir en quelques heures. Pour éviter cela, après le dosage, rincez votre bol sous le robinet et laissez-le sécher à l'air libre. COMMENT ÇA MARCHE ? - DOSEZ-LE Retirez le capuchon en caoutchouc du distributeur. Placez votre Globe + distributeur sur le bol, côté distributeur vers le bas. Poussez doucement le Globe vers le bas et tournez-le dans le sens des aiguilles d'une montre. Vous entendrez quelques petits clics puis un "bruit sourd" à environ 90 degrés. - FOUETTEZ LE Soulever le couvercle pour révéler une dose de liquide et deux tas de poudre. Fouettez le tout pendant environ 5 secondes jusqu'à ce qu'il se transforme en un sérum crème-gel léger. Prélevez tout ce qu'il y a de bon et appliquez-le sur votre visage et votre cou. - NETTOYEZ-LE Votre bol peut être rapidement essuyé avec un mouchoir en papier entre deux utilisations ou rincé et laissé à sécher à l'air libre. | J37: BETAINE,DIMETHICONE CROSSPOLYMER,DIMETHICONE,SILICA,CALCIUM SILICATE,HYDROXYETHYL ACRYLATE/SODIUM ACRYLOYLDIMETHYL TAURATE COPOLYMER,EPIGALLOCATECHIN GALLATE,DISTARCH PHOSPHATE,WATER (AQUA),CITRIC ACID,RESVERATROL,ASIATICOSIDE,QUERCETIN,ALOE BARBADENSIS LEAF JUICE,BUTYROSPERMUM PARKII (SHEA) BUTTER,PHENOXYETHANOL,POTASSIUM SORBATE,ETHYLHEXYLGLYCERIN,ANTHEMIS NOBILIS (ROMAN CHAMOMILE) OIL,MICA,TITANIUM DIOXIDE (CI 77891) | K37: POT,RECHARGEABLE | L37: 6 g | M37: USA | O37: 0
A38: PLEIN AIR - POUDRE ÉCLAT RAYONNANT | B38: HERMÈS | C38: HERMÈS INTERNATIONAL | D38: PLEIN AIR | E38: MAQUILLAGE | F38: JOUES | G38: FARD À JOUES/BLUSH,POUDRE,COMPACT | H38: TOUS TYPES DE PEAUX,TOUTES CARNATIONS | I38: Appliquez la poudre éclat rayonnant sur peau nue ou après le rituel de teint pour illuminer les pommettes, les tempes, l'arête du nez ou l'arc de Cupidon, au doigt ou à l'aide du pinceau fard à joues Rose Hermès. | J38: MICA,SQUALANE,OCTYLDODECYL STEAROYL STEARATE,GLYCERIN,SILICA,HDI/TRIMETHYLOL HEXYLLACTONE CROSSPOLYMER,ZINC STEARATE,KAOLIN,SYNTHETIC FLUORPHLOGOPITE,PENTYLENE GLYCOL,CAPRYLYL GLYCOL,DICALCIUM PHOSPHATE,SORBITAN SESQUIISOSTEARATE,PARFUM (FRAGRANCE),SODIUM DEHYDROACETATE,CAPRYLIC/CAPRIC TRIGLYCERIDE,TOCOPHEROL,TOCOPHERYL ACETATE,CHONDRUS CRISPUS POWDER,XANTHAN GUM,MORUS ALBA BARK EXTRACT,BENZYL SALICYLATE,LIMONENE,GERANIOL,CITRONELLOL,LINALOOL,HYDROXYCITRONELLAL,CI 77891 (TITANIUM DIOXIDE),CI 77491 (IRON OXIDES) | K38: BOÎTIER,RECHARGEABLE | L38: 8,5 g | M38: ITALIE | N38: 3346130412212 | O38: 1
A39: TERRACOTTA LIGHT - LA POUDRE ÉCLAT BONNE MINE NATURELLE | B39: GUERLAIN | C39: LVMH | D39: TERRACOTTA | E39: MAQUILLAGE | F39: VISAGE,COU | G39: ENLUMINEUR,POUDRE | H39: TOUTES CARNATIONS | I39: LE MOT DE VIOLETTE, DIRECTRICE DE LA CRÉATION DU MAQUILLAGE GUERLAIN : « MON SECRET POUR UN EFFET SUN-KISSED IRRÉSISTIBLE ? APPLIQUER LA TERRACOTTA SUR LES ZONES LES PLUS BOMBÉES COMME LES POMMETTES, L’ARÊTE DU NEZ ET LE HAUT DU FRONT POUR APPORTER PLUS DE STRUCTURE AU VISAGE TOUT EN RÉCHAUFFANT DÉLICATEMENT LE TEINT. » | J39: MICA,SILICA,LAUROYL LYSINE,ZINC STEARATE,BIS-BEHENYL/ISOSTEARYL/PHYTOSTERYL DIMER DILINOLEYL DIMER DILINOLEATE,OCTYLDODECYL STEAROYL STEARATE,DICAPRYLYL ETHER,CELLULOSE,CALCIUM SODIUM BOROSILICATE,DIMER DILINOLEYL DIMER DILINOLEATE,KAOLIN,PARFUM (FRAGRANCE),CAPRYLYL GLYCOL,ETHYLHEXYLGLYCERIN,SODIUM DEHYDROACETATE,PENTYLENE GLYCOL,AQUA (WATER),BUTYLENE GLYCOL,PROPANEDIOL,MEL (HONEY),GLYCERIN,TOCOPHEROL,TIN OXIDE,BUTYROSPERMUM PARKII SEEDCAKE EXTRACT,+/- (MAY CONTAIN),CI 77891 (TITANIUM DIOXIDE),CI 77163 (BISMUTH OXYCHLORIDE),CI 77491, CI 77492, CI 77499 (IRON OXIDES),CI 73360 (RED 30 LAKE) | K39: BOÎTIER | L39: 10 g | M39: FRANCE | N39: 3346470435612 | O39: 1
A40: PRISME LIBRE PRESSED POWDER - POUDRE FIXATRICE MATIFIANTE & FLOUTANTE | B40: GIVENCHY | C40: LVMH | D40: PRISME LIBRE | E40: MAQUILLAGE | F40: VISAGE | G40: POUDRE,COMPACT | H40: TOUTES CARNATIONS | I40: La poudre compacte Prisme Libre Pressed Powder s'applique seule pour matifier le teint ou après le fond de teint pour fixer et sculpter le maquillage. LA PERFECTION MATE EN 3 ÉTAPES PRISMATIQUES 1. MÉLANGER les 4 couleurs avec le pinceau pour un résultat homogène. 2. APPLIQUER la poudre du centre vers l'extérieur en privilégiant la zone T, ou sur l'ensemble du visage pour un fini mat modulable. 3. ESTOMPER sur la peau pour créer le parfait look mat et lumineux à l'effet floutant. | J40: TALC,SYNTHETIC FLUORPHLOGOPITE,SILICA,ZINC STEARATE,DIMETHICONE,DIISOSTEARYL MALATE,OCTYLDODECYL STEAROYL STEARATE,CAPRYLYL GLYCOL,PENTYLENE GLYCOL,PHENYL TRIMETHICONE,SODIUM DEHYDROACETATE,PARFUM (FRAGRANCE),SORBITAN SESQUIOLEATE,TOCOPHERYL ACETATE,HYDROLYZED SERICIN,KAOLIN,+/- (MAY CONTAIN),CI 77891 (TITANIUM DIOXIDE),CI 77007 (ULTRAMARINES),CI 77491, CI 77492 (IRON OXIDES),CI 19140 (YELLOW 5 LAKE),CI 77742 (MANGANESE VIOLET),CI 15850 (RED 6),CI 42090 (BLUE 1 LAKE),CI 73360 (RED 30 LAKE) | K40: BOÎTIER | L40: 9,5 g | M40: ITALIE | O40: 1
A41: KIND & FREE - POUDRE BONNE MINE | B41: RIMMEL LONDON | C41: BENCKISER | D41: KIND & FREE | E41: MAQUILLAGE | F41: VISAGE | G41: POUDRE/SPRAY DE FINITION,COMPACT | H41: CONVIENT AUX PEAUX SENSIBLES/RÉACTIVES,TOUS TYPES DE PEAUX | I41: Prélever une petite quantité de poudre avec le pinceau ou à l'aide de la houpette, puis l’appliquer sur les zones du visage que vous souhaitez matifier, habituellement le front, le nez et le menton. | J41: INCI TEINTE 01 TRANSLUCENT : MICA,KAOLIN,ZINC STEARATE,AVENA SATIVA (OAT) KERNEL FLOUR,OCTYLDODECYL STEAROYL STEARATE,TAPIOCA STARCH,ISOPROPYL PALMITATE,CALCIUM SILICATE,DIMETHICONE,AQUA/WATER/EAU,1,2-HEXANEDIOL,CAPRYLYL GLYCOL,PHENOXYETHANOL,SORBITAN SESQUIOLEATE,ALOE BARBADENSIS LEAF JUICE,+/- (MAY CONTAIN),IRON OXIDES (CI 77491, CI 77492, CI 77499),TITANIUM DIOXIDE (CI 77891) | K41: BOÎTIER | L41: 10 g | M41: U.K. | O41: 1
A42: LE FARD À JOUES LUMIÈRE D'OCRES | B42: LA PROVENÇALE BIO | C42: L'ORÉAL | E42: MAQUILLAGE | F42: JOUES | G42: FARD À JOUES/BLUSH,POUDRE | H42: TOUS TYPES DE PEAUX,TOUTES CARNATIONS | I42: Appliquer par petites touches à l'aide d'un pinceau en haut des pommettes et le long de la joue. | J42: TALC,ZEA MAYS STARCH/CORN STARCH,COCOS NUCIFERA OIL/COCONUT OIL,PENTYLENE GLYCOL,MAGNESIUM STEARATE,GLYCERYL CAPRYLATE,SILICA,PARFUM/FRAGRANCE,OLEA EUROPAEA FRUIT OIL/OLIVE FRUIT OIL,LINALOOL,BENZYL ALCOHOL,CITRONELLOL,GERANIOL,EUGENOL,+/- (MAY CONTAIN),MICA,CI 77891/TITANIUM DIOXIDE,CI 77491/IRON OXIDES,CI 75470/CARMINE,CI 77007/ULTRAMARINES | K42: BOÎTIER | L42: 8 g | M42: ITALIE | N42: 3600551058566 | O42: 1
A43: LA POUDRE DE TEINT LUMIÈRE D'OCRES | B43: LA PROVENÇALE BIO | C43: L'ORÉAL | E43: MAQUILLAGE | F43: VISAGE | G43: ENLUMINEUR,POUDRE | H43: TOUS TYPES DE PEAUX,TOUTES CARNATIONS | I43: Appliquer avec un pinceau sur l'ensemble du visage pour un résultat naturel lumineux. | J43: TALC,ZEA MAYS STARCH/CORN STARCH,COCOS NUCIFERA OIL/COCONUT OIL,PENTYLENE GLYCOL,MAGNESIUM STEARATE,GLYCERYL CAPRYLATE,PARFUM/FRAGRANCE,OLEA EUROPAEA FRUIT OIL/OLIVE FRUIT OIL,LINALOOL,BENZYL ALCOHOL,CITRONELLOL,GERANIOL,EUGENOL,+/- (MAY CONTAIN),CI 77491, CI 77492, CI 77499/IRON OXIDES,MICA,CI 77891/TITANIUM DIOXIDE | K43: BOÎTIER | L43: 8 g | M43: ITALIE | N43: 3600551058627 | O43: 1
A44: N°1 DE CHANEL - POUDRE DE MOUSSE NETTOYANTE AU CAMÉLIA ROUGE | B44: CHANEL | C44: GROUPE CHANEL | D44: N°1 DE CHANEL | E44: SOIN VISAGE | F44: VISAGE | G44: DÉMAQUILLANT/NETTOYANT,POUDRE | H44: TOUS TYPES DE PEAUX,CONVIENT AUX PEAUX SENSIBLES/RÉACTIVES | I44: La poudre de mousse est le soin parfait pour retirer le maquillage tel que le fond de teint N°1 DE CHANEL. Pour ouvrir votre flacon, tournez délicatement la capsule Twist and Slide dans le sens inverse des aiguilles d’une montre. Déposer l’équivalent d’1/2 cuillère à café de poudre dans le creux de la main. Ajouter quelques gouttes d’eau pour obtenir une mousse généreuse. Répartir la mousse nettoyante sur le menton, les joues et le front. Réaliser des mouvements circulaires sur le menton et remonter vers les joues puis vers le front en évitant le contour des yeux. Rincer soigneusement la mousse à l’eau tiède. Bien refermer en tournant dans le sens des aiguilles d’une montre. Garder dans un endroit sec. Poursuivre avec les autres soins N°1 DE CHANEL : la lotion, la crème yeux, le sérum et la crème. | J44: ORYZA SATIVA (RICE) STARCH,SODIUM LAUROYL GLUTAMATE,DISODIUM COCOYL GLUTAMATE,SODIUM CHLORIDE,XANTHAN GUM,CAMELLIA JAPONICA SEED OIL,CAMELLIA JAPONICA FLOWER EXTRACT,HYDROLYZED RHODOPHYCEAE EXTRACT,AQUA (WATER),PARFUM (FRAGRANCE),POTASSIUM SORBATE,PROPANEDIOL,MARIS SAL (SEA SALT),1,2-HEXANEDIOL,CAPRYLYL GLYCOL | K44: FLACON,CAPSULE TWIST AND SLIDE | L44: 25 g | M44: FRANCE | N44: 3145891406306 | O44: 0
A45: BLUSH LUMIÈRE | B45: CHANEL | C45: GROUPE CHANEL | D45: COLLECTION PRINTEMPS-ÉTÉ 2022 LA PAUSA DE CHANEL | E45: MAQUILLAGE | F45: JOUES | G45: FARD À JOUES/BLUSH,POUDRE | H45: TOUTES CARNATIONS | I45: Vous pouvez appliquer le BLUSH LUMIÈRE sur les joues, les pommettes, les tempes. Selon le résultat souhaité, vous pouvez : Travailler le BLUSH LUMIÈRE sur les pommettes pour un résultat naturel. Travailler le BLUSH LUMIÈRE sur les pommettes et les joues pour un résultat solaire, lumineux et bonne mine. Travailler le BLUSH LUMIÈRE sur les pommettes, les joues et les tempes, vous obtiendrez un look plus intense qui marquera vos contours. Le BLUSH LUMIÈRE peut être appliqué au-dessus du BAUME ESSENTIEL pour un effet frais et lumineux. Le pinceau demi-lune intégré est excellent pour appliquer cette poudre crémeuse. Utiliser le côté plat pour appliquer sur de plus grandes surfaces et le bord pour les petits détails, comme l'arête du nez pour un effet bonne mine et ensoleillé. Un côté du pinceau peut être utilisé pour appliquer la texture et l'autre pour l'estomper. | J45: INCI TEINTE PÊCHE ROSÉE : CELLULOSE,DICAPRYLYL CARBONATE,DIMETHICONE,SYNTHETIC FLUORPHLOGOPITE,MAGNESIUM STEARATE,RICINUS COMMUNIS (CASTOR) SEED OIL,LAURYL PEG-9 POLYDIMETHYLSILOXYETHYL DIMETHICONE,ALUMINUM HYDROXIDE,HYDROGENATED CASTOR OIL,CHLORPHENESIN,HYDROGEN DIMETHICONE,TIN OXIDE,TOCOPHEROL,SILICA,+/- (MAY CONTAIN),CI 12085 (RED 36),CI 15850 (RED 6),CI 15850 (RED 7 LAKE),CI 15880 (RED 34),CI 15985 (YELLOW 6 LAKE),CI 17200 (RED 33 LAKE),CI 19140 (YELLOW 5 LAKE),CI 42090 (BLUE 1 LAKE),CI 45380 (RED 22 LAKE),CI 45410 (RED 28 LAKE),CI 73360 (RED 30 LAKE),CI 77007 (ULTRAMARINES),CI 77163 (BISMUTH OXYCHLORIDE),CI 77491, CI 77492, CI 77499 (IRON OXIDES),CI 77510 (FERRIC FERROCYANIDE),CI 77742 (MANGANESE VIOLET),CI 77891 (TITANIUM DIOXIDE),MICA | K45: BOÎTIER | L45: 14 g | M45: FRANCE | N45: 3145891517675 | O45: 1
A46: CLARIFYING FACIAL POLISH | B46: NATURE OF THINGS | C46: QOA LLC | E46: SOIN VISAGE | F46: VISAGE,COU | G46: GOMMAGE,POUDRE,DÉMAQUILLANT/NETTOYANT | H46: TOUS TYPES DE PEAUX | I46: Versez 1/2 cuillère à café de poudre dans le creux de votre main. Ajoutez quelques gouttes d'eau et mélangez jusqu'à obtenir une consistance crémeuse. (Conseil : utilisez moins d'eau pour un effet exfoliant plus fort, plus pour un effet plus doux). Massez délicatement le visage et le cou en effectuant des mouvements circulaires. Évitez le contour des yeux. Rincez à l'eau tiède. Pour de meilleurs résultats, utilisez ensuite l’Essence Equilibrante afin de rééquilibrer le pH et obtenir de l'éclat. | J46: MICROCRYSTALLINE CELLULOSE,ORYZA SATIVA (RICE) POWDER,SODIUM COCOYL ISETHIONATE,AVENA SATIVA (OAT) KERNEL EXTRACT,SOLUM DIATOMEAE/DIATOMACEOUS EARTH,ORYZA SATIVA (RICE) STARCH,SODIUM LAUROYL GLUTAMATE,COCONUT ACID,COLLOIDAL OATMEAL,SODIUM ISETHIONATE,CLAY,VOLCANIC ASH,NIACINAMIDE,SILICA,PAPAIN,BROMELAIN,OLEA EUROPAEA (OLIVE) FRUIT EXTRACT,XYLITOL,MENTHA ARVENSIS LEAF OIL,EUCALYPTUS GLOBULUS LEAF OIL,PCA,LACTIC ACID,SALICYLIC ACID,AQUA/WATER/EAU,POTASSIUM SORBATE | K46: FLACON,CAPSULE SERVICE | L46: 45 g | M46: USA | N46: 0400017161726 | O46: 0
A47: HOLLYWOOD GLOW GLIDE FACE ARCHITECT HIGHLIGHTER | B47: CHARLOTTE TILBURY | C47: CHARLOTTE TILBURY BEAUTY LTD. | E47: MAQUILLAGE | F47: VISAGE,LÈVRES,SOURCILS,NEZ,YEUX | G47: ENLUMINEUR,POUDRE | H47: TOUS TYPES DE PEAUX,PEAUX CLAIRES À MEDIUMS,PEAUX CLAIRES,PEAUX MEDIUMS | I47: GUIDE POUR UN TEINT ÉCLATANT DE CHARLOTTE ! 6 FAÇONS DE L'UTILISER... L'ASTUCE POMMETTES... POUR UN EFFET LIFTANT ! Appliquez votre teinte préférée de Hollywood Glow Glide Face Architect Highlighter des POMMETTES JUSQU'AUX TEMPES en estompant vers l'arrière et l'avant pour un effet liftant instantané ! L'ASTUCE MÂCHOIRE… POUR SCULPTER ! Appliquez le long de la MÂCHOIRE à l'aide du pinceau Powder & Sculpt Brush pour une application précise en évitant toujours le menton ! Vous sculpterez ainsi les traits de votre visage en un instant ! L'ASTUCE YEUX… POUR OUVRIR ET ILLUMINER LE REGARD ! Appliquez dans le COIN INTERNE DE L'ŒIL, AU CENTRE DE LA PAUPIÈRE et le long de la LIGNE INFÉRIEURE DES CILS en soulignant le centre pour illuminer et agrandir votre regard ! Utilisez le pinceau Smudger Brush pour une application plus précise, uniquement sur les zones que vous souhaitez illuminer ! L'ASTUCE NEZ… POUR DÉFINIR ET SCULPTER ! Charlotte appelle cette technique le point d'exclamation ! Commencez par l'arête et appliquez sur le CENTRE DU NEZ puis tapotez sur le bout du nez, comme un point ! Estompez du bout des doigts. L'ASTUCE SOURCILS… POUR UN REGARD À EFFET LIFTÉ ! Appliquez sous l'arcade sourcilière pour un effet liftant instantané ! Vous pouvez également tapoter au-dessus du centre de votre sourcil pour un effet encore plus intense ! L'ASTUCE LÈVRES... POUR UNE MOUE PULPEUSE ! Appliquez votre highlighter sur la ligne supérieure des lèvres en vous concentrant sur l'ARC DE CUPIDON pour ne pas aller trop haut ! Cette astuce vous permet d'obtenir des lèvres plus pulpeuses et plus généreuses ! Conseils Tilbury : EN JOURNÉE : appliquez sur la peau pour un ÉCLAT ZÉRO DÉFAUT MULTIDIMENSIONNEL ! EN SOIRÉE : appliquez à l'aide d'un PINCEAU HUMIDE pour un résultat PLUS INTENSE ! | J47: INCI TEINTE CHAMPAGNE GLOW : MICA,TALC,SQUALANE,DIISOSTEARYL MALATE,BORON NITRIDE,HDI/TRIMETHYLOL HEXYLLACTONE CROSSPOLYMER,ZEA MAYS (CORN) STARCH,DIMETHICONE,CAPRYLYL GLYCOL,ETHYLHEXYLGLYCERIN,ZINC STEARATE,DIMETHICONOL,SILICA,MALTODEXTRIN,TIN OXIDE,+/- (MAY CONTAIN),TITANIUM DIOXIDE (CI 77891),IRON OXIDES (CI 77491),YELLOW 5 LAKE (CI 19140),CARMINE (CI 75470) | K47: BOÎTIER | L47: 7 g | M47: ITALIE | N47: 5056446610964 | O47: 1
A48: ALWAYS FABULOUS - SHINE CONTROL MATTE POWDER | B48: BOURJOIS | C48: COTY GROUP INC | D48: ALWAYS FABULOUS | E48: MAQUILLAGE | F48: VISAGE | G48: POUDRE/SPRAY DE FINITION,FOND DE TEINT,POUDRE,COMPACT | H48: TOUTES CARNATIONS | I48: Appliquez d'abord la poudre matifiante sur la zone T, puis sur l'ensemble du visage si nécessaire, pour un teint matifié. | J48: TALC,MICA,POLYETHYLENE,HDI/TRIMETHYLOL HEXYLLACTONE CROSSPOLYMER,OCTYLDODECYL STEAROYL STEARATE,PPG-51/SMDI COPOLYMER,DIMETHICONE,PHENYL TRIMETHICONE,SILICA,AMODIMETHICONE,TRIMETHYLSILOXYSILICATE,METHYLPARABEN,LECITHIN,PHENOXYETHANOL,LAUROYL LYSINE,PROPYLPARABEN,PARFUM/FRAGRANCE,ETHYLPARABEN,EUTERPE OLERACEA JUICE,PUNICA GRANATUM FRUIT JUICE,SAPPHIRE POWDER,VITIS VINIFERA (GRAPE) JUICE,GERANIOL,LINALOOL,KAOLIN,+/- (MAY CONTAIN),IRON OXIDES (CI 77491, CI 77492, CI 77499),TITANIUM DIOXIDE (CI 77891),BISMUTH OXYCHLORIDE (CI 77163),ULTRAMARINES (CI 77007) | K48: BOÎTIER | L48: 10 g | O48: 1
A49: POUDRE PURIFIANTE 3 EN 1 À LA MENTHE BIO ET ARGILE | B49: KLORANE | C49: GROUPE PIERRE FABRE | D49: MENTHE AQUATIQUE | E49: SOIN VISAGE | F49: VISAGE | G49: DÉMAQUILLANT/NETTOYANT,POUDRE | H49: PEAUX MIXTES À GRASSES,PEAUX MIXTES,PEAUX GRASSES | I49: FRÉQUENCE D’UTILISATION : Quotidien. 1 - VERSER Verser un peu de poudre au creux de la main préalablement humidifiée. 2 - FROTTER Frictionner vos mains jusqu'à faire apparaitre une mousse légère et aérienne. 3 - APPLIQUER Appliquer en mouvements circulaires sur l'ensemble du visage et rincer abondamment à l’eau claire. Pour un effet plus "gommant" : verser plus de poudre au creux de la main en y ajoutant moins d'eau, pour sentir davantage les grains sur la peau. Le faire ponctuellement pour ne pas sursolliciter la peau. Rincer abondamment. | J49: ZEA MAYS (CORN) STARCH,SODIUM COCOYL GLUTAMATE,CLAY,SODIUM COCOYL ISETHIONATE,PERLITE,ACACIA SENEGAL GUM,MENTHA AQUATICA FLOWER/LEAF/STEM EXTRACT*,CITRIC ACID,COCONUT ACID,FRAGRANCE (PARFUM),LIMONENE,LINALOOL,PROPANEDIOL,WATER (AQUA),XANTHAN GUM | K49: FLACON,CAPSULE SERVICE | L49: 50 g | M49: FRANCE | O49: 0
A50: FOND DE TEINT MINÉRAL SPF 15 | B50: MADEMOISELLE BIO | C50: BIO DOO SASU | E50: MAQUILLAGE | F50: VISAGE | G50: FOND DE TEINT,POUDRE | H50: TOUS TYPES DE PEAUX,CONVIENT AUX PEAUX SENSIBLES/RÉACTIVES | I50: Déposer une petite quantité de fond de teint minéral à l'intérieur du couvercle. Tourner le Grand Pinceau Poudre à l'intérieur pour prélever la poudre et écraser les pigments. Tapoter votre pinceau pour enlever le surplus. Appliquer sur la peau par mouvements circulaires de l'intérieur du visage vers l'extérieur. Pour les peaux grasses ou mixtes, appliquer d’abord une base lissante pour une tenue optimale. | J50: SILICA,ZEA MAYS (CORN) STARCH*,ORYZA SATIVA (RICE) POWDER*,MICA,TITANIUM DIOXIDE,ZINC OXIDE,JOJOBA ESTERS,BENZYL ALCOHOL,PARFUM,BAMBUSA ARUNDINACEA STEM POWDER,HYALURONIC ACID,DEHYDROACETIC ACID,LECITHIN,TOCOPHEROL,ASCORBYL PALMITATE,CITRIC ACID,+/- (MAY CONTAIN),CI 77891 (TITANIUM DIOXIDE),CI 77491, CI 77492, CI 77499 (IRON OXIDES) | K50: BOÎTIER | L50: 10 g | O50: 1
A51: AC CLEAN UP - PINK POWDER SPOT - NOUVELLE FORMULE 2021 | B51: ETUDE HOUSE | C51: AMOREPACIFIC Corp. | E51: SOIN VISAGE | F51: VISAGE | G51: SOIN,BI-PHASE,LOTION,POUDRE | H51: PEAUX À IMPERFECTIONS,PEAUX À TENDANCE ACNÉIQUE | I51: Sans agiter le flacon, tremper un coton-tige dans le flacon, prélever de la poudre au fond et en appliquer sur les boutons. - Pour usage externe seulement. - Eviter les yeux. - Ne pas laisser en présence d'enfants. - Arrêter l'usage si des signes d'irritations apparaissent. | J51: ALCOHOL DENAT.,GLYCERIN,CALAMINE,CHAMAECYPARIS OBTUSA WATER,TITANIUM DIOXIDE (CI 77891),BUTYLENE GLYCOL,COLLOIDAL SULFUR,ALCOHOL,PORTULACA OLERACEA EXTRACT,SALICYLIC ACID,WATER\AQUA\EAU,1,2-HEXANEDIOL,DIPOTASSIUM GLYCYRRHIZATE,IRON OXIDES (CI 77491),MELALEUCA ALTERNIFOLIA (TEA TREE) LEAF OIL,HOUTTUYNIA CORDATA EXTRACT,SILICA,MADECASSOSIDE,ETHYLHEXYLGLYCERIN,SAURURUS CHINENSIS EXTRACT | K51: FLACON | L51: 15 ml | M51: CORÉE | N51: 8809667983242 | O51: 0
A52: COULEURS NATURE - POUDRE DE TEINT | B52: YVES ROCHER | C52: GROUPE ROCHER | D52: COULEURS NATURE | E52: MAQUILLAGE | F52: VISAGE | G52: FOND DE TEINT,POUDRE | H52: TOUS TYPES DE PEAUX,TOUTES CARNATIONS | I52: Prélevez la poudre à l'aide de la houppette ou d'un pinceau poudre, et enlevez le surplus en tapotant légèrement l'accessoire. Appliquez ensuite sur l'ensemble du visage en insistant plus particulièrement sur la zone T : le front, le nez, et le menton. | J52: TALC,NYLON-12,SYNTHETIC FLUORPHLOGOPITE,ZEA MAYS (CORN) STARCH,DIMETHICONE,ZINC STEARATE,PENTYLENE GLYCOL,DIISOSTEARYL MALATE,OCTYLDODECYL STEAROYL STEARATE,CAPRYLYL GLYCOL,SODIUM DEHYDROACETATE,BAMBUSA ARUNDINACEA JUICE,ORYZA SATIVA (RICE) HULL POWDER,TOCOPHERYL ACETATE,+/- (MAY CONTAIN),CI 15850 (RED 7 LAKE),CI 19140 (YELLOW 5 LAKE),CI 73360 (RED 30 LAKE),CI 77007 (ULTRAMARINES),CI 77491 (IRON OXIDES),CI 77492 (IRON OXIDES),CI 77499 (IRON OXIDES),KAOLIN | K52: BOÎTIER | L52: 10 g | M52: FRANCE | O52: 1
A53: AC COLLECTION - BLEMISH SPOT DRYING LOTION | B53: COSRX | C53: COSRX. Inc | D53: AC COLLECTION | E53: SOIN VISAGE | F53: VISAGE | G53: SOIN,BI-PHASE,LOTION,POUDRE | H53: PEAUX À IMPERFECTIONS,PEAUX À TENDANCE ACNÉIQUE | I53: Dip the silicon swab into the jar and dab onto the problematic spot. Do not shake the jar. Simply wash the swab under running water and keep it in the pouch to reuse. | J53: ALCOHOL,CALAMINE,WATER,GLYCERIN,ZINC OXIDE,TITANIUM DIOXIDE,SALIX NIGRA (WILLOW) BARK EXTRACT,DIMETHYL SULFONE,SILICA,SALICYLIC ACID,COLLOIDAL SULFUR,CAMPHOR,CYANOCOBALAMIN,MADECASSIC ACID,ASIATICOSIDE,ASIATIC ACID | K53: FLACON | L53: 30 ml | M53: CORÉE | N53: 8809598454101 | O53: 0
A54: PRITIPOLISH - INSTANT GLOW EXFOLIATOR | B54: PRAKTI | C54: Prakti Beauty | E54: SOIN VISAGE | F54: VISAGE | G54: GOMMAGE,POUDRE | H54: TOUS TYPES DE PEAUX | I54: Mix one spoonful of powder with a few drops of water, using less water for deeper exfoliation. Massage over face and rinse for instant glow. Polish every few days for the ultimate glow. | J54: MICROCRYSTALLINE CELLULOSE,ORYZA SATIVA (RICE) STARCH,XANTHAN GUM,LAUROYL LYSINE,MALTODEXTRIN,ORYZA SATIVA (RICE) POWDER,HELIANTHUS ANNUUS (SUNFLOWER) SEED OIL*,LACTOBACILLUS/PUNICA GRANATUM FRUIT FERMENT EXTRACT,OENOTHERA BIENNIS (EVENING PRIMROSE) OIL*,VETIVERIA ZIZANOIDES ROOT OIL*,ARNICA MONTANA FLOWER EXTRACT,HYDROLYZED GARDENIA FLORIDA EXTRACT,ROSA DAMASCENA FLOWER OIL,LEUCONOSTOC FERMENT FILTRATE,GERANIOL,CITRONELLOL | K54: POT | L54: 30 g | M54: USA | N54: 0051497273095 | O54: 0
A55: BIG BRONZER INFINITE SUN EDITION - POUDRE BRONZANTE VISAGE & CORPS | B55: NOCIBÉ | C55: NOCIBÉ FRANCE DISTRIBUTION SAS | E55: MAQUILLAGE | F55: VISAGE,COU,BUSTE/DÉCOLLETÉ,CORPS | G55: POUDRE BRONZANTE,COMPACT | H55: TOUTES CARNATIONS | I55: Appliquez-le Big Bronzer avec un gros pinceau poudre ou un kabuki tout doux sur les joues, le front et le menton pour sculpter les traits de votre visage. Prolongez jusqu’au cou et au décolleté pour un effet bonne mine naturel. | J55: INCI BRONZING POWDER AND BLUSH : TALC,MICA,CAPRYLIC/CAPRIC TRIGLYCERIDE,ZINC STEARATE,DIMETHICONE,LAUROYL LYSINE,ETHYLHEXYLGLYCERIN,DEHYDROACETIC ACID,STEARIC ACID,TOCOPHEROL,+/- (MAY CONTAIN),CI 15850,CI 19140,CI 77491, CI 77492, CI 77499 (IRON OXIDES),CI 77891 (TITANIUM DIOXIDE) | K55: BOÎTIER | L55: 18 g | M55: ITALIE | O55: 1
A56: GLOWISH - SOFT RADIANCE BRONZING POWDER | B56: HUDA BEAUTY | C56: HB USA Holdings, Inc. | D56: GLOWISH | E56: MAQUILLAGE | F56: VISAGE | G56: POUDRE BRONZANTE,COMPACT | H56: TOUS TYPES DE PEAUX,TOUTES CARNATIONS | I56: For a Sun-Kissed, Radiant Glow: Swirl a bronzer brush onto the powder and sweep across the face to add warmth. For best results, apply with our All Over Bronze Brush! | J56: LIGHT SHADE INGREDIENTS LISTING : MICA,SILICA,CETEARYL ETHYLHEXANOATE,ZINC STEARATE,DIMETHICONE,DODECANE,SUCROSE ACETATE ISOBUTYRATE,ROSA DAMASCENA FLOWER OIL,CAPSICUM ANNUUM EXTRACT,BUTYROSPERMUM PARKII (SHEA) BUTTER,HELIANTHUS ANNUUS (SUNFLOWER) SEED OIL,TOCOPHEROL,GLYCERIN,SQUALENE,ETHYLHEXYLGLYCERIN,CITRONELLYL METHYLCROTONATE,TRIETHYLHEXANOIN,C30-45 ALKYL DIMETHICONE,PHENYLISOPROPYL DIMETHICONE,CETYL PEG/PPG-10/1 DIMETHICONE,SORBITAN SESQUIOLEATE,DIMETHICONOL,BETA-SITOSTEROL,SODIUM BENZOATE,CITRIC ACID,SODIUM SALICYLATE,XANTHAN GUM,IRON OXIDES (CI 77491),IRON OXIDES (CI 77492),IRON OXIDES (CI 77499),TITANIUM DIOXIDE (CI 77891) | K56: BOÎTIER | L56: 8 g | O56: 1
A57: MASQUE POUDRE REVITALISANT | B57: YANNE WELLNESS | C57: AMCAN, SARL | E57: SOIN VISAGE | F57: VISAGE,COU,BUSTE/DÉCOLLETÉ | G57: MASQUE,SOIN,POUDRE | H57: TOUS TYPES DE PEAUX | I57: Verser 80 ml d’eau dans un petit bol. Saupoudrer uniformément la poudre sur toute la surface de l’eau. Laisser gonfler quelques secondes, puis mélanger doucement. La texture se transforme en un gel bleu léger et aérien. Appliquer immédiatement, avec l’aide d’un pinceau, sur l’ensemble du visage, du cou et du décolleté. Laisser poser 15 minutes. Retirer l’excédent avec un linge humide, de préférence tiède, pour une double action sur la peau. | J57: SODIUM CARBOXYMETHYL STARCH,HYDRATED SILICA,AQUA (WATER/EAU),PROPYLENE GLYCOL,SARGASSUM MUTICUM EXTRACT,DURVILLAEA ANTARCTICA EXTRACT,PARFUM (FRAGRANCE),HIPPOPHAE RHAMNOIDES OIL,BUTYLENE GLYCOL,CI 42090 (BLUE 1),HELIANTHUS ANNUUS (SUNFLOWER) SEED OIL,ROSMARINUS OFFICINALIS (ROSEMARY) LEAF EXTRACT | K57: EMBALLAGE SACHET/CARTON | L57: 10 unités | M57: FRANCE | O57: 0
A58: POUDRE NETTOYANTE POUR LE VISAGE À LA COQUILLE D'HUITRE BLANCHE | B58: PERLUCINE | C58: Entre Mer et Terre SA | E58: SOIN VISAGE | F58: VISAGE | G58: DÉMAQUILLANT/NETTOYANT,POUDRE,ANHYDRE | H58: TOUS TYPES DE PEAUX | I58: - Saupoudrer la poudre nettoyante visage dans le creux de votre main. - Ajouter quelques gouttes d’eau et frotter vos mains entre elles. - Une crème moussante onctueuse apparait. - Massez-vous le visage par mouvements circulaires pour bien le nettoyer. - Rincer à l’eau claire. - Eviter le contact avec les yeux. | J58: OSTREA SHELL POWDER,SODIUM LAUROYL GLUTAMATE,SODIUM MYRISTOYL GLUTAMATE,XANTHAN GUM | K58: TUBE,RECHARGEABLE | L58: 40 g | M58: FRANCE | O58: 0
A59: TEINT DIVIN - BLUSH BONNE MINE | B59: SO'BIO ETIC | C59: GROUPE LÉA NATURE | D59: TEINT DIVIN | E59: MAQUILLAGE | F59: JOUES | G59: FARD À JOUES/BLUSH,COMPACT | H59: TOUS TYPES DE PEAUX,TOUTES CARNATIONS,CONVIENT AUX PEAUX SENSIBLES/RÉACTIVES | I59: Pour un effet bonne mine, déposer le blush bonne mine certifié bio SO’BiO étic® en formant une virgule : partir des tempes en redescendant sur les pommettes. | J59: MICA,CALCIUM CARBONATE,TAPIOCA STARCH*,HELIANTHUS ANNUUS (SUNFLOWER) SEED OIL*,KAOLIN,LAUROYL LYSINE,HYDROGENATED CASTOR OIL,CELLULOSE,HYDROGENATED OLIVE OIL DECYL ESTERS,MANGIFERA INDICA SEED BUTTER*,PARFUM (FRAGRANCE),RUBUS IDAEUS (RASPBERRY) SEED OIL*,GLYCOLIPIDS,TOCOPHEROL,ALOE BARBADENSIS LEAF EXTRACT*,ORYZA SATIVA (RICE) POWDER*,JOJOBA ESTERS,MAGNESIUM STEARATE,QUARTZ,+/- (MAY CONTAIN),CI 77491 (IRON OXIDES),CI 77742 (MANGANESE VIOLET),CI 77492 (IRON OXIDES) | K59: BOÎTIER | L59: 8 g | M59: FRANCE | O59: 1
A60: TEINT DIVIN - POUDRE DE TEINT UNIFIANTE | B60: SO'BIO ETIC | C60: GROUPE LÉA NATURE | D60: TEINT DIVIN | E60: MAQUILLAGE | F60: VISAGE,ZONE T,COU | G60: FOND DE TEINT,POUDRE | H60: TOUS TYPES DE PEAUX,TOUTES CARNATIONS,CONVIENT AUX PEAUX SENSIBLES/RÉACTIVES | I60: 1. À l’aide d’un pinceau, prélever de la poudre de teint unifiante certifiée bio SO’BiO étic®. 2. Tapoter le pinceau pour enlever l’excédent. 3. Balayer largement sur l’ensemble du visage. Insister sur la zone T, plus productrice de sébum (le nez, le menton, et le front). 4. Elle peut s’utiliser en retouches matité à tout moment de la journée. | J60: MICA,CALCIUM CARBONATE,TAPIOCA STARCH*,HELIANTHUS ANNUUS (SUNFLOWER) SEED OIL*,KAOLIN,LAUROYL LYSINE,HYDROGENATED CASTOR OIL,CELLULOSE,HYDROGENATED OLIVE OIL DECYL ESTERS,MANGIFERA INDICA SEED BUTTER*,PARFUM (FRAGRANCE),RUBUS IDAEUS (RASPBERRY) SEED OIL*,GLYCOLIPIDS,TOCOPHEROL,ALOE BARBADENSIS LEAF EXTRACT*,ORYZA SATIVA (RICE) POWDER*,MAGNESIUM STEARATE,JOJOBA ESTERS,+/- (MAY CONTAIN),CI 77492 (IRON OXIDES),CI 77499 (IRON OXIDES),CI 77491 (IRON OXIDES) | K60: BOÎTIER | L60: 8 g | M60: FRANCE | O60: 1
A61: LUMINOUS SILK - GLOW FUSION POWDER | B61: GIORGIO ARMANI | C61: L'ORÉAL | D61: LUMINOUS SILK | E61: MAQUILLAGE | F61: VISAGE | G61: POUDRE/SPRAY DE FINITION,COMPACT | H61: TOUS TYPES DE PEAUX | I61: Pour flouter les imperfections, choisissez la teinte la plus proche de votre carnation. Mélangez avec une poudre sculptante ou un pinceau blush. Appliquez de préférence sur une peau hydratée. Pour accentuer les traits du visage, choisissez une teinte 2 à 3 tons plus clairs pour mettre les zones clés en lumière et 2 à 3 tons plus foncés pour réchauffer le teint ou sculpter les traits. | J61: INCI TEINTE 9 : SYNTHETIC FLUORPHLOGOPITE,TALC,LAUROYL LYSINE,OCTYLDODECANOL,SORBITAN ISOSTEARATE,ISOTRIDECYL ISONONANOATE,DIMETHICONE,BARIUM SULFATE,ZEA MAYS STARCH/CORN STARCH,DIMETHICONE/VINYL DIMETHICONE CROSSPOLYMER,CAPRYLYL GLYCOL,PETROLATUM,POLYSORBATE 80,PHENOXYETHANOL,AQUA/WATER,ARGILLA/MAGNESIUM ALUMINUM SILICATE,ACRYLONITRILE/METHYL METHACRYLATE/VINYLIDENE CHLORIDE COPOLYMER,DISODIUM STEAROYL GLUTAMATE,XANTHAN GUM,ALUMINUM HYDROXIDE,LAURETH-4,+/- (MAY CONTAIN),MICA,CI 77891 (TITANIUM DIOXIDE),CI 77163 (BISMUTH OXYCHLORIDE),CI 77491, CI 77492, CI 77499 (IRON OXIDES) | K61: BOÎTIER | M61: FRANCE | O61: 1
A62: LE PHYTO-BLUSH - BLUSH LUMIÈRE | B62: SISLEY | C62: GROUPE SISLEY | E62: MAQUILLAGE | F62: VISAGE,JOUES | G62: FARD À JOUES/BLUSH,POUDRE | H62: TOUS TYPES DE PEAUX,TOUTES CARNATIONS | I62: Teinte Blush : à l’aide du pinceau blush, appliquer en mouvements circulaires ou en lissages pour habiller les pommettes. Teinte Highlighter : à l’aide du pinceau blush, appliquer en touche finale sur les zones clés du visage à illuminer : du haut des pommettes vers les tempes, l'arête du nez, l'arc de cupidon, l’arcade sourcilière. | J62: INCI TEINTES 1,2,3 & 5 : MICA,POLYETHYLENE,BORON NITRIDE,C12-15 ALKYL BENZOATE,CAPRYLIC/CAPRIC TRIGLYCERIDE,POLYGLYCERYL-2 ISOSTEARATE/DIMER DILINOLEATE COPOLYMER,SILICA,ETHYLHEXYLGLYCERIN,CAMELLIA OLEIFERA SEED OIL,GOSSYPIUM HERBACEUM (COTTON) SEED OIL,TOCOPHERYL ACETATE,ZINC STEARATE,TIN OXIDE,PARFUM/FRAGRANCE,+/- (MAY CONTAIN),TITANIUM DIOXIDE (CI 77891),IRON OXIDES (CI 77491, CI 77492, CI 77499),RED 7 LAKE (CI 15850),RED 6 (CI 15850),YELLOW 5 LAKE (CI 19140),BLUE 1 LAKE (CI 42090),RED 28 LAKE (CI 45410) | K62: BOÎTIER | L62: 6,5 g | M62: ITALIE | O62: 1
A63: I LIKE TO SCRUB IT SCRUB IT - POUDRE EXFOLIANTE VISAGE | B63: GLIME | C63: Beauty Story | E63: SOIN VISAGE | F63: VISAGE | G63: GOMMAGE,POUDRE | H63: TOUS TYPES DE PEAUX | I63: Matin ou soir, pressez délicatement pour verser une petite quantité de poudre dans vos mains humides puis appliquez sur le visage en effectuant des mouvements circulaires. Rincez à l’eau tiède. | J63: CELLULOSE,ORYZA SATIVA (RICE) HULL POWDER,SODIUM COCOYL ISETHIONATE,KAOLIN,TALC,AQUA (WATER/EAU),BAMBUSA ARUNDINACEA STEM POWDER,COCONUT ACID,PARFUM (FRAGRANCE),SALICYLIC ACID,SODIUM ISETHIONATE,CI 42090,CI 19140 | K63: FLACON | L63: 30 g | M63: FRANCE | O63: 0
A64: PRO FILT'R SOFT MATTE POWDER | B64: FENTY BEAUTY | C64: LVMH | E64: MAQUILLAGE | F64: VISAGE | G64: FOND DE TEINT,POUDRE | H64: TOUS TYPES DE PEAUX,TOUTES CARNATIONS | I64: UTILISER PRO FILT'R FOND DE TEINT POUDRE MAT Préparation : Veillez d'abord à bien hydrater la peau avec l'écran solaire hydratant invisible à large spectre SPF 30 Hydra Vizor de Fenty Skin avant d'appliquer le fond de teint en poudre. 1. Poursuivez avec votre Base Pro Filt'r. Laissez poser pour des résultats optimaux. 2. Pour une couvrance complète, appliquez le produit à l'aide de l'éponge incluse. Pour une couvrance légère et modulable, utilisez le pinceau Poudre De Finition 170 (non inclus) afin d'obtenir la couvrance désirée ; moins les poils du pinceau sont serrés, plus la couvrance sera légère. La méthode de Rihanna : Appliquez par-dessus votre fond de teint liquide Pro Filt'r pour une couvrance supplémentaire où que vous soyez. TROUVER SA TEINTE PRO FILT'R - Le fond de teint mat et doux en poudre Pro-Filt'r se décline dans les 50 mêmes nuances que le Pro Filt'r original. - Vous ne connaissez pas votre teinte ? Commencez par sélectionner votre famille de teintes (Claire, Moyenne, Hâlée et Foncée), puis réduisez votre choix au sous-ton de votre peau. Essayez notre Fenty Face Shade Finder si vous avez besoin d'aide en la matière. | J64: INCI TEINTE #105 (LIGHT WITH WARM YELLOW UNDERTONES) : TALC,NYLON-12,SYNTHETIC FLUORPHLOGOPITE,KAOLIN,ISOAMYL LAURATE,DIMETHICONE,ZINC STEARATE,PHENYL TRIMETHICONE,1,2-HEXANEDIOL,CAPRYLYL GLYCOL,MAGNESIUM MYRISTATE,POLYESTER-4,BORON NITRIDE,BARIUM SULFATE,PHENOXYETHANOL,DIMETHICONOL,DECYLENE GLYCOL,HYDRATED SILICA,METHYL METHACRYLATE CROSSPOLYMER,TITANIUM DIOXIDE (CI 77891),IRON OXIDES (CI 77491, CI 77492, CI 77499) | K64: BOÎTIER | L64: 9,1 g | M64: ITALIE | O64: 1
A65: INFAILLIBLE - UP TO 24H FRESH WEAR FOUNDATION IN A POWDER | B65: L'ORÉAL PARIS | C65: L'ORÉAL | D65: INFAILLIBLE | E65: MAQUILLAGE | F65: VISAGE | G65: FOND DE TEINT,POUDRE,COMPACT | H65: TOUS TYPES DE PEAUX | I65: 1. Pour un teint naturellement mat et unifié, appliquer le fond de teint en poudre Infaillible uniformément sur l'ensemble du visage à l'aide d'un pinceau. 2. Pour corriger l'excès de brillance, insister sur la zone T délimitée par le front et le nez pour matifier le teint et diminuer l'apparence des pores. | J65: TALC,ZINC STEARATE,DIMETHICONE,ZEA MAYS STARCH/CORN STARCH,CAPRYLIC/CAPRIC TRIGLYCERIDE,SILICA,DIMETHICONE/VINYL DIMETHICONE CROSSPOLYMER,TRIETHOXYCAPRYLYLSILANE,CAPRYLYL GLYCOL,ETHYLHEXYLGLYCERIN,POTASSIUM SORBATE,SILICA [NANO]/SILICA,PARFUM/FRAGRANCE,ISOCETETH-10,ALARIA ESCULENTA EXTRACT,HEXYL CINNAMAL,BENZYL SALICYLATE,LINALOOL,ALPHA-ISOMETHYL IONONE,BENZYL ALCOHOL,CITRONELLOL,TOCOPHEROL,+/- (MAY CONTAIN),CI 77891/TITANIUM DIOXIDE,CI 77491, CI 77492, CI 77499/IRON OXIDES,MICA,CI 19140/YELLOW 5 LAKE,CI 77007/ULTRAMARINES,CI 15850/RED 7 LAKE | K65: BOÎTIER | L65: 9 g | M65: USA | O65: 1
A66: CRÈME N°2 MASQUE PEEL-OFF DOUCEUR - LE SOIN SOS APAISANT RÉCONFORTANT | B66: PAYOT | C66: USHOPAL | D66: CRÈME N°2 | E66: SOIN VISAGE | F66: VISAGE | G66: MASQUE,SOIN,POUDRE,PEEL-OFF | H66: PEAUX SENSIBLES/TRÈS SENSIBLES,PEAUX RÉACTIVES | I66: 1. Verser de l’eau froide jusqu’au niveau indiqué. 2. Mélanger énergiquement à l’aide de la spatule jusqu’à l’obtention d’une pâte homogène. 3. Appliquer en couche épaisse sur l’ensemble du visage en évitant le contour des yeux et laisser poser 5-10min. 4.Décoller le masque par le bas. Rincer à l’eau. | J66: DIATOMACEOUS EARTH,CALCIUM SULFATE HYDRATE,ALGIN,TETRASODIUM PYROPHOSPHATE,XANTHAN GUM,ALPHA-GLUCAN OLIGOSACCHARIDE,AQUA (WATER),AVENA SATIVA KERNEL MEAL/OAT KERNEL MEAL,MAGNESIUM OXIDE,BIFIDA FERMENT LYSATE,LACTOSE,MILK PROTEIN,HYDROGENATED LECITHIN,PHENETHYL ALCOHOL,PARFUM (FRAGRANCE),CI 77491 (IRON OXIDES),CI 19140 (YELLOW 5 LAKE),CI 77499 (IRON OXIDES) | K66: POT | L66: 10 g | M66: FRANCE | O66: 0
A67: TOUCHE ÉCLAT ALL OVER GLOW - POUDRE ILLUMINATRICE ÉCLAT TOTAL MULTIDIMENSIONNEL | B67: YVES SAINT LAURENT | C67: L'ORÉAL | D67: TOUCHE ÉCLAT | E67: MAQUILLAGE | F67: VISAGE | G67: ENLUMINEUR,POUDRE | H67: TOUS TYPES DE PEAUX,TOUTES CARNATIONS | I67: À l'aide du pinceau, appliquer sur l'ensemble du visage pour un éclat naturel multidimensionnel et instantané. Faîtes glisser sur les pommettes, le nez et le menton pour doner une touche d'éclat plus prononcée. | J67: TALC,MICA,CI 77891/TITANIUM DIOXIDE,CAPRYLIC/CAPRIC TRIGLYCERIDE,NYLON-12,MAGNESIUM STEARATE,CI 77491/IRON OXIDES,SYNTHETIC FLUORPHLOGOPITE,CAPRYLYL GLYCOL,PARFUM/FRAGRANCE,AQUA/WATER,TIN OXIDE,PROPYLENE GLYCOL,ALTHAEA OFFICINALIS ROOT EXTRACT,CALENDULA OFFICINALIS FLOWER EXTRACT,CITRIC ACID,SODIUM BENZOATE,POTASSIUM SORBATE | K67: BOÎTIER | L67: 8,8 g | M67: FRANCE | O67: 1
A68: SET+GLOW DUO - POUDRE+ENLUMINEUR AUX PROBIOTIQUES | B68: BE+RADIANCE | C68: BelleRadiance SAS | E68: MAQUILLAGE | F68: VISAGE | G68: FARD À JOUES/BLUSH,ENLUMINEUR,POUDRE | H68: TOUS TYPES DE PEAUX,TOUTES CARNATIONS,CONVIENT AUX PEAUX SENSIBLES/RÉACTIVES | I68: Le Set+Glow Probiotics peut s’appliquer aux doigts ou au pinceau. Vous pouvez appliquer la poudre seule et ajouter l’highlighter sur les pomettes pour un magnifique résultat glowy, ou mélanger les deux produits pour obtenir un teint matifié et éblouissant. | J68: INCI POUDRE DE TEINT : MICA,MARANTA ARUNDINACEA ROOT POWDER,TAPIOCA STARCH,KAOLIN,MAGNESIUM MYRISTATE,MORINGA OLEIFERA SEED OIL,SQUALANE,HELIANTHUS ANNUUS (SUNFLOWER) SEED OIL,ZINC STEARATE,COCO-CAPRYLATE/CAPRATE,BENTONITE,PROTIUM HEPTAPHYLLUM RESIN,CAPRYLYL GLYCOL,TOCOPHERYL ACETATE,LANNEA MICROCARPA FRUIT EXTRACT,LACTOBACILLUS FERMENT,+/- (MAY CONTAIN),CI 77891 (TITANIUM DIOXIDE),CI 77491 (IRON OXIDES),CI 77492 (IRON OXIDES),CI 77499 (IRON OXIDES) | K68: BOÎTIER | L68: 10 g | M68: FRANCE | O68: 1
A69: TRIO D'HUILES - NETTOYANT POUDRE AU PRÉBIOTIQUE | B69: YODI | C69: YODI BEAUTY SAS | E69: SOIN VISAGE | F69: VISAGE | G69: SOIN,POUDRE,ANHYDRE,DÉMAQUILLANT/NETTOYANT | H69: PEAUX SÈCHES | I69: 1. Bien agitez le nettoyant avant usage. 2. Versez environ une demi-cuillère à café de nettoyant dans la main. 3. Ajoutez quelques gouttes d'eau et faites mousser entre vos mains. 4. Massez-vous le visage par mouvements circulaires pour bien le nettoyer. 5. Bien rincer à l'eau. Astuce : Dans le cas des peaux très sensibles ne supportant pas l'eau du robinet ou le calcaire, il est préférable d'utiliser une eau pour peaux sensibles pour faire mousser et pour rincer le nettoyant. | J69: ZEA MAYS (CORN) STARCH*,MANNITOL,SODIUM COCOYL GLUTAMATE,ARGANIA SPINOSA KERNEL OIL*,CARTHAMUS TINCTORIUS (SAFFLOWER) SEED OIL*,CANNABIS SATIVA SEED OIL*,ALPHA-GLUCAN OLIGOSACCHARIDE | K69: FLACON,CAPSULE SERVICE | L69: 30 g | M69: FRANCE | O69: 0
A70: CHARBON PURIFIANT - NETTOYANT VISAGE POUDRE | B70: YODI | C70: YODI BEAUTY SAS | E70: SOIN VISAGE | F70: VISAGE | G70: DÉMAQUILLANT/NETTOYANT,POUDRE,ANHYDRE | H70: PEAUX MIXTES À GRASSES,PEAUX MIXTES,PEAUX GRASSES,PEAUX À IMPERFECTIONS | I70: Bien agiter le nettoyant avant usage. Verser environ 1/2 cuillère à café de nettoyant dans la main. Ajoutez quelques gouttes d’eau et frotter entre vos mains. (une texture lactée va se créer). Massez-vous le visage par mouvements circulaires pour bien le nettoyer. Bien rincer à l’eau. Astuce : Dans le cas des peaux très sensibles ne supportant pas l’eau du robinet ou le calcaire, il est préférable d’utiliser une eau pour peaux sensibles pour faire mousser et pour rincer le nettoyant. | J70: ZEA MAYS (CORN) STARCH*,MANNITOL,SODIUM COCOYL GLUTAMATE,ALPHA-GLUCAN OLIGOSACCHARIDE,CHARCOAL POWDER,SESAMUM INDICUM (SESAME) SEED OIL*,SIMMONDSIA CHINENSIS (JOJOBA) SEED OIL*,ZINC PCA | K70: FLACON,CAPSULE SERVICE | L70: 30 g | M70: FRANCE | N70: 3770016116046 | O70: 0
A71: PHYTO-POUDRE COMPACTE - MATIFIANTE ET EMBELLISSANTE | B71: SISLEY | C71: GROUPE SISLEY | D71: COLLECTION GOLDEN ZEBRA 2020 | E71: MAQUILLAGE | F71: VISAGE | G71: POUDRE,COMPACT | H71: TOUS TYPES DE PEAUX,TOUTES CARNATIONS | I71: Appliquer avec le Pinceau Poudre pour une couvrance légère et un fini seconde peau. Pour une couvrance plus intense, appliquer à l’aide de la houppette intégrée par légères pressions sur la zone T puis balayer vers l’extérieur. | J71: SYNTHETIC FLUORPHLOGOPITE,TALC,PHENYL TRIMETHICONE,THEOBROMA GRANDIFLORUM SEED BUTTER,BORON NITRIDE,SILICA,MANGIFERA INDICA (MANGO) SEED BUTTER,THEOBROMA CACAO (COCOA) SEED BUTTER,HIBISCUS SABDARIFFA FLOWER EXTRACT,TRIETHOXYCAPRYLYLSILANE,CAPRYLYL GLYCOL,ETHYLHEXYLGLYCERIN,LECITHIN,POLYMETHYLSILSESQUIOXANE,C20-24 OLEFIN,ALUMINA,GLYCERIN,AQUA/WATER/EAU,CITRIC ACID,POTASSIUM SORBATE,SODIUM BENZOATE,TOCOPHEROL,ASCORBYL PALMITATE,+/- (MAY CONTAIN),BISMUTH OXYCHLORIDE (CI 77163),TITANIUM DIOXIDE (CI 77891),IRON OXIDES (CI 77491, CI 77492, CI 77499) | K71: BOÎTIER | L71: 12 g | M71: ITALIE | O71: 1
A72: BLUSH BRAZILIAN SHIMMER - POUDRE VISAGE NACRÉE | B72: GUERLAIN | C72: LVMH | D72: COLLECTION BRAZILIAN CLUB 2020 ÉDITION LIMITÉE | E72: MAQUILLAGE | F72: VISAGE,BUSTE/DÉCOLLETÉ | G72: FARD À JOUES/BLUSH,POUDRE | H72: TOUTES CARNATIONS | I72: Touche finale de votre routine maquillage, le blush Brazilian Shimmer fait rayonner le hâle de votre peau. Souriez et appliquez le blush Brazilian Shimmer à l'aide d'un pinceau sur la partie bombée des pommettes jusqu'aux tempes. | J72: TALC,SYNTHETIC FLUORPHLOGOPITE,NYLON-12,LAUROYL LYSINE,MAGNESIUM MYRISTATE,OCTYLDODECYL STEAROYL STEARATE,ETHYLHEXYL PALMITATE,HYDROGENATED POLYISOBUTENE,BORON NITRIDE,SILICA,PENTAERYTHRITYL TETRAISOSTEARATE,POLYMETHYLSILSESQUIOXANE,ZINC STEARATE,DIMETHICONE,SODIUM DEHYDROACETATE,PARFUM (FRAGRANCE),CAPRYLYL GLYCOL,PENTYLENE GLYCOL,TOCOPHEROL,ALPHA-ISOMETHYL IONONE,BENZYL BENZOATE,LINALOOL,BENZYL ALCOHOL,LIMONENE,AMYL CINNAMAL,GERANIOL,BHT,+/- (MAY CONTAIN),CI 77891 (TITANIUM DIOXIDE),CI 77163 (BISMUTH OXYCHLORIDE),CI 77491, CI 77492, CI 77499 (IRON OXIDES),CI 73360 (RED 30 LAKE) | K72: BOÎTIER | L72: 6 g | M72: FRANCE | O72: 1
A73: MÉTÉORITES BRAZILIAN FIZZ - PERLES DE POUDRE RÉVÉLATRICES DE LUMIÈRE | B73: GUERLAIN | C73: LVMH | D73: COLLECTION BRAZILIAN CLUB 2020 ÉDITION LIMITÉE | E73: MAQUILLAGE | F73: VISAGE,BUSTE/DÉCOLLETÉ | G73: ENLUMINEUR,PERLES,POUDRE | H73: TOUTES CARNATIONS | I73: Utiliser le pinceau Météorites pour appliquer uniformément sur l’ensemble du visage. Pour un éclat boosté, illuminer les parties bombées : dessiner un G du centre du front vers les tempes, les pommettes et le haut du nez en redescendant jusqu’à la pointe du menton. | J73: SYNTHETIC FLUORPHLOGOPITE,TALC,NYLON-12,DISTARCH PHOSPHATE,MAGNESIUM MYRISTATE,MAGNESIUM CARBONATE,HYDRATED SILICA,PENTYLENE GLYCOL,TRITICUM VULGARE (TRITICUM VULGARE (WHEAT) STARCH),POLYMETHYLSILSESQUIOXANE,PARFUM (FRAGRANCE),SODIUM DEHYDROACETATE,GLYCERYL STEARATE,CAPRYLYL GLYCOL,SORBIC ACID,ALPHA-ISOMETHYL IONONE,BENZYL BENZOATE,TOCOPHEROL,LINALOOL,BENZYL ALCOHOL,DIAMOND POWDER,LIMONENE,AMYL CINNAMAL,GERANIOL,BHT,CINNAMYL ALCOHOL,+/- (MAY CONTAIN),CI 77891 (TITANIUM DIOXIDE),CI 77289 (CHROMIUM HYDROXIDE GREEN),CI 77491, CI 77492, CI 77499 (IRON OXIDES),CI 73360 (RED 30 LAKE),CI 77007 (ULTRAMARINES) | K73: BOÎTIER | L73: 25 g | M73: FRANCE | O73: 0
A74: SKINCOLOR DE LA MER - LE FOND DE TEINT POUDRE HYDRATANT SOYEUX SPF 30 | B74: CRÈME DE LA MER | C74: CRÈME DE LA MER INC. | D74: SKINCOLOR DE LA MER | E74: MAQUILLAGE | F74: VISAGE,COU | G74: FOND DE TEINT,POUDRE,COMPACT | H74: TOUTES CARNATIONS | I74: Appliquez sur l'ensemble du visage avec l'applicateur en éponge sèche et estompez vers l'extérieur jusqu'au cou pour un teint unifié et sublimé. Faites des retouches au cours de la journée si besoin. | J74: TALC,SYNTHETIC FLUORPHLOGOPITE,METHYL METHACRYLATE CROSSPOLYMER,BORON NITRIDE,WATER\AQUA\EAU,VINYL DIMETHICONE/METHICONE SILSESQUIOXANE CROSSPOLYMER,DIMETHICONE,ALUMINUM HYDROXIDE,DIISOSTEARYL MALATE,ALGAE (SEAWEED) EXTRACT,SESAMUM INDICUM (SESAME) SEED OIL,MEDICAGO SATIVA (ALFALFA) SEED POWDER,HELIANTHUS ANNUUS (SUNFLOWER) SEEDCAKE,PRUNUS AMYGDALUS DULCIS (SWEET ALMOND) SEED MEAL,EUCALYPTUS GLOBULUS (EUCALYPTUS) LEAF OIL,SODIUM GLUCONATE,COPPER GLUCONATE,CALCIUM GLUCONATE,MAGNESIUM GLUCONATE,ZINC GLUCONATE,TOCOPHERYL SUCCINATE,NIACIN,SESAMUM INDICUM (SESAME) SEED POWDER,CITRUS AURANTIFOLIA (LIME) PEEL EXTRACT,CODIUM TOMENTOSUM EXTRACT,HYDROLYZED CORALLINA OFFICINALIS EXTRACT,WHEY PROTEIN\LACTIS PROTEIN\PROTEINE DU PETIT-LAIT,ACETYL GLUCOSAMINE,ERYNGIUM MARITIMUM EXTRACT,LAMINARIA DIGITATA EXTRACT,GLYCERIN,ACETYL HEXAPEPTIDE-8,BUTYLENE GLYCOL,HYDROLYZED RICE PROTEIN,SIGESBECKIA ORIENTALIS (ST. PAUL'S WORT) EXTRACT,YEAST EXTRACT\FAEX\EXTRAIT DE LEVURE,BARIUM SULFATE,ISOCETYL MYRISTATE,METHICONE,TETRAHEXYLDECYL ASCORBATE,SQUALANE,PHYTOSTERYL/ISOSTEARYL/CETYL/STEARYL/BEHENYL DIMER DILINOLEATE,POLYSORBATE 80,CAPRYLYL GLYCOL,SILICA,HYDRATED SILICA,ALUMINUM DISTEARATE,HYDROGEN DIMETHICONE,TOCOPHEROL,FRAGRANCE (PARFUM),BHT,ALCOHOL DENAT.,POTASSIUM SORBATE,SODIUM DEHYDROACETATE,PHENOXYETHANOL,+/- (MAY CONTAIN),MICA,TITANIUM DIOXIDE (CI 77891),IRON OXIDES (CI 77491),IRON OXIDES (CI 77492),IRON OXIDES (CI 77499),ACTIVE INGREDIENTS,TITANIUM DIOXIDE,ETHYLHEXYL METHOXYCINNAMATE (OCTINOXATE) | K74: BOÎTIER,APPLICATEUR ÉPONGE | L74: 9,5 g | M74: JAPON | O74: 1
A75: MÉTÉORITES PEARL DUST PALETTE - PALETTE ILLUMINATRICE SUR MESURE | B75: GUERLAIN | C75: LVMH | D75: MÉTÉORITES | E75: MAQUILLAGE | F75: VISAGE,YEUX,PAUPIÈRES | G75: ENLUMINEUR,POUDRE,COMPACT | H75: TOUS TYPES DE PEAUX,TOUTES CARNATIONS | I75: En enlumineur : À l'aide d'un pinceau, appliquez la poudre sur les zones à illuminer: le haut des pommettes, l'arête du nez, l'arc de Cupidon et le menton. Pour un éclat plus intense, appliquez la poudre à l'aide de votre doigt et estomper. En blush : À l'aide d'un pinceau, appliquez la poudre sur l'ensemble de la pommette. En fard à paupière : Au pinceau ou au doigt, appliquez la poudre sur l'ensemble de la paupière mobile pour unifier et dans le coin interne de l'oeil pour illuminer. | J75: INCI FORMULE #14264 : SYNTHETIC FLUORPHLOGOPITE,TALC,ZEA MAYS (CORN) STARCH,TRIISOSTEARIN,OCTYLDODECANOL,BORON NITRIDE,MAGNESIUM ALUMINUM SILICATE,DIMETHICONE,AQUA (WATER),ETHYLHEXYLGLYCERIN,1,2-HEXANEDIOL,CAPRYLYL GLYCOL,PARFUM (FRAGRANCE),ALPHA-ISOMETHYL IONONE,BENZYL BENZOATE,BUTYLENE GLYCOL,LINALOOL,BENZYL ALCOHOL,TIN OXIDE,LIMONENE,AMYL CINNAMAL,GERANIOL,BHT,CINNAMYL ALCOHOL,TOCOPHEROL,ALUMINUM HYDROXIDE,HYDROLYZED CONCHIOLIN PROTEIN,HYDRATED SILICA,HYDROGEN DIMETHICONE,+/- (MAY CONTAIN),CI 77891 (TITANIUM DIOXIDE),CI 77491 (IRON OXIDES) | K75: BOÎTIER | L75: 8,5 g | M75: ITALIE | O75: 1
A76: POWDER POP - FLOWER HIGHLIGHTER | B76: CLINIQUE | C76: THE ESTÉE LAUDER COS. | D76: COLLECTION FLOWER POWER 2020 | E76: MAQUILLAGE | F76: VISAGE | G76: ENLUMINEUR,POUDRE | H76: TOUTES CARNATIONS | I76: Appliquer au doigt ou à l’aide d’un pinceau sur une peau nue ou maquillée pour illuminer légèrement l'arête du nez, donner du relief aux pommettes et/ou donner de l'éclat à toute autre zone du visage. | J76: MICA,CETEARYL ETHYLHEXANOATE,C12-20 ACID PEG-8 ESTER,HDI/TRIMETHYLOL HEXYLLACTONE CROSSPOLYMER,SQUALANE,GLYCERIN,ETHYLHEXYLGLYCERIN,CAPRYLYL GLYCOL,CHONDRUS CRISPUS (CARRAGEENAN) EXTRACT,DICALCIUM PHOSPHATE,1,2-HEXANEDIOL,POLYSORBATE 80,SILICA,SYNTHETIC FLUORPHLOGOPITE,+/- (MAY CONTAIN),TITANIUM DIOXIDE (CI 77891),IRON OXIDES (CI 77491),IRON OXIDES (CI 77492),IRON OXIDES (CI 77499),MANGANESE VIOLET (CI 77742),YELLOW 5 LAKE (CI 19140),RED 22 LAKE (CI 45380),RED 30 LAKE (CI 73360),CHROMIUM OXIDE GREENS (CI 77288),CHROMIUM HYDROXIDE GREEN (CI 77289),CARMINE (CI 75470),BISMUTH OXYCHLORIDE (CI 77163),RED 33 LAKE (CI 17200),RED 28 LAKE (CI 45410),BLUE 1 LAKE (CI 42090),RED 34 LAKE (CI 15880),YELLOW 6 LAKE (CI 15985),RED 7 LAKE (CI 15850),RED 6 (CI 15850),FERRIC FERROCYANIDE (CI 77510),ULTRAMARINES (CI 77007) | K76: BOÎTIER | L76: 9 g | M76: ITALIE | O76: 1
A77: LES BEIGES - POUDRE BELLE MINE ILLUMINATRICE | B77: CHANEL | C77: GROUPE CHANEL | D77: COLLECTION LES BEIGES SUMMER OF GLOW 2020 | E77: MAQUILLAGE | F77: VISAGE | G77: ENLUMINEUR,POUDRE | H77: TOUTES CARNATIONS | I77: Pour un look naturel lumineux, appliquer la poudre en finition de votre fond de teint sur les zones du visage qui reflètent la lumière.Pour un résultat plus léger, réaliser de larges mouvements afin d’appliquer la poudre sur l’ensemble du visage, de l’intérieur vers l’extérieur. | J77: INCI TEINTE SAND : TALC,SYNTHETIC FLUORPHLOGOPITE,POLYAMIDE-5,STEARYL/PPG-3 MYRISTYL ETHER DIMER DILINOLEATE,BORON NITRIDE,SYNTHETIC WAX,PPG-2 MYRISTYL ETHER PROPIONATE,PARAFFINUM LIQUIDUM (MINERAL OIL),SILICA,KALANCHOE PINNATA LEAF EXTRACT,AMMONIUM SILVER ZINC ALUMINUM SILICATE,CERA MICROCRISTALLINA (MICROCRYSTALLINE WAX),ALUMINUM DIMYRISTATE,METHYLPARABEN,CERA ALBA (BEESWAX),PARAFFIN,PARFUM (FRAGRANCE),CHLORPHENESIN,TOCOPHERYL ACETATE,TIN OXIDE,MALTODEXTRIN,+/- (MAY CONTAIN),CI 73360 (RED 30 LAKE),CI 75470 (CARMINE),CI 77007 (ULTRAMARINES),CI 77491, CI 77492, CI 77499 (IRON OXIDES),CI 77891 (TITANIUM DIOXIDE),MICA | K77: BOÎTIER | L77: 10 g | M77: FRANCE | O77: 1
A78: COULEURS NATURE - RAYONNANT JEUNESSE - DUO ENLUMINEUR | B78: YVES ROCHER | C78: GROUPE ROCHER | D78: COULEURS NATURE | E78: MAQUILLAGE | F78: VISAGE | G78: ENLUMINEUR,POUDRE | H78: TOUS TYPES DE PEAUX,TOUTES CARNATIONS | J78: MICA,TALC,SYNTHETIC FLUORPHLOGOPITE,DIMETHICONE,NYLON-12,OCTYLDODECYL STEAROYL STEARATE,ISOPROPYL PALMITATE,POLYSORBATE 20,MAGNESIUM ALUMINUM SILICATE,CAPRYLYL GLYCOL,SORBITAN STEARATE,PHENOXYETHANOL,SODIUM DEHYDROACETATE,ACRYLAMIDE/SODIUM ACRYLOYLDIMETHYLTAURATE COPOLYMER,SIMMONDSIA CHINENSIS (JOJOBA) SEED OIL,LAUROYL LYSINE,ISOHEXADECANE,TOCOPHERYL ACETATE,HEXYLENE GLYCOL,POLYSORBATE 80,SORBITAN OLEATE,CALCIUM SODIUM BOROSILICATE,CALCIUM ALUMINUM BOROSILICATE,MAGNESIUM OXIDE,ALUMINA,SILICA,TIN OXIDE,+/- (MAY CONTAIN),CI 77491 (IRON OXIDES),CI 77492 (IRON OXIDES),CI 77499 (IRON OXIDES),CI 77891 (TITANIUM DIOXIDE) | K78: BOÎTIER | L78: 6 g | M78: ITALIE | O78: 1
A79: SYNCHRO SKIN - TONE UP PRIMER COMPACT SPF 24/PA++ | B79: SHISEIDO | C79: SHISEIDO CO. | D79: SYNCHRO SKIN | E79: MAQUILLAGE | F79: VISAGE | G79: BASE TEINT,POUDRE,COMPACT | H79: TOUTES CARNATIONS | I79: After skincare, apply primer alone, or under foundation. Can also be used over makeup to touch up during the day. Slide fingers under the ribbon on the puff and swipe over the primer from top to bottom. Tap the puff under the eyes and cheeks. Smooth outward over the contours and forehead. Tap on more primer as needed. Apply liberally. Reducing the quantity of application will lower the level of sunscreen protection significantly. Avoid direct contact with eyes. | J79: WATER (AQUA),DIMETHICONE,DIPROPYLENE GLYCOL,PARAFFIN,ETHYLHEXYL METHOXYCINNAMATE,GLYCERIN,NYLON-12,TITANIUM DIOXIDE,SILICA,POLYMETHYLSILSESQUIOXANE,PEG-10 DIMETHICONE,TITANIUM DIOXIDE (CI 77891),SORBITAN SESQUIISOSTEARATE,PHENOXYETHANOL,POLYETHYLENE,MICA,MICROCRYSTALLINE WAX (CERA MICROCRISTALLINA),DISTEARYLDIMONIUM CHLORIDE,ALUMINA,HYDROGEN DIMETHICONE,PALMITIC ACID,SODIUM CITRATE,LITHIUM MAGNESIUM SODIUM SILICATE,ALUMINUM HYDROXIDE,TRIETHOXYCAPRYLYLSILANE,DIMETHICONE/PEG-10/15 CROSSPOLYMER,TOCOPHEROL,IRON OXIDES (CI 77491),IRON OXIDES (CI 77492),ISOPROPYL ALCOHOL,CITRIC ACID,MAGNESIUM ALUMINOMETASILICATE,BUTYLENE GLYCOL,ISODODECANE,PEG/PPG-19/19 DIMETHICONE,POLYQUATERNIUM-51,HYDROGENATED POLYISOBUTENE,TRIMETHYLSILOXYSILYLCARBAMOYL PULLULAN,BHT,POLYSILICONE-2,TIN OXIDE,SODIUM ACETYLATED HYALURONATE,HYDROLYZED CONCHIOLIN PROTEIN,THYMUS SERPYLLUM EXTRACT,DIMETHICONE/VINYL DIMETHICONE CROSSPOLYMER | K79: BOÎTIER | L79: 13 g | M79: JAPON | O79: 1
A80: RADIANCE ENZYME PEELING | B80: ONE. TWO. FREE! | C80: Ultimate Skin Aesthetics GmbH | D80: CLEANSE | E80: SOIN VISAGE | F80: VISAGE,COU | G80: GOMMAGE,PEELING,POUDRE,ANHYDRE | H80: TOUS TYPES DE PEAUX,CONVIENT AUX PEAUX SENSIBLES/RÉACTIVES | I80: Appliquez une à deux fois par semaine. Versez la poudre (1/2 dose) dans la paume de votre main, ajoutez quelques gouttes d'eau chaude et faites mousser. Appliquez généreusement sur le visage et le cou. Laissez agir 5 minutes. Rincez abondamment et essuyez. En cas de contact avec les yeux, rincez à l'eau. | J80: DISODIUM LAURYL SULFOSUCCINATE,ZEA MAYS STARCH,TALC,SODIUM MYRISTOYL GLUTAMATE,KAOLIN,LYSOLECITHIN,SCLEROTIUM GUM,LACTOBACILLUS/PUNICA GRANATUM FRUIT FERMENT EXTRACT,XANTHAN GUM,PULLULAN,SILICA,PARFUM,LINALOOL | K80: FLACON | L80: 35 g | M80: ALLEMAGNE | O80: 0
A81: MY CLARINS - RE-MOVE - POUDRE EXFOLIANTE ÉCLAT | B81: CLARINS | C81: GROUPE CLARINS | D81: MY CLARINS | E81: SOIN VISAGE | F81: VISAGE | G81: GOMMAGE,POUDRE | H81: TOUS TYPES DE PEAUX,CONVIENT AUX PEAUX SENSIBLES/RÉACTIVES | I81: Mélanger la poudre avec le gel nettoyant purifiant RE-MOVE My Clarins ou à de l'eau. 1 à 2 fois par semaine au creux de la main, frictionnez le mélange pour obtenir une mousse légère. Masser délicatement sur l'ensemble du visage en évitant le contour des yeux. Rincer abondamment à l'eau puis sécher. Quantité recommandée : 1/2 cuillère à café par utilisation. Adapter la dose et la fréquence en la diminuant si nécessaire en fonction de votre type de peau. | J81: ORYZA SATIVA (RICE) POWDER,SUCROSE,SODIUM LAUROYL GLUTAMATE,BAMBUSA ARUNDINACEA STEM EXTRACT,DISTARCH PHOSPHATE,VACCINIUM MACROCARPON (CRANBERRY) FRUIT POWDER,PRUNUS AMYGDALUS DULCIS (SWEET ALMOND) SHELL POWDER,MALTODEXTRIN,MORINGA OLEIFERA SEED EXTRACT | K81: FLACON,CAPSULE SERVICE | L81: 40 g | M81: FRANCE | O81: 0
A82: TERRACOTTA NUDE - POUDRE ÉCLAT NATUREL | B82: GUERLAIN | C82: LVMH | E82: MAQUILLAGE | F82: VISAGE,COU | G82: ENLUMINEUR,POUDRE | H82: TOUTES CARNATIONS | I82: Le bon geste pour illuminer et réchauffer naturellement l'ensemble du visage : un secret Guerlain, la gestuelle du "3". Appliquez la poudre Terracotta Nude au pinceau en dessinant une 3 de chaque côté du visage : du front aux pommettes, puis des pommettes au menton, et enfin en redescendant le long du cou. Terminez, en effleurant le centre du visage, du front au menton. | J82: MICA,TALC,LAUROYL LYSINE,CELLULOSE,ZINC STEARATE,DIISOSTEARYL MALATE,OCTYLDODECYL STEAROYL STEARATE,PARFUM (FRAGRANCE),SODIUM DEHYDROACETATE,ETHYLENE BRASSYLATE,CAPRYLYL GLYCOL,ETHYLHEXYLGLYCERIN,LIMONENE,MAGNESIUM ASPARTATE,TOCOPHERYL ACETATE,PRUNUS ARMENIACA (APRICOT) KERNEL OIL,TRIETHOXYCAPRYLYLSILANE,MANGANESE GLUCONATE,LINALOOL,HEXYL CINNAMAL,ASCORBYL PALMITATE,ALPHA-ISOMETHYL IONONE,COUMARIN,CITRAL,EUGENOL,GERANIOL,HYDROXYCITRONELLAL,SOLANUM LYCOPERSICUM (TOMATO) FRUIT/LEAF/STEM EXTRACT,TOCOPHEROL,HELIANTHUS ANNUUS (SUNFLOWER) SEED OIL,ROSMARINUS OFFICINALIS (ROSEMARY) LEAF EXTRACT,+/- (MAY CONTAIN),CI 77163 (BISMUTH OXYCHLORIDE),CI 77491, CI 77492 (IRON OXIDES),CI 77891 (TITANIUM DIOXIDE) | K82: BOÎTIER | L82: 10 g | M82: FRANCE | O82: 1
A83: TERRACOTTA MATTE - POUDRE SCULPTANTE | B83: GUERLAIN | C83: LVMH | E83: MAQUILLAGE | F83: VISAGE,COU | G83: ENLUMINEUR,POUDRE | H83: TOUTES CARNATIONS | I83: Le bon geste pour sculpter le teint en 3 secondes ou ensoleiller le visage sans brillance : un secret Guerlain, la gestuelle du "3". Appliquez la poudre sculptante en dessinant un "3" de chaque côté du visage : du front aux bas des pommettes, puis du bas des pommettes au menton, enfin en redescendant le long du cou. | J83: TALC,SILICA,LAUROYL LYSINE,KAOLIN,BIS-BEHENYL/ISOSTEARYL/PHYTOSTERYL DIMER DILINOLEYL DIMER DILINOLEATE,ETHYLHEXYL PALMITATE,OCTYLDODECYL STEAROYL STEARATE,CAPRYLYL GLYCOL,PARFUM (FRAGRANCE),PENTAERYTHRITYL TETRAETHYLHEXANOATE,PENTYLENE GLYCOL,ZINC STEARATE,SODIUM DEHYDROACETATE,ETHYLENE BRASSYLATE,LIMONENE,MAGNESIUM ASPARTATE,TOCOPHERYL ACETATE,PRUNUS ARMENIACA (APRICOT) KERNEL OIL,MANGANESE GLUCONATE,LINALOOL,HEXYL CINNAMAL,TOCOPHEROL,ASCORBYL PALMITATE,ALPHA-ISOMETHYL IONONE,COUMARIN,CITRAL,EUGENOL,GERANIOL,ALUMINA,MAGNESIUM OXIDE,HYDROXYCITRONELLAL,SOLANUM LYCOPERSICUM (TOMATO) FRUIT/LEAF/STEM EXTRACT,HELIANTHUS ANNUUS (SUNFLOWER) SEED OIL,ROSMARINUS OFFICINALIS (ROSEMARY) LEAF EXTRACT,CI 77491, CI 77492, CI 77499 (IRON OXIDES),CI 77891 (TITANIUM DIOXIDE) | K83: BOÎTIER | L83: 10 g | M83: FRANCE | O83: 1
A84: ÉCLAT DU DÉSERT - POUDRE ILLUMINATRICE | B84: CHANEL | C84: GROUPE CHANEL | D84: SPRING-SUMMER 2020 COLLECTION | E84: MAQUILLAGE | F84: VISAGE | G84: ENLUMINEUR,POUDRE | H84: TOUS TYPES DE PEAUX | I84: Les astuces de Lucia Pica : C’est la touche finale pour apporter un supplément de lumière au visage. S’applique sur peau nue ou déjà maquillée sur les zones reliefs du visage : commencer de la pommette et étirer vers les tempes, puis illuminer l’arête du nez et l’arc de cupidon pour un effet sensuel. Estomper grâce à l’applicateur. | J84: SYNTHETIC FLUORPHLOGOPITE,BORON NITRIDE,MAGNESIUM CARBONATE,DIISOSTEARYL MALATE,TRIHYDROXYSTEARIN,DIMETHICONE,SILICA,ETHYLHEXYL PALMITATE,PARAFFINUM LIQUIDUM (MINERAL OIL),POLYMETHYL METHACRYLATE,AMMONIUM SILVER ZINC ALUMINUM SILICATE,SUCROSE TETRASTEARATE TRIACETATE,CERA MICROCRISTALLINA (MICROCRYSTALLINE WAX),MAGNESIUM STEARATE,TOCOPHERYL ACETATE,POTASSIUM SORBATE,PARAFFIN,CHLORPHENESIN,TIN OXIDE,SORBITAN ISOSTEARATE,TALC,+/- (MAY CONTAIN),CI 12085 (RED 36),CI 15850 (RED 7 LAKE),CI 15880 (RED 34),CI 15985 (YELLOW 6 LAKE),CI 17200 (RED 33 LAKE),CI 19140 (YELLOW 5 LAKE),CI 42090 (BLUE 1 LAKE),CI 45380 (RED 22 LAKE),CI 45410 (RED 28 LAKE),CI 73360 (RED 30 LAKE),CI 75470 (CARMINE),CI 77007 (ULTRAMARINES),CI 77163 (BISMUTH OXYCHLORIDE),CI 77491, CI 77492, CI 77499 (IRON OXIDES),CI 77510 (FERRIC FERROCYANIDE),CI 77742 (MANGANESE VIOLET),CI 77891 (TITANIUM DIOXIDE),MICA | K84: BOÎTIER | L84: 11 g | M84: FRANCE | O84: 1
A85: HIGH GLASS - ILLUMINATING POWDER | B85: NYX PROFESSIONAL MAKEUP | C85: L'ORÉAL | D85: HIGH GLASS | E85: MAQUILLAGE | F85: VISAGE | G85: ENLUMINEUR,POUDRE | H85: TOUTES CARNATIONS | I85: Rehausse les points saillants de ton visage grâce à notre HIGH GLASS ILLUMINATING POWDER BRUSH. | J85: DIMETHICONE,CAPRYLIC/CAPRIC TRIGLYCERIDE,TRIMETHYLSILOXYPHENYL DIMETHICONE,POLYBUTENE,DIMETHICONE CROSSPOLYMER,ZINC OXIDE [NANO],LAUROYL LYSINE,AQUA/WATER/EAU,CAPRYLYL GLYCOL,PHENOXYETHANOL,+/- (MAY CONTAIN),CI 77491, CI 77499/IRON OXIDES,CI 77891/TITANIUM DIOXIDE,MICA | K85: BOÎTIER | L85: 4 g | M85: TAIWAN | O85: 1
A86: SEPHORA COLLECTION - SAL - LOTION ANTI-IMPERFECTIONS | B86: SEPHORA | C86: LVMH | D86: SEPHORA COLLECTION | E86: SOIN VISAGE | F86: VISAGE | G86: SOIN,BI-PHASE,LOTION,POUDRE | H86: PEAUX À IMPERFECTIONS | I86: Ne pas secouer. À l'aide d'un coton tige, prélever de la poudre et l'appliquer sur les imperfections. Laisser sécher toute la nuit, et rincer à l'eau claire le matin. | J86: AQUA (WATER),ALCOHOL DENAT.,CI 77947 (ZINC OXIDE),ISOPROPYL ALCOHOL,GLYCERIN,VACCINIUM MYRTILLUS FRUIT EXTRACT,SACCHARUM OFFICINARUM (SUGAR CANE) EXTRACT,SALICYLIC ACID,CITRUS AURANTIUM DULCIS (ORANGE) FRUIT EXTRACT,CITRUS LIMON (LEMON) FRUIT EXTRACT,CI 77288 (CHROMIUM OXIDE GREENS),SODIUM HYDROXIDE,ACER SACCHARUM (SUGAR MAPLE) EXTRACT | K86: FLACON | L86: 15 ml | M86: FRANCE | N86: 3378872139270 | O86: 0
A87: ÉCLAT MAGNÉTIQUE DE CHANEL - POUDRE ILLUMINATRICE | B87: CHANEL | C87: GROUPE CHANEL | D87: LES ORNEMENTS DE CHANEL HOLIDAY 2019 COLLECTION | E87: MAQUILLAGE | F87: VISAGE | G87: ENLUMINEUR,POUDRE | H87: TOUS TYPES DE PEAUX | I87: Appliquez sur le haut des pommettes et estomper jusqu’à ce que la matière s’estompe au profit de la lumière. Créez un halo étincelant autour des yeux, avant ou après l’application de l’ombre à paupières. Déposez un léger voile de poudre sur l’ensemble du visage comme une subtile pluie de lumière, et insistez plus spécialement sur les pommettes, l’arête du nez et l’arcade sourcilière. Peut s’appliquer sur un maquillage poudre ou crème. | J87: DICAPRYLYL CARBONATE,DIMETHICONE,CELLULOSE,MAGNESIUM STEARATE,SYNTHETIC FLUORPHLOGOPITE,PARAFFINUM LIQUIDUM (MINERAL OIL),MAGNESIUM SILICATE,CERA MICROCRISTALLINA (MICROCRYSTALLINE WAX),LAURYL PEG-9 POLYDIMETHYLSILOXYETHYL DIMETHICONE,PARAFFIN,CHLORPHENESIN,SILICA,TIN OXIDE,TOCOPHEROL,+/- (MAY CONTAIN),CI 77007 (ULTRAMARINES),CI 77491, CI 77492, CI 77499 (IRON OXIDES),CI 77891 (TITANIUM DIOXIDE),MICA | K87: BOÎTIER | L87: 10 g | M87: FRANCE | O87: 1
A88: DUO DE CAMÉLIAS - ILLUMINATING POWDER DUO | B88: CHANEL | C88: GROUPE CHANEL | E88: MAQUILLAGE | F88: VISAGE | G88: ENLUMINEUR,POUDRE | H88: TOUS TYPES DE PEAUX | I88: Sweep onto center of forehead, tops of cheekbones, brow bones and Cupid’s bow. Or, apply all over for a subtly radiant look. | J88: ALUMINA,SYNTHETIC FLUORPHLOGOPITE,CETEARYL ETHYLHEXANOATE,GLYCERIN,SQUALANE,C12-20 ACID PEG-8 ESTER,HDI/TRIMETHYLOL HEXYLLACTONE CROSSPOLYMER,TIN OXIDE,SILICA,CAPRYLYL GLYCOL,POLYSORBATE 80,ETHYLHEXYLGLYCERIN,1,2-HEXANEDIOL,CHONDRUS CRISPUS EXTRACT,XANTHAN GUM,PENTAERYTHRITYL TETRA-DI-T-BUTYL HYDROXYHYDROCINNAMATE,CALCIUM CHLORIDE,DICALCIUM PHOSPHATE,+/- (MAY CONTAIN),CI 77007 (ULTRAMARINES),CI 77491, CI 77492, CI 77499 (IRON OXIDES),CI 77891 (TITANIUM DIOXIDE),MICA | K88: BOÎTIER | L88: 8,5 g | O88: 1
A89: O !MEGA GLAZE ALL-OVER FOIL LUMINIZER | B89: MARC JACOBS BEAUTY | C89: COTY GROUP INC | D89: ÉDITION LIMITÉE | E89: MAQUILLAGE | F89: VISAGE,CORPS | G89: ENLUMINEUR,POUDRE | H89: TOUS TYPES DE PEAUX,TOUTES CARNATIONS | I89: Appliquez-le pour illuminer vos pommettes, le haut de vos épaules, vos jambes ou n'importe quelle zone où vous souhaitez apporter une touche de lumière. | J89: MICA,CALCIUM ALUMINUM BOROSILICATE,CAPRYLIC/CAPRIC TRIGLYCERIDE,MICROCRYSTALLINE CELLULOSE,BIS-DIGLYCERYL POLYACYLADIPATE-2,DIISOSTEARYL MALATE,PHENYL TRIMETHICONE,DIMETHICONE,DIMETHICONE/VINYL DIMETHICONE CROSSPOLYMER,CAPRYLYL GLYCOL,ETHYLHEXYLGLYCERIN,TIN OXIDE,SODIUM DEHYDROACETATE,AQUA/WATER/EAU,TOCOPHEROL,CALCIUM SODIUM BOROSILICATE,SYNTHETIC FLUORPHLOGOPITE,SILICA,TITANIUM DIOXIDE (CI 77891),IRON OXIDES (CI 77491, CI 77492, CI 77499) | K89: BOÎTIER | L89: 10 g | M89: CANADA | O89: 1
A90: THE GLOW HIGHLIGHTER | B90: CRÈME DE LA MER | C90: CRÈME DE LA MER INC. | D90: HOLIDAY 2019 COLLECTION | E90: MAQUILLAGE | F90: VISAGE | G90: ENLUMINEUR,POUDRE | H90: TOUTES CARNATIONS | I90: Appliquer la crème sur les pommettes, le nez, les arcs du visage et la clavicule pour un look irisé et lumineux. Puis, appliquer la poudre sur les zones où la lumière réfléchit naturellement le front, les joues, le nez et le menton. Pour un résultat optimal, utiliser le Pinceau pour appliquer la crème et le Pinceau Poudre pour appliquer la poudre. | J90: INCI TEXTURE CRÈME : CAPRYLIC/CAPRIC TRIGLYCERIDE,TRIMETHYLOLPROPANE TRIISOSTEARATE,POLYETHYLENE,CETYL ETHYLHEXANOATE,C20-40 ALCOHOLS,SYNTHETIC FLUORPHLOGOPITE,SILICA,BIS-DIGLYCERYL POLYACYLADIPATE-2,ALUMINUM STARCH OCTENYLSUCCINATE,CETYL ALCOHOL,ALGAE (SEAWEED) EXTRACT,SESAMUM INDICUM (SESAME) SEED OIL,MEDICAGO SATIVA (ALFALFA) SEED POWDER,HELIANTHUS ANNUUS (SUNFLOWER) SEEDCAKE,PRUNUS AMYGDALUS DULCIS (SWEET ALMOND) SEED MEAL,EUCALYPTUS GLOBULUS (EUCALYPTUS) LEAF OIL,SODIUM GLUCONATE,COPPER GLUCONATE,CALCIUM GLUCONATE,ZINC GLUCONATE,TOCOPHERYL SUCCINATE,NIACIN,SESAMUM INDICUM (SESAME) SEED POWDER,WATER\AQUA\EAU,MALACHITE,TOURMALINE,TOCOPHEROL,BUTYROSPERMUM PARKII (SHEA BUTTER),MANGIFERA INDICA (MANGO) SEED BUTTER,MAGNESIUM GLUCONATE,GLYCINE SOJA (SOYBEAN) OIL,ISODODECANE,VINYL DIMETHICONE/METHICONE SILSESQUIOXANE CROSSPOLYMER,TRIMETHYLSILOXYSILICATE,TIN OXIDE,CALCIUM CARBONATE,FRAGRANCE (PARFUM),+/- (MAY CONTAIN),MICA,IRON OXIDES (CI 77491),IRON OXIDES (CI 77492),IRON OXIDES (CI 77499),TITANIUM DIOXIDE (CI 77891),CARMINE (CI 75470),ULTRAMARINES (CI 77007),FERRIC FERROCYANIDE (CI 77510),RED 6 (CI 15850),RED 7 LAKE (CI 15850),RED 27 (CI 45410),RED 7 (CI 15850),YELLOW 6 LAKE (CI 15985),BLUE 1 LAKE (CI 42090),RED 21 (CI 45380),BISMUTH OXYCHLORIDE (CI 77163),CHROMIUM HYDROXIDE GREEN (CI 77289),CHROMIUM OXIDE GREENS (CI 77288),YELLOW 5 LAKE (CI 19140),MANGANESE VIOLET (CI 77742) | K90: BOÎTIER | L90: 5 g | M90: CANADA | O90: 1
A91: BROW STYLER - CRAYON ET POUDRE À SOURCILS MULTIFONCTION | B91: BENEFIT | C91: LVMH | E91: MAQUILLAGE | F91: SOURCILS | G91: CRAYON À SOURCILS,CIRE,POUDRE | I91: 3 styles. 3 minutes. TOP CHRONO ! - Pour un arc net et dessiné utilisez le crayon-cire, - Pour un résultat discret et étoffé utilisez la poudre, - Pour une courbe audacieuse et définie utilisez le crayon cire + la poudre. Dessinez et mettez en forme vos sourcils à l'aide du crayon-cire, puis appliquez la poudre pour un effet plus prononcé.Envie de d'autres styles ? - De la définition et un fini naturel. Commencez par définir à la poudre votre courbe et comblez les zones clairsemées. Pour un résultat subtil, dessinez ensuite des petits traits avec le crayon-cire le long de la base des sourcils et jusqu'à la pointe. Sourcils en épi : - Déposez de la poudre sur les sourcils. - À l'aide du crayon-cire, tracez ensuite des traits en diagonale pour imiter les poils naturels. - Brossez vers le haut pour un effet en épi encore plus prononcé. | J91: INCI CIRE : SYNTHETIC FLUORPHLOGOPITE,BEHENIC ACID,RHUS SUCCEDANEA FRUIT WAX,TRIETHYLHEXANOIN,DIPENTAERYTHRITYL HEXAHYDROXYSTEARATE/HEXASTEARATE/HEXAROSINATE,SUCROSE TETRASTEARATE TRIACETATE,HYDROGENATED CASTOR OIL,CAPRYLIC/CAPRIC TRIGLYCERIDE,SORBITAN SESQUIISOSTEARATE,ALUMINUM HYDROXIDE,TOCOPHEROL,TALC,+/- (MAY CONTAIN),CI 19140 (YELLOW 5, YELLOW 5 LAKE),CI 42090 (BLUE 1 LAKE),CI 77007 (ULTRAMARINES),CI 77163 (BISMUTH OXYCHLORIDE),CI 77288 (CHROMIUM OXIDE GREENS),CI 77289 (CHROMIUM HYDROXIDE GREEN),CI 77491, CI 77492, CI 77499 (IRON OXIDES),CI 77510 (FERRIC FERROCYANIDE, FERRIC AMMONIUM FERROCYANIDE),CI 77742 (MANGANESE VIOLET),CI 77891 (TITANIUM DIOXIDE) | K91: CRAYON,STICK,APPLICATEUR EMBOUT BISEAUTÉ | L91: 0,3 g|0,75 g | M91: JAPON | O91: 0
A92: HIGHLIGHTER - POUDRE VISAGE ILLUMINATRICE | B92: GUERLAIN | C92: LVMH | D92: ÉDITION LIMITÉE | E92: MAQUILLAGE | F92: VISAGE | G92: ENLUMINEUR,POUDRE | H92: TOUS TYPES DE PEAUX | I92: Pour un éclat boosté, illuminez les parties bombées du visages. Dessinez un G du centre du front vers les tempes, les pommettes et le haut du nez en redescendant jusqu'à la pointe du menton. | J92: SYNTHETIC FLUORPHLOGOPITE,MICA,LIMNANTHES ALBA (MEADOWFOAM) SEED OIL,HYDROGENATED VEGETABLE OIL,CAPRYLIC/CAPRIC TRIGLYCERIDE,HECTORITE,POLYMETHYLSILSESQUIOXANE,PARFUM (FRAGRANCE),SOYBEAN GLYCERIDES,CAPRYLYL GLYCOL,PHENETHYL ALCOHOL,BUTYROSPERMUM PARKII BUTTER UNSAPONIFIABLES,BUTYROSPERMUM PARKII (SHEA) BUTTER EXTRACT,ALPHA-ISOMETHYL IONONE,OLEIC/LINOLEIC/LINOLENIC POLYGLYCERIDES,BENZYL BENZOATE,SORBITAN TRISTEARATE,LINALOOL,BENZYL ALCOHOL,LIMONENE,DIAMOND POWDER,AMYL CINNAMAL,GERANIOL,BHT,CINNAMYL ALCOHOL,EUGENOL,ASCORBYL PALMITATE,TOCOPHEROL,CITRIC ACID,+/- (MAY CONTAIN),CI 77891 (TITANIUM DIOXIDE),CI 77491, CI 77492, CI 77499 (IRON OXIDES),CI 77163 (BISMUTH OXYCHLORIDE) | K92: BOÎTIER | L92: 6 g | M92: ITALIE | O92: 1
A93: MÉTÉORITES GOLDENLAND - PERLES DE POUDRE RÉVÉLATRICES DE LUMIÈRE | B93: GUERLAIN | C93: LVMH | D93: GOLDENLAND COLLECTION HOLIDAY 2019 | E93: MAQUILLAGE | F93: VISAGE | G93: ENLUMINEUR,PERLES,POUDRE | H93: TOUTES CARNATIONS | I93: Utiliser le pinceau Météorites, conçu pour prélever la juste mesure de poudre et appliquer Météorites Goldenland uniformément sur l’ensemble du visage finaliser le maquillage. Pour un éclat boosté, illuminer les parties bombées : dessiner un G du centre du front vers les tempes, les pommettes et le haut du nez en redescendant jusqu’à la pointe du menton. | J93: SYNTHETIC FLUORPHLOGOPITE,TALC,NYLON-12,MAGNESIUM MYRISTATE,DISTARCH PHOSPHATE,SILICA,MAGNESIUM CARBONATE,TRITICUM VULGARE (TRITICUM VULGARE (WHEAT) STARCH),HYDRATED SILICA,PENTYLENE GLYCOL,POLYMETHYLSILSESQUIOXANE,MICA,PARFUM (FRAGRANCE),SODIUM DEHYDROACETATE,GLYCERYL STEARATE,CAPRYLYL GLYCOL,SORBIC ACID,ALPHA-ISOMETHYL IONONE,BENZYL BENZOATE,TOCOPHEROL,LINALOOL,BENZYL ALCOHOL,DIAMOND POWDER,LIMONENE,AMYL CINNAMAL,GERANIOL,BHT,CINNAMYL ALCOHOL,+/- (MAY CONTAIN),CI 77491, CI 77492, CI 77499 (IRON OXIDES),CI 77891 (TITANIUM DIOXIDE),CI 15850 (RED 7) | K93: BOÎTIER | L93: 25 g | M93: FRANCE | O93: 1
A94: BORN THIS WAY - MULTI-USE COMPLEXION POWDER | B94: TOO FACED | C94: THE ESTÉE LAUDER COS. | D94: BORN THIS WAY | E94: MAQUILLAGE | F94: VISAGE | G94: FOND DE TEINT,POUDRE,COMPACT | H94: TOUTES CARNATIONS,TOUS TYPES DE PEAUX | I94: Appliquez avec le bout des doigts, une éponge ou le pinceau Kabuki rétractable. Commencez par le centre du visage puis travaillez vers l’extérieur. Renouvelez jusqu'à obtenir la couvrance désirée. | J94: TALC,MAGNESIUM MYRISTATE,NYLON-12,POLYETHYLENE,OCTYLDODECYL STEAROYL STEARATE,OCTYLDODECYL STEARATE,SODIUM HYALURONATE,TOCOPHERYL ACETATE,LECITHIN,RHODODENDRON FERRUGINEUM EXTRACT,GLYCERIN,ETHYLHEXYL PALMITATE,PANTHENYL TRIACETATE,FARNESYL ACETATE,WATER\AQUA\EAU,SILICA,PISTACIA LENTISCUS (MASTIC) GUM,TRIETHOXYCAPRYLYLSILANE,1,2-HEXANEDIOL,SILICA DIMETHYL SILYLATE,PTFE,CAPRYLYL GLYCOL,BUTYLENE GLYCOL,HEXYLENE GLYCOL,ALCOHOL,COCOS NUCIFERA (COCONUT) LIQUID ENDOSPERM,TETRAHEXYLDECYL ASCORBATE,TETRASODIUM EDTA,PHENOXYETHANOL,POTASSIUM SORBATE,+/- (MAY CONTAIN),TITANIUM DIOXIDE (CI 77891),MICA,BISMUTH OXYCHLORIDE (CI 77163),IRON OXIDES (CI 77491),IRON OXIDES (CI 77492),IRON OXIDES (CI 77499) | K94: BOÎTIER | L94: 10 g | M94: CANADA | O94: 1
A95: BOUNCE & BLUR - BLUSH FARD À JOUES | B95: BAREMINERALS | C95: AI beauty Holding Limited / Advent International | E95: MAQUILLAGE | F95: VISAGE | G95: FARD À JOUES/BLUSH,POUDRE | H95: TOUS TYPES DE PEAUX,TOUTES CARNATIONS | I95: Prélevez le produit avec votre doigt en effectuant de petits mouvements circulaires et tapotez la couleur sur la paupière, en estompant du bout des doigts. Pas besoin d'appuyer pour prélever le produit. Il s'agit d'une formule souple et fragile qui peut parfois glisser à l'intérieur de l'emballage pendant le transport. Si tel est le cas, elle peut être délicatement replacée dans la palette afin de tenir toutes ses promesses. | J95: DIMETHICONE,SILICA,ETHYLHEXYL ISONONANOATE,BORON NITRIDE,DIISOSTEARYL MALATE,TRIMETHYLSILOXYSILICATE,DIMETHICONE CROSSPOLYMER,BHT,IMPERATA CYLINDRICA ROOT EXTRACT,LYCOPODIUM CLAVATUM EXTRACT,CALCIUM ALUMINUM BOROSILICATE,ETHYLHEXYLGLYCERIN,GLYCERIN,METHICONE,NYLON-12,PYRIDOXINE CYCLIC PHOSPHATE,SODIUM HYALURONATE,TIN OXIDE,PHENOXYETHANOL,+/- (MAY CONTAIN),MICA,TITANIUM DIOXIDE (CI 77891),IRON OXIDES (CI 77491, CI 77492, CI 77499),CARMINE (CI 75470),RED 7 LAKE (CI 15850) | K95: BOÎTIER | L95: 5,9 g | M95: CANADA | O95: 1
A96: ENCRE DE PEAU - ALL HOURS SETTING POWDER | B96: YVES SAINT LAURENT | C96: L'ORÉAL | D96: ENCRE DE PEAU | E96: MAQUILLAGE | F96: VISAGE | G96: POUDRE,COMPACT,FOND DE TEINT,BASE TEINT | H96: TOUS TYPES DE PEAUX | I96: 2 TECHNIQUES D'APPLICATION AU PINCEAU POUR UNE COUVRANCE LÉGÈRE Prélevez à l'aide d'un pinceau à poudre. Appliquez la poudre en insistant sur la zone T (front, arête du nez, menton). Estompez vers l'extérieur du visage. À L'APPLICATEUR POUR UNE COUVRANCE SUR-MESURE Prélevez la poudre à l'aide du côté beige en éponge. Appliquez-la par de petites pressions sur l'ensemble du visage en insistant sur la zone T, puis lissez pour un teint parfaitement unifié. Retouchez tout au long de la journée à l'aide du côté blanc en velours en effectuant de légères pressions au niveau des zones de brillance. QUELLES SONT LES DIFFÉRENCES ENTRE LA POUDRE UNIVERSELLE ET LA POUDRE TEINTÉE ? POUDRE TEINTÉE - 2 UTILISATIONS Seule en fond de teint poudre ou après votre fond de teint en poudre de finition. Disponible en plusieurs teintes. POUDRE UNIVERSELLE - 1 UTILISATION En poudre de finition pour contrôler la brillance et fixer le maquillage. Pour toutes les carnations. | J96: TALC,SILICA,BORON NITRIDE,CAPRYLIC/CAPRIC TRIGLYCERIDE,OCTYLDODECYL STEAROYL STEARATE,CAPRYLYL GLYCOL,PARFUM/FRAGRANCE,MAGNESIUM STEARATE,BENZYL ALCOHOL,LINALOOL,+/- (MAY CONTAIN),CI 77491, CI 77492, CI 77499/IRON OXIDES,CI 77891/TITANIUM DIOXIDE | K96: BOÎTIER | L96: 8,5 g | M96: FRANCE | O96: 1
A97: JOLI BLUSH - BLUSH COULEUR & ÉCLAT LONGUE TENUE | B97: CLARINS | C97: GROUPE CLARINS | E97: MAQUILLAGE | F97: JOUES | G97: FARD À JOUES/BLUSH,POUDRE | H97: TOUS TYPES DE PEAUX,TOUTES CARNATIONS | I97: À appliquer à tout moment de la journée ou de la soirée ! | J97: INCI TEINTE 03 : TALC,MICA,CI 77891/TITANIUM DIOXIDE,OCTYLDODECYL STEAROYL STEARATE,SYNTHETIC FLUORPHLOGOPITE,ZINC STEARATE,DIMETHICONE,CI 19140/YELLOW 5 LAKE,CI 73360/RED 30 LAKE,CI 77007/ULTRAMARINES,CITRIC ACID,LAUROYL LYSINE,PHENOXYETHANOL,AQUA/WATER/EAU,CORYLUS AVELLANA (HAZEL) SEED OIL,CI 77499/IRON OXIDES,SILICA,PARFUM/FRAGRANCE,CI 45380/RED 21,TOCOPHERYL ACETATE,BUTYLENE GLYCOL,CI 77491/IRON OXIDES,CAMELLIA SINENSIS LEAF EXTRACT,CALCIUM SODIUM BOROSILICATE,CALCIUM ALUMINUM BOROSILICATE,LAPSANA COMMUNIS FLOWER/LEAF/STEM EXTRACT,TIN OXIDE | K97: BOÎTIER | L97: 5 g | M97: ITALIE | O97: 1
A98: DIORSKIN MINERAL NUDE MATTE - POUDRE PERFECTRICE MATE NATURELLE | B98: DIOR | C98: LVMH | D98: DIORSKIN - ÉDITION LIMITÉE | E98: MAQUILLAGE | F98: VISAGE | G98: ENLUMINEUR,POUDRE | H98: TOUS TYPES DE PEAUX,TOUTES CARNATIONS | I98: 1. Pour un teint naturellement mat et flouté, appliquer la poudre de finition uniformément sur l'ensemble du visage à l'aide d'un pinceau kabuki. 2. Pour corriger l'excès de brillance, insister sur la zone T délimitée par le front et le nez pour matifier le teint et diminuer l'apparence des pores. Appliquer au cours de la journée pour rafraîchir instantanément le teint et le sublimer d'un éclat mat lumineux. | J98: TALC,NYLON-12,ZINC STEARATE,POLYMETHYLSILSESQUIOXANE,MICA,HDI/TRIMETHYLOL HEXYLLACTONE CROSSPOLYMER,POLYETHYLENE,LAUROYL LYSINE,SILICA,DIMETHICONE,ISOSTEARYL ISOSTEARATE,ETHYLHEXYL ISONONANOATE,ETHYLHEXYL PALMITATE,PHENYL TRIMETHICONE,OCTYLDODECYL STEAROYL STEARATE,CAPRYLYL GLYCOL,ETHYLHEXYLGLYCERIN,AQUA (WATER),SODIUM DEHYDROACETATE,SODIUM BENZOATE,DIMETHICONE/PEG-10/15 CROSSPOLYMER,PARFUM (FRAGRANCE),ASCORBYL GLUCOSIDE,MAGNESIUM ASPARTATE,ZINC GLUCONATE,LINALOOL,LIMONENE,TOCOPHEROL,CITRONELLOL,RHODOCHROSITE EXTRACT,PHENOXYETHANOL,SODIUM CITRATE,SORBIC ACID,BHT,+/- (MAY CONTAIN),CI 15850 (RED 6, RED 7, RED 7 LAKE),CI 15985 (YELLOW 6, YELLOW 6 LAKE),CI 19140 (YELLOW 5, YELLOW 5 LAKE),CI 42090 (BLUE 1 LAKE),CI 45410 (RED 27, RED 27 LAKE, RED 28 LAKE),CI 73360 (RED 30, RED 30 LAKE),CI 77007 (ULTRAMARINES),CI 77163 (BISMUTH OXYCHLORIDE),CI 77288 (CHROMIUM OXIDE GREENS),CI 77289 (CHROMIUM HYDROXIDE GREEN),CI 77491, CI 77492, CI 77499 (IRON OXIDES),CI 77510 (FERRIC FERROCYANIDE, FERRIC AMMONIUM FERROCYANIDE),CI 77742 (MANGANESE VIOLET),CI 77891 (TITANIUM DIOXIDE) | K98: BOÎTIER | L98: 7 g | M98: FRANCE | O98: 1
A99: SKIN CAVIAR - POWDER FOUNDATION SPF 15 UVA/PA++ | B99: LA PRAIRIE | C99: BEIERSDORF | D99: SKIN CAVIAR | E99: MAQUILLAGE | F99: VISAGE | G99: FOND DE TEINT,POUDRE,COMPACT | H99: TOUS TYPES DE PEAUX,TOUTES CARNATIONS | I99: Appliquez le fond de teint par effleurage avec sa houppette suédée dédiée ou par mouvements circulaires avec le Pinceau pour Fond de Teint Compact La Prairie. Commencez par le front, puis l’arête du nez, les joues et le menton. Insistez autour de la naissance des cheveux et en bas du nez, tout en évitant les sourcils. Continuez à estomper autour de la bouche, le long de la ligne de démarcation avec le cou et sous le cou pour une couvrance homogène. | J99: LAUROYL LYSINE,TALC,BORON NITRIDE,SILICA,ETHYLHEXYL METHOXYCINNAMATE,POLYMETHYLSILSESQUIOXANE,DIMETHICONE,MAGNESIUM STEARATE,GLYCOPROTEINS,PANAX GINSENG ROOT EXTRACT,EQUISETUM ARVENSE EXTRACT,CAVIAR EXTRACT,ASCORBYL PALMITATE,TOCOPHEROL,BUTYROSPERMUM PARKII BUTTER UNSAPONIFIABLES,SODIUM HYALURONATE,LACTOBACILLUS FERMENT,ALUMINA,SACCHAROMYCES CEREVISIAE EXTRACT,GLYCERIN,PHENYL TRIMETHICONE,WATER (AQUA),ISOPROPYL TITANIUM TRIISOSTEARATE,CAPRYLYL GLYCOL,ETHYL LINOLEATE,ETHYL OLEATE,ETHYL STEARATE,TRIMETHYLSILOXYSILICATE,ETHYL PALMITATE,BHT,CAPRYLIC/CAPRIC TRIGLYCERIDE,PENTYLENE GLYCOL,PROPYLENE GLYCOL,ETHYLHEXYLGLYCERIN,FRAGRANCE (PARFUM),BENZYL SALICYLATE,LINALOOL,CITRONELLOL,GERANIOL,ALPHA-ISOMETHYL IONONE,LIMONENE,PHENOXYETHANOL,+/- (MAY CONTAIN),BISMUTH OXYCHLORIDE (CI 77163),MICA (CI 77019),TITANIUM DIOXIDE (CI 77891),IRON OXIDES (CI 77491, CI 77492, CI 77499) | K99: BOÎTIER,APPLICATEUR HOUPETTE | L99: 9 g | M99: SUISSE | O99: 1
A100: BLUR EXPERT - VOILE POUDRE PERFECTEUR LISSANT | B100: SISLEY | C100: GROUPE SISLEY | E100: MAQUILLAGE | F100: VISAGE | G100: BLUR/FLOUTEUR,POUDRE | H100: TOUTES CARNATIONS,TOUS TYPES DE PEAUX | I100: Prélever à l’aide d’un gros pinceau* et appliquer sur l'ensemble du visage. Pour plus de couvrance insister sur les zones à flouter. Peut s'utiliser sur peau nue, seul ou après une base de maquillage pour un résultat lumineux, frais et naturel. Peut s'appliquer après le fond de teint pour parfaire le maquillage.En retouches au cours de la journée pour matifier, lisser et embellir.*pinceau poudre Sisley ou Kabuki Phyto-Touches rétractable | J100: MICA,TITANIUM DIOXIDE (CI 77891),SYNTHETIC FLUORPHLOGOPITE,BISMUTH OXYCHLORIDE (CI 77163),PENTAERYTHRITYL TETRAISOSTEARATE,IRON OXIDES (CI 77492),DIPHENYL DIMETHICONE/VINYL DIPHENYL DIMETHICONE/SILSESQUIOXANE CROSSPOLYMER,PEG-12 DIMETHICONE,SORBITAN ISOSTEARATE,METHYL METHACRYLATE CROSSPOLYMER,IRON OXIDES (CI 77491),GLYCERIN,HYDROGENATED LECITHIN,CAPRYLYL GLYCOL,ETHYLHEXYLGLYCERIN,SILICA,1,2-HEXANEDIOL,CARRAGEENAN,XANTHAN GUM,PEG-10 DIMETHICONE,IRON OXIDES (CI 77499) | K100: BOÎTIER | L100: 11 g | M100: ITALIE | O100: 1
...

Sheet clean
A1: NAME | B1: BRAND | C1: COSMETIC CATEGORY | D1: APPLICATION ZONE | E1: PRODUCT TYPE | F1: COSMETIC TARGET | G1: HOW TO USE | H1: INGREDIENTS | I1: PACKAGING | J1: CAPACITY | K1: MADE IN | L1: CODE EAN | M1: link | N1: price
A2: voile caresse spf 15 | B2: bareminerals | C2: maquillage | D2: visage | E2: foundation,powder,compact | F2: toutes carnations | G2: à appliquer en lissage avec le pinceau application visage zéro défaut. | H2: alaria esculenta extract, ascorbyl palmitate, bambusa arundinacea stem powder, benzyl benzoate, benzyl salicylate, boron nitride, camellia sinensis (green tea) leaf extract, cananga odorata flower oil, caprylic/capric triglyceride, cetyl phosphate, coco-caprylate, corallina officinalis extract, geraniol, iron oxides, jojoba esters, lauroyl lysine, linalool, mica, silica, jojoba oil, tocopherol, vitis vinifera (grape) seed oil, zinc oxide, titanium dioxide | I2: boîtier | J2: 10 g | K2: canada
A3: all hours - hyper luminize - poudre illuminatrice versatile | B3: yves saint laurent | C3: maquillage | D3: visage | E3: highlighter,powder | F3: tous types de peaux | G3: appliquez all hours hyper luminize sur les points saillants du visage : pommettes, arête du nez, arc de cupidon et coin interne de l'œil. estompez délicatement au doigt ou au pinceau. | H3: synthetic fluorphlogopite, c12-15 alkyl benzoate, dimethicone, titanium dioxide, mica, calcium aluminum borosilicate, talc, hydrogenated polyisobutene, glass beads, boron nitride, magnesium stearate, ci 77491, silica, hydrogenated styrene/butadiene copolymer, caprylyl glycol, niacinamide, sodium hyaluronate, caprylic/capric triglyceride, sorbitan isostearate, isododecane, methicone, ci 75470, ci 77861, citrus limon peel extract, tris-bht mesitylene, tocopherol | I3: boîtier | J3: 5 g | K3: france | L3: 3614274197044
A4: blush poudre | B4: le rouge français | C4: maquillage | D4: joues | E4: blush,powder | F4: toutes carnations | G4: le blush poudre s’applique après avoir préparé et unifié la base teint. à l’aide du pinceau kabuki intégré, prélevez une petite quantité de poudre en tapotant pour contrôler sa quantité. retirez l’excédent et appliquez par mouvements circulaires sur les zones bombées de votre visage, comme les pommettes. pour intensifier le résultat, répétez l’application par légères touches jusqu’à obtenir le fini souhaité, naturel ou sophistiqué. | H4: talc, tapioca starch, ci 77007, zinc oxide, kaolin, mica, rubia tinctorum root*, coco-caprylate/caprate, squalane, glyceryl caprylate, shea butter, jojoba oil, zinc stearate, tocopherol, argania spinosa kernel oil, glyceryl undecylenate, sunflower seed oil | I4: boîtier | J4: 9 g | K4: france
A5: les tarots de chanel - poudre blush mate | B5: chanel | C5: maquillage | D5: joues | E5: blush,powder | F5: toutes carnations | G5: appliquer la création exclusive les tarots de chanel sur les pommettes à l'aide du pinceau inclus pour apporter de la couleur au teint. appliquer une touche légère pour un maquillage naturel. ajouter une seconde touche pour intensifier le résultat. | H5: synthetic fluorphlogopite, zinc stearate, squalane, caprylyl glycol, ethylhexylglycerin, aluminum hydroxide, water, alcohol, glycerin, tocopherol, polysorbate 80 | I5: boîtier | J5: 14 g | K5: italie | L5: 3145891517286
A6: teint idole ultra wear - c.e. skin transforming highlighter | B6: lancôme | C6: maquillage | D6: visage | E6: highlighter,powder | F6: tous types de peaux,toutes carnations | G6: appliquer advance génifique et masser vers le haut du visage pour une peau instantanément hydratée. appliquer le fond de teint teint idole ultra wear pour une couverture parfaite. appliquer ensuite un correcteur pour un effet lumineux et lifté. bronzez instantanément votre peau avec le nouveau teint idole ultra wear c.e. skin transforming bronzer. utilisez un pinceau large et appliquez-le par mouvements circulaires là où le soleil se pose naturellement sur la peau (joues, nez, tempes et menton). highlightez les zones naturelles de lumière avec le nouveau teint idole ultra wear c.e. skin transforming highlighter. utilisez un pinceau large et appliquez-le là où la lumière illumine votre visage (haut des joues, nez, menton). | H6: talc, caprylic/capric triglyceride, dimethicone, zinc stearate, silica, corn starch, punica granatum pericarp extract, moringa oleifera seed oil, alaria esculenta extract, isododecane, dimethicone/vinyl dimethicone crosspolymer, dimethiconol, silica [nano]/silica, trimethylsiloxysilicate, ascorbyl tetraisopalmitate, caprylyl glycol, ethylhexylglycerin, tocopherol, potassium sorbate, parfum, linalool, limonene | I6: boîtier | J6: 10 g | K6: italie | L6: 3614274110470
A7: les beiges - poudre belle mine ensoleillée 2024 | B7: chanel | C7: maquillage | D7: visage,cou,buste/décolleté | E7: highlighter,powder | F7: toutes carnations,tous types de peaux | G7: pour une application simple et intuitive, prélever les trois poudres en un seul geste avec le pinceau poudre n°106. appliquer sur les pommettes et à l’envi sur le front, les tempes, le nez et le menton pour réchauffer l’ensemble du visage. pour une application plus structurée, utiliser le pinceau poudre n°106 pour appliquer les différents tons de les beiges poudre belle mine ensoleillée. - appliquer la poudre bronzante sur les pommettes en commençant par l'extérieur du visage et en terminant par le milieu de la joue, en effectuant des mouvements circulaires. cette teinte peut également être appliquée sur le front, les tempes, le nez et le menton pour donner plus de chaleur à l'ensemble du visage. - appliquer le blush en l’étirant des pommettes vers l’extérieur pour rehausser les pommettes. - appliquer l’highlighter sur le haut des pommettes pour rehausser le teint et apporter une touche supplémentaire de lumière. | H7: synthetic fluorphlogopite, lauroyl lysine, zinc stearate, boron nitride, octyldodecyl stearoyl stearate, corn starch, octyldodecanol, jasminum grandiflorum (jasmine) flower extract, 1-2-hexanediol, caprylyl glycol, parfum, ethylhexyl palmitate, kaolin, tocopheryl acetate, silica | I7: boîtier | J7: 15 g | K7: italie | L7: 3145891863703
A8: ombre essentielle - ombre à paupières longue tenue multi-usage | B8: chanel | C8: maquillage | D8: paupières | E8: eyeshadow,compact,powder | F8: convient aux porteurs de lentilles | G8: avec ombre essentielle, affirmer son look en jouant sur 3 applications différentes, à porter seules ou en accumulation : - ombrer l’intégralité des paupières d’une couleur intense et lumineuse. - accentuer le regard d’un simple trait d’eye-liner aussi graphique que subtil. - intensifier les sourcils d’une pointe de couleur audacieuse pour un look singulier. humidifier légèrement le pinceau eye-liner biseauté afin d’obtenir un fini précis et une couleur intensifiée. | H8: synthetic fluorphlogopite, octyldodecyl stearoyl stearate, dimethicone, polybutene, trimethylsiloxysilicate, cellulose, hydrogen dimethicone, caprylyl glycol, magnesium stearate, potassium sorbate, silica, chlorphenesin, tocopheryl acetate, dimethicone crosspolymer, salvia hispanica seed oil, tocopherol | I8: boîtier | J8: 1,9 g | K8: france | L8: 3145891812268
A9: météorites - perles de poudre révélatrices de lumière - nouvelle formule 2024 | B9: guerlain | C9: maquillage | D9: visage | E9: highlighter,pearls,powder | F9: toutes carnations | G9: utiliser le pinceau météorites pour appliquer uniformément sur l’ensemble du visage, pour fixer le maquillage et améliorer sa tenue. pour un éclat boosté, illuminer les parties bombées : dessiner un g du centre du front vers les tempes, les pommettes et le haut du nez en redescendant jusqu’à la pointe du menton. | H9: mica, distarch, silica, magnesium myristate, synthetic fluorphlogopite, cellulose, magnesium carbonate hydroxide, calcium sodium borosilicate, hydroxypropyl starch, caprylyl glycol, ethylhexylglycerin, parfum, sodium dehydroacetate, calcium aluminum borosilicate, sorbic acid, ci 77861, tocopherol | I9: boîtier | J9: 25 g | K9: france | L9: 3346470438781
A10: artist eyeshadow - nouvelle formule 2024 | B10: make up for ever | C10: maquillage | D10: paupières | E10: eyeshadow,powder | F10: toutes carnations | G10: 1/ prélever la matière avec le côté plat du pinceau #248. 2/ appliquer l'ombre à paupières sur la zone souhaitée en tapotant délicatement puis en effectuant des mouvements de balayage avec la partie plate du pinceau. 3/ avec le côté rond du pinceau #248, estomper avec de petits mouvements circulaires, puis d'avant en arrière. | H10: synthetic fluorphlogopite, dimethicone, zinc stearate, caprylyl glycol, pentylene glycol, ethylhexylglycerin, silica, diisostearyl malate, octyldodecyl stearoyl stearate, sodium dehydroacetate, kaolin, tocopheryl acetate, sorbitan sesquioleate, tocopherol | I10: boîtier | J10: 5 g
A11: lingerie de peau - fond de teint compact poudre | B11: guerlain | C11: maquillage | D11: visage | E11: foundation,powder,compact | F11: tous types de peaux,toutes carnations | G11: appliquer sur le visage à l’aide de l’éponge, puis étirer à volonté pour obtenir la couvrance idéale, du centre du visage vers l’extérieur et le cou. | H11: barium sulfate, talc, synthetic fluorphlogopite, silica, ethylhexyl methoxycinnamate, cellulose, dimethicone, hydrogenated polyisobutene, mica, pentylene glycol, acrylates/stearyl acrylate/dimethicone methacrylate copolymer, diisostearyl malate, decyloxazolidinone, octyldodecyl stearoyl stearate, sodium dehydroacetate, jojoba esters, caprylyl glycol, aluminum hydroxide, dimethicone/methicone copolymer, palmitic acid, isopropyl titanium triisostearate, parfum, water, sodium lauroyl aspartate, hyaluronic acid, butylphenyl methylpropional, magnesium hydroxide, zinc chloride, linalool, bht, citronellol, alpha-isomethyl ionone, sericin, benzyl benzoate, geraniol, hydrolyzed linseed extract, phenoxyethanol, tocopherol, citric acid, potassium sorbate | I11: boîtier | J11: 10 g | K11: france
A12: ombre d'hermès - palette de couleurs quatuor ombres pour les yeux | B12: hermès | C12: maquillage | D12: paupières | E12: eyeshadow,powder | F12: tous types de peaux | G12: appliquer et estomper sur les paupières à l'aide de votre pinceau préféré. si vous le souhaitez, mouillez légèrement le pinceau avant l'application pour amplifier l'intensité et la précision de la couleur. | H12: mica, calcium sodium borosilicate, caprylic/capric triglyceride, octyldodecyl stearoyl stearate, zinc stearate, methylpropanediol, phenoxyethanol, caprylyl glycol, sodium dehydroacetate, ci 77861, phenylpropanol, cellulose, magnesium stearate, morus alba bark extract | I12: boîtier,rechargeable | J12: 3 g | K12: italie | L12: 3346130411314
A13: goof proof brow powder - easy brow filling powder | B13: benefit | C13: maquillage | D13: sourcils | E13: powder,compact | G13: apply with an angled brush to outline brows, shape and define. use light strokes to fill in sparse brow areas and layer to build color. blend with spoolie. | H13: mica, synthetic fluorphlogopite, dimethicone, trimethylsiloxysilicate, microcrystalline cellulose, kaolin, magnesium stearate, triethoxycaprylylsilane, magnesium myristate, ricinus communis (castor) seed oil, phenoxyethanol, sorbic acid, caprylyl glycol, tocopherol, sunflower seed oil | I13: boîtier | J13: 1,9 g | K13: france | L13: 0602004140357
A14: terracotta luminizer - la poudre enlumineur | B14: guerlain | C14: maquillage | D14: visage | E14: highlighter,powder | F14: toutes carnations | G14: la poudre enlumineur terracotta luminizer peut s’utiliser sur le fond de teint ou la peau nue. appliquer en touches sur le haut des pommettes, l’arête du nez et l’arc de cupidon, pour un maquillage sensuel, éclatant et scintillant. étirer sous l’arcade sourcilière, ou en ombre à paupières, pour un regard subtilement illuminé. | H14: mica, caprylic/capric triglyceride, silica, alumina, c13-15 alkane, coco-caprylate/caprate, polyglyceryl-3 polyricinoleate, polyglyceryl-4 caprate, butylene glycol, triheptanoin, glycerin, c9-12 alkane, parfum, dilinoleic acid/butanediol copolymer, caprylyl glycol, ethylhexylglycerin, triethoxycaprylylsilane, 1-2-hexanediol, lauroyl lysine, polyglyceryl-3 diisostearate, gellan gum, calcium chloride, castor oil, argania spinosa kernel oil, tocopherol | I14: boîtier | J14: 7 g | K14: france | L14: 3346470435667
A15: double wear - poudre de teint mat | B15: estée lauder | C15: maquillage | D15: visage | E15: foundation,powder,compact | F15: tous types de peaux,toutes carnations | G15: trouvez la teinte parfaite : choisissez d’abord l’intensité de la teinte (de clair à foncé, soit de 0 à 8), puis le sous-ton (rosé : c , neutre : n ou chaud : w). comment déterminer son sous-ton ? le sous-ton caractérise l’apparence de la peau nue et la manière dont elle réagit.lequel des sous-tons ci-dessous vous ressemble le plus ? - rosé (c) : la peau a une teinte rosée naturelle et attrape facilement des coups de soleil. - neutre (n) : la peau n’est ni totalement rosée ni totalement dorée mais entre les deux. | H15: boron nitride, polymethylsilsesquioxane, octyldodecyl stearoyl stearate, silica, calcium silicate, isostearyl neopentanoate, tocopheryl acetate, dimethicone, methicone, phenyl trimethicone, titanium dioxide, talc, triethoxycaprylylsilane, trimethylsiloxysilicate, methyl methacrylate crosspolymer, sodium lauroyl aspartate, caprylyl glycol, hexylene glycol, zinc stearate, isopropyl titanium triisostearate, phenoxyethanol | I15: boîtier,applicateur éponge | J15: 12 g | K15: u.k.
A16: le teint ultra tenue - teint compact haute perfection spf 15 | B16: chanel | C16: maquillage | D16: visage | E16: foundation,compact,powder | F16: toutes carnations | G16: appliquer le teint ultra tenue compact à l’aide de l’éponge intégrée par petites pressions sur l’ensemble du visage. pour une couvrance plus intense, répéter le geste sur les zones concernées. | H16: boron nitride, talc, vinyl dimethicone/methicone silsesquioxane crosspolymer, acrylates/ethylhexyl acrylate crosspolymer, triethylhexanoin, dimethicone, barium sulfate, polymethylsilsesquioxane, polymethyl methacrylate, hdi/trimethylol hexyllactone crosspolymer, alumina, silica, magnesium carbonate, stearic acid, aluminum hydroxide, ammonium silver zinc aluminum silicate, triethoxycaprylylsilane, potassium sorbate, sodium dehydroacetate, chlorphenesin, isopropyl titanium triisostearate, hydrolyzed algin, aluminum dimyristate, parfum, methyl methacrylate crosspolymer, sodium lauroyl aspartate, tocopheryl acetate, trifluoropropyldimethyl/trimethylsiloxysilicate, zinc sulfate, zinc chloride, phenoxyethanol, bht, sodium lauroyl glutamate, lysine, magnesium chloride | I16: boîtier | J16: 13 g | K16: france
A17: terracotta blooming bee - la poudre éclat bonne mine - édition limitée | B17: guerlain | C17: maquillage | D17: visage,cou | E17: highlighter,powder | F17: toutes carnations | G17: le mot de violette, directrice de la création du maquillage guerlain : « mon secret pour un effet sun-kissed irrésistible ? appliquer la terracotta sur les zones les plus bombées comme les pommettes, l’arête du nez et le haut du front pour apporter plus de structure au visage tout en réchauffant délicatement le teint. » | H17: mica, silica, lauroyl lysine, zinc stearate, bis-behenyl/isostearyl/phytosteryl dimer dilinoleyl dimer dilinoleate, octyldodecyl stearoyl stearate, dicaprylyl ether, cellulose, calcium sodium borosilicate, dimer dilinoleyl dimer dilinoleate, parfum, caprylyl glycol, ethylhexylglycerin, sodium dehydroacetate, pentylene glycol, water, butylene glycol, propanediol, honey, glycerin, tocopherol, butyrospermum parkii seedcake extract, ci 77861 | I17: boîtier | J17: 10 g | K17: france
A18: oh my cream skincare - blush | B18: oh my cream | C18: maquillage | D18: joues | E18: blush,powder | F18: tous types de peaux | G18: à l’aide du pinceau blush, déposer la poudre sur le bombé des pommettes et estomper vers les tempes. intensifier la couleur si nécessaire. | H18: mica, zinc stearate, c12-15 alkyl benzoate, lauroyl lysine, sodium starch, octyldodecyl stearoyl stearate, silica, caprylic/capric triglyceride, ethylhexylglycerin, coco-caprylate/caprate, calcium carbonate, tocopheryl acetate, carthamus tinctorius seed oil, aloe barbadensis leaf extract, magnesium stearate, tocopherol | I18: boîtier | J18: 4 g | K18: france
A19: poudre compacte certifié bio et végan | B19: jch respect | C19: maquillage | D19: visage,cou | E19: powder,compact | F19: toutes carnations | G19: après votre bb crème ou seule après votre crème de jour, prélevez votre poudre à l’aide votre pinceau poudre, tapotez légèrement votre pinceau pour enlever l’excèdent, avant de l’appliquer sur votre visage. commencez par le front puis sur les joues en balayant toujours de l’intérieur vers l’extérieur. n’oubliez pas votre cou. | H19: mica, corn starch, zinc stearate, octyldodecanol, squalane, benzyl alcohol, lecithin, limonene, prunus amygdalus dulcis oil, shea butter, parfum, dehydroacetic acid, tocopherol, ascorbyl palmitate, citrus aurantium dulcis peel oil, citric acid, linalool | I19: boîtier | J19: 9 g | K19: italie
A20: illuminateur certifié bio et végan | B20: jch respect | C20: maquillage | D20: visage | E20: highlighter,powder | F20: toutes carnations | G20: il s’applique en touche finale sur les parties bombées du visage. débutez par les yeux, afin d’agrandir votre regard, déposez une touche d’illuminateur au niveau de l’arcade sourcilière, juste en dessous du sourcil et terminez par le coin interne de l’œil. passez ensuite aux pommettes, balayez légèrement sur le haut de vos pommettes de l’intérieur vers l’extérieurs. vous pouvez si vous souhaitez affiner votre nez, tracer une ligne le long de son arête. appliquez une légère touche d’illuminateur dans le creux qui se situe entre votre lèvre supérieure et votre nez (l’arc de cupidon). | H20: mica, corn starch, titanium dioxide, squalane, caprylic/capric triglyceride, octyldodecanol, zinc stearate, ci 77491 , benzyl alcohol, limonene, lecithin, prunus amygdalus dulcis oil, shea butter, parfum, dehydroacetic acid, tocopherol, ascorbyl palmitate, citrus aurantium dulcis peel oil, citric acid, linalool | I20: boîtier | J20: 9 g | K20: italie
A21: plein air - poudre éclat rayonnant | B21: hermès | C21: maquillage | D21: joues | E21: blush,powder,compact | F21: tous types de peaux,toutes carnations | G21: appliquez la poudre éclat rayonnant sur peau nue ou après le rituel de teint pour illuminer les pommettes, les tempes, l'arête du nez ou l'arc de cupidon, au doigt ou à l'aide du pinceau fard à joues rose hermès. | H21: mica, squalane, octyldodecyl stearoyl stearate, glycerin, silica, hdi/trimethylol hexyllactone crosspolymer, zinc stearate, kaolin, synthetic fluorphlogopite, pentylene glycol, caprylyl glycol, dicalcium phosphate, sorbitan sesquiisostearate, parfum, sodium dehydroacetate, caprylic/capric triglyceride, tocopherol, tocopheryl acetate, chondrus crispus powder, xanthan gum, morus alba bark extract, benzyl salicylate, limonene, geraniol, citronellol, linalool, hydroxycitronellal, titanium dioxide, ci 77491 | I21: boîtier,rechargeable | J21: 8,5 g | K21: italie | L21: 3346130412212
A22: terracotta light - la poudre éclat bonne mine naturelle | B22: guerlain | C22: maquillage | D22: visage,cou | E22: highlighter,powder | F22: toutes carnations | G22: le mot de violette, directrice de la création du maquillage guerlain : « mon secret pour un effet sun-kissed irrésistible ? appliquer la terracotta sur les zones les plus bombées comme les pommettes, l’arête du nez et le haut du front pour apporter plus de structure au visage tout en réchauffant délicatement le teint. » | H22: mica, silica, lauroyl lysine, zinc stearate, bis-behenyl/isostearyl/phytosteryl dimer dilinoleyl dimer dilinoleate, octyldodecyl stearoyl stearate, dicaprylyl ether, cellulose, calcium sodium borosilicate, dimer dilinoleyl dimer dilinoleate, kaolin, parfum, caprylyl glycol, ethylhexylglycerin, sodium dehydroacetate, pentylene glycol, water, butylene glycol, propanediol, honey, glycerin, tocopherol, ci 77861, butyrospermum parkii seedcake extract | I22: boîtier | J22: 10 g | K22: france | L22: 3346470435612
A23: prisme libre pressed powder - poudre fixatrice matifiante & floutante | B23: givenchy | C23: maquillage | D23: visage | E23: powder,compact | F23: toutes carnations | G23: la poudre compacte prisme libre pressed powder s'applique seule pour matifier le teint ou après le fond de teint pour fixer et sculpter le maquillage. la perfection mate en 3 étapes prismatiques 1. mélanger les 4 couleurs avec le pinceau pour un résultat homogène. 2. appliquer la poudre du centre vers l'extérieur en privilégiant la zone t, ou sur l'ensemble du visage pour un fini mat modulable. 3. estomper sur la peau pour créer le parfait look mat et lumineux à l'effet floutant. | H23: talc, synthetic fluorphlogopite, silica, zinc stearate, dimethicone, diisostearyl malate, octyldodecyl stearoyl stearate, caprylyl glycol, pentylene glycol, phenyl trimethicone, sodium dehydroacetate, parfum, sorbitan sesquioleate, tocopheryl acetate, hydrolyzed sericin, kaolin | I23: boîtier | J23: 9,5 g | K23: italie
A24: kind & free - poudre bonne mine | B24: rimmel london | C24: maquillage | D24: visage | E24: finishing powder/spray,compact | F24: convient aux peaux sensibles/réactives,tous types de peaux | G24: prélever une petite quantité de poudre avec le pinceau ou à l'aide de la houpette, puis l’appliquer sur les zones du visage que vous souhaitez matifier, habituellement le front, le nez et le menton. | H24: mica, kaolin, zinc stearate, avena sativa (oat) kernel flour, octyldodecyl stearoyl stearate, tapioca starch, isopropyl palmitate, calcium silicate, dimethicone, water, 1-2-hexanediol, caprylyl glycol, phenoxyethanol, sorbitan sesquioleate, aloe barbadensis leaf juice | I24: boîtier | J24: 10 g | K24: u.k.
A25: le fard à joues lumière d'ocres | B25: la provençale bio | C25: maquillage | D25: joues | E25: blush,powder | F25: tous types de peaux,toutes carnations | G25: appliquer par petites touches à l'aide d'un pinceau en haut des pommettes et le long de la joue. | H25: talc, corn starch, coconut oil, pentylene glycol, magnesium stearate, glyceryl caprylate, silica, parfum, olea europaea fruit oil, linalool, benzyl alcohol, citronellol, geraniol, eugenol | I25: boîtier | J25: 8 g | K25: italie | L25: 3600551058566
A26: la poudre de teint lumière d'ocres | B26: la provençale bio | C26: maquillage | D26: visage | E26: highlighter,powder | F26: tous types de peaux,toutes carnations | G26: appliquer avec un pinceau sur l'ensemble du visage pour un résultat naturel lumineux. | H26: talc, corn starch, coconut oil, pentylene glycol, magnesium stearate, glyceryl caprylate, parfum, olea europaea fruit oil, linalool, benzyl alcohol, citronellol, geraniol, eugenol | I26: boîtier | J26: 8 g | K26: italie | L26: 3600551058627
A27: blush lumière | B27: chanel | C27: maquillage | D27: joues | E27: blush,powder | F27: toutes carnations | G27: vous pouvez appliquer le blush lumière sur les joues, les pommettes, les tempes. selon le résultat souhaité, vous pouvez : travailler le blush lumière sur les pommettes pour un résultat naturel. travailler le blush lumière sur les pommettes et les joues pour un résultat solaire, lumineux et bonne mine. travailler le blush lumière sur les pommettes, les joues et les tempes, vous obtiendrez un look plus intense qui marquera vos contours. le blush lumière peut être appliqué au-dessus du baume essentiel pour un effet frais et lumineux. le pinceau demi-lune intégré est excellent pour appliquer cette poudre crémeuse. utiliser le côté plat pour appliquer sur de plus grandes surfaces et le bord pour les petits détails, comme l'arête du nez pour un effet bonne mine et ensoleillé. un côté du pinceau peut être utilisé pour appliquer la texture et l'autre pour l'estomper. | H27: cellulose, dicaprylyl carbonate, dimethicone, synthetic fluorphlogopite, magnesium stearate, ricinus communis (castor) seed oil, lauryl peg-9 polydimethylsiloxyethyl dimethicone, aluminum hydroxide, hydrogenated castor oil, chlorphenesin, hydrogen dimethicone, ci 77861, tocopherol, silica | I27: boîtier | J27: 14 g | K27: france | L27: 3145891517675
A28: hollywood glow glide face architect highlighter | B28: charlotte tilbury | C28: maquillage | D28: visage,lèvres,sourcils,nez,yeux | E28: highlighter,powder | F28: tous types de peaux,peaux claires à mediums,peaux claires,peaux mediums | G28: guide pour un teint éclatant de charlotte ! 6 façons de l'utiliser... l'astuce pommettes... pour un effet liftant ! appliquez votre teinte préférée de hollywood glow glide face architect highlighter des pommettes jusqu'aux tempes en estompant vers l'arrière et l'avant pour un effet liftant instantané ! l'astuce mâchoire… pour sculpter ! appliquez le long de la mâchoire à l'aide du pinceau powder & sculpt brush pour une application précise en évitant toujours le menton ! vous sculpterez ainsi les traits de votre visage en un instant ! l'astuce yeux… pour ouvrir et illuminer le regard ! appliquez dans le coin interne de l'œil, au centre de la paupière et le long de la ligne inférieure des cils en soulignant le centre pour illuminer et agrandir votre regard ! utilisez le pinceau smudger brush pour une application plus précise, uniquement sur les zones que vous souhaitez illuminer ! l'astuce nez… pour définir et sculpter ! charlotte appelle cette technique le point d'exclamation ! commencez par l'arête et appliquez sur le centre du nez puis tapotez sur le bout du nez, comme un point ! estompez du bout des doigts. l'astuce sourcils… pour un regard à effet lifté ! appliquez sous l'arcade sourcilière pour un effet liftant instantané ! vous pouvez également tapoter au-dessus du centre de votre sourcil pour un effet encore plus intense ! l'astuce lèvres... pour une moue pulpeuse ! appliquez votre highlighter sur la ligne supérieure des lèvres en vous concentrant sur l'arc de cupidon pour ne pas aller trop haut ! cette astuce vous permet d'obtenir des lèvres plus pulpeuses et plus généreuses ! conseils tilbury : en journée : appliquez sur la peau pour un éclat zéro défaut multidimensionnel ! en soirée : appliquez à l'aide d'un pinceau humide pour un résultat plus intense ! | H28: mica, talc, squalane, diisostearyl malate, boron nitride, hdi/trimethylol hexyllactone crosspolymer, corn starch, dimethicone, caprylyl glycol, ethylhexylglycerin, zinc stearate, dimethiconol, silica, maltodextrin, ci 77861 | I28: boîtier | J28: 7 g | K28: italie | L28: 5056446610964
A29: blanc de perle - fond de teint compact éclaircissant ip20 - pa++ | B29: guerlain | C29: maquillage | D29: visage,cou | E29: foundation,powder,compact | F29: toutes carnations | G29: mélanger ou utiliser les 2 teintes séparément pour un teint pur, lumineux et parfaitement sculpté.1. après votre soin blanc de perle, appliquer la poudre beige unifiante à l’éponge pour homogénéiser et lisser l’ensemble du visage et du cou. 2. avec une extrémité de l’éponge, prélever la bande blanche pour travailler les zones d’ombres, sculpter et illuminer. pour sublimer l'éclat du visage, poudre beige et bande blanche peuvent être balayées d'un seul geste en estompant uniformément à l'éponge. | H29: boron nitride, titanium dioxide, diphenyl dimethicone/vinyl diphenyl dimethicone/silsesquioxane crosspolymer, mica, talc, ethylhexyl methoxycinnamate, silica, barium sulfate, ethylene/acrylic acid copolymer, synthetic fluorphlogopite, nylon-12, benzophenone-3, polymethyl methacrylate, stearic acid, phenyl trimethicone, alumina, neopentyl glycol diethylhexanoate, water, pentylene glycol, sodium dehydroacetate, dipentaerythrityl hexahydroxystearate/hexastearate/hexarosinate, diisostearyl malate, lauroyl lysine, caprylyl glycol, butylene glycol, dimethicone, parfum, aluminum hydroxide, ophiopogon japonicus root extract, benzyl salicylate, faex (yeast extract, bht, geraniol, hydroxycitronellal, magnesium aspartate, lilium candidum bulb extract, phenoxyethanol, hydrolyzed conchiolin protein, ethylhexylglycerin | I29: boîtier | J29: 9 g | K29: france
A30: ready - fond de teint spf 20 | B30: bareminerals | C30: maquillage | D30: visage | E30: foundation,compact | G30: tapoter le pinceau sur le fond de teint jusqu'à ce que les poils soient légèrement colorés. appliquer en douceur sur la peau. en utilisant un pinceau avec une tête rondre, comme le pinceau application zéro défaut, travaillez la matière en mouvements circulaires. en utilisant un pinceau avec une tête plate, comme le pinceau visage précision, travaillez la matière en larges mouvement de lissage. | H30: boron nitride, titanium dioxide, octyldodecyl stearoyl stearate, caprylic/capric triglyceride, glycerin, magnesium silicate, silica, nylon-12, humic acids, rosa canina fruit oil, jojoba esters, corallina officinalis extract, lecithin, betaine, algae extract | I30: boîtier | J30: 14 g | K30: usa
A31: matt minerals - fond de teint mat | B31: une natural beauty | C31: maquillage | D31: visage | E31: foundation,compact | F31: toutes carnations,peaux mixtes à grasses,peaux mixtes,peaux grasses | G31: application au pinceau kabuki ou à l'éponge. | H31: corn starch, octyldodecyl stearoyl stearate, zinc stearate, octyldodecanol, silica, glyceryl caprylate, p-anisic acid, bambusa arundinacea stem powder, sesamum indicum (sesame) seed oil, parfum, tocopherol, glycine soja (soybean) oil | I31: boîtier,rechargeable | J31: 8,5 g | K31: france
A32: big bronzer infinite sun edition - poudre bronzante visage & corps | B32: nocibé | C32: maquillage | D32: visage,cou,buste/décolleté,corps | E32: bronzing,compact | F32: toutes carnations | G32: appliquez-le big bronzer avec un gros pinceau poudre ou un kabuki tout doux sur les joues, le front et le menton pour sculpter les traits de votre visage. prolongez jusqu’au cou et au décolleté pour un effet bonne mine naturel. | H32: talc, mica, caprylic/capric triglyceride, zinc stearate, dimethicone, lauroyl lysine, ethylhexylglycerin, dehydroacetic acid, stearic acid, tocopherol | I32: boîtier | J32: 18 g | K32: italie
A33: glowish - soft radiance bronzing powder | B33: huda beauty | C33: maquillage | D33: visage | E33: bronzing,compact | F33: tous types de peaux,toutes carnations | G33: for a sun-kissed, radiant glow: swirl a bronzer brush onto the powder and sweep across the face to add warmth. for best results, apply with our all over bronze brush! | H33: mica, silica, cetearyl ethylhexanoate, zinc stearate, dimethicone, dodecane, sucrose acetate isobutyrate, rosa damascena flower oil, capsicum annuum extract, shea butter, sunflower seed oil, tocopherol, glycerin, squalene, ethylhexylglycerin, citronellyl methylcrotonate, triethylhexanoin, c30-45 alkyl dimethicone, phenylisopropyl dimethicone, cetyl peg/ppg-10/1 dimethicone, sorbitan sesquioleate, dimethiconol, beta-sitosterol, sodium benzoate, citric acid, sodium salicylate, xanthan gum, ci 77491, ci 77492, ci 77499, titanium dioxide | I33: boîtier | J33: 8 g
A34: teint divin - blush bonne mine | B34: so'bio etic | C34: maquillage | D34: joues | E34: blush,compact | F34: tous types de peaux,toutes carnations,convient aux peaux sensibles/réactives | G34: pour un effet bonne mine, déposer le blush bonne mine certifié bio so’bio étic® en formant une virgule : partir des tempes en redescendant sur les pommettes. | H34: mica, calcium carbonate, tapioca starch, sunflower seed oil, kaolin, lauroyl lysine, hydrogenated castor oil, cellulose, hydrogenated olive oil, mango seed butter, parfum, rubus idaeus (raspberry) seed oil, glycolipids, tocopherol, aloe barbadensis leaf extract, rice powder*, jojoba esters, magnesium stearate, quartz | I34: boîtier | J34: 8 g | K34: france
A35: luminous silk - glow fusion powder | B35: giorgio armani | C35: maquillage | D35: visage | E35: finishing powder/spray,compact | F35: tous types de peaux | G35: pour flouter les imperfections, choisissez la teinte la plus proche de votre carnation. mélangez avec une poudre sculptante ou un pinceau blush. appliquez de préférence sur une peau hydratée. pour accentuer les traits du visage, choisissez une teinte 2 à 3 tons plus clairs pour mettre les zones clés en lumière et 2 à 3 tons plus foncés pour réchauffer le teint ou sculpter les traits. | H35: synthetic fluorphlogopite, talc, lauroyl lysine, octyldodecanol, sorbitan isostearate, isotridecyl isononanoate, dimethicone, barium sulfate, corn starch, dimethicone/vinyl dimethicone crosspolymer, caprylyl glycol, petrolatum, polysorbate 80, phenoxyethanol, water, argilla/magnesium aluminum silicate, acrylonitrile/methyl methacrylate/vinylidene chloride copolymer, disodium stearoyl glutamate, xanthan gum, aluminum hydroxide, laureth-4 | I35: boîtier | K35: france
A36: le phyto-blush - blush lumière | B36: sisley | C36: maquillage | D36: visage,joues | E36: blush,powder | F36: tous types de peaux,toutes carnations | G36: teinte blush : à l’aide du pinceau blush, appliquer en mouvements circulaires ou en lissages pour habiller les pommettes. teinte highlighter : à l’aide du pinceau blush, appliquer en touche finale sur les zones clés du visage à illuminer : du haut des pommettes vers les tempes, l'arête du nez, l'arc de cupidon, l’arcade sourcilière. | H36: mica, polyethylene, boron nitride, c12-15 alkyl benzoate, caprylic/capric triglyceride, polyglyceryl-2 isostearate/dimer dilinoleate copolymer, silica, ethylhexylglycerin, camellia oleifera seed oil, gossypium herbaceum (cotton) seed oil, tocopheryl acetate, zinc stearate, ci 77861, parfum | I36: boîtier | J36: 6,5 g | K36: italie
A37: skin caviar - powder foundation spf 15 uva/pa++ | B37: la prairie | C37: maquillage | D37: visage | E37: foundation,powder,compact | F37: tous types de peaux,toutes carnations | G37: appliquez le fond de teint par effleurage avec sa houppette suédée dédiée ou par mouvements circulaires avec le pinceau pour fond de teint compact la prairie. commencez par le front, puis l’arête du nez, les joues et le menton. insistez autour de la naissance des cheveux et en bas du nez, tout en évitant les sourcils. continuez à estomper autour de la bouche, le long de la ligne de démarcation avec le cou et sous le cou pour une couvrance homogène. | H37: lauroyl lysine, talc, boron nitride, silica, ethylhexyl methoxycinnamate, polymethylsilsesquioxane, dimethicone, magnesium stearate, glycoproteins, panax ginseng root extract, equisetum arvense extract, caviar extract, ascorbyl palmitate, tocopherol, shea butter, sodium hyaluronate, lactobacillus ferment, alumina, saccharomyces cerevisiae extract, glycerin, phenyl trimethicone, water, isopropyl titanium triisostearate, caprylyl glycol, ethyl linoleate, ethyl oleate, ethyl stearate, trimethylsiloxysilicate, ethyl palmitate, bht, caprylic/capric triglyceride, pentylene glycol, propylene glycol, ethylhexylglycerin, parfum, benzyl salicylate, linalool, citronellol, geraniol, alpha-isomethyl ionone, limonene, phenoxyethanol | I37: boîtier,applicateur houpette | J37: 9 g | K37: suisse
A38: naked skin - poudre compacte ultra-haute définition | B38: urban decay | C38: maquillage | D38: visage | E38: finishing powder/spray,powder,compact | F38: tous types de peaux | G38: appliquez-la sur le fond de teint pour fixer votre maquillage ou en retouche tout au long de la journée. utilisez cette poudre avec le baume de beauté spf 20 naked skin pour une couvrance légère ou avec le teint perfection effet peau nue naked skin pour une couvrance plus intense. | H38: mica, boron nitride, zinc stearate, vinyl dimethicone/methicone silsesquioxane crosspolymer, polyethylene, dimethicone, octyldodecyl stearoyl stearate, lauroyl lysine, triethylhexanoin, synthetic wax, trimyristin, glyceryl caprylate, nylon-12 fluorescent brightener 230 salt, polyvinylalcohol crosspolymer, potassium sorbate, sodium dehydroacetate, hydrogenated lecithin, tocopheryl acetate | I38: boîtier | J38: 7,4 g | K38: usa
A39: touche éclat all over glow - poudre illuminatrice éclat total multidimensionnel | B39: yves saint laurent | C39: maquillage | D39: visage | E39: highlighter,powder | F39: tous types de peaux,toutes carnations | G39: à l'aide du pinceau, appliquer sur l'ensemble du visage pour un éclat naturel multidimensionnel et instantané. faîtes glisser sur les pommettes, le nez et le menton pour doner une touche d'éclat plus prononcée. | H39: talc, mica, titanium dioxide, caprylic/capric triglyceride, nylon-12, magnesium stearate, ci 77491, synthetic fluorphlogopite, caprylyl glycol, parfum, water, ci 77861, propylene glycol, althaea officinalis root extract, calendula officinalis flower extract, citric acid, sodium benzoate, potassium sorbate | I39: boîtier | J39: 8,8 g | K39: france
A40: set+glow duo - poudre+enlumineur aux probiotiques | B40: be+radiance | C40: maquillage | D40: visage | E40: blush,highlighter,powder | F40: tous types de peaux,toutes carnations,convient aux peaux sensibles/réactives | G40: le set+glow probiotics peut s’appliquer aux doigts ou au pinceau. vous pouvez appliquer la poudre seule et ajouter l’highlighter sur les pomettes pour un magnifique résultat glowy, ou mélanger les deux produits pour obtenir un teint matifié et éblouissant. | H40: mica, maranta arundinacea root powder, tapioca starch, kaolin, magnesium myristate, moringa oleifera seed oil, squalane, sunflower seed oil, zinc stearate, coco-caprylate/caprate, bentonite, protium heptaphyllum resin, caprylyl glycol, tocopheryl acetate, lannea microcarpa fruit extract, lactobacillus ferment | I40: boîtier | J40: 10 g | K40: france
A41: phyto-poudre compacte - matifiante et embellissante | B41: sisley | C41: maquillage | D41: visage | E41: powder,compact | F41: tous types de peaux,toutes carnations | G41: appliquer avec le pinceau poudre pour une couvrance légère et un fini seconde peau. pour une couvrance plus intense, appliquer à l’aide de la houppette intégrée par légères pressions sur la zone t puis balayer vers l’extérieur. | H41: synthetic fluorphlogopite, talc, phenyl trimethicone, theobroma grandiflorum seed butter, boron nitride, silica, mango seed butter, cocoa seed butter, hibiscus sabdariffa flower extract, triethoxycaprylylsilane, caprylyl glycol, ethylhexylglycerin, lecithin, polymethylsilsesquioxane, c20-24 olefin, alumina, glycerin, water, citric acid, potassium sorbate, sodium benzoate, tocopherol, ascorbyl palmitate | I41: boîtier | J41: 12 g | K41: italie
A42: blush brazilian shimmer - poudre visage nacrée | B42: guerlain | C42: maquillage | D42: visage,buste/décolleté | E42: blush,powder | F42: toutes carnations | G42: touche finale de votre routine maquillage, le blush brazilian shimmer fait rayonner le hâle de votre peau. souriez et appliquez le blush brazilian shimmer à l'aide d'un pinceau sur la partie bombée des pommettes jusqu'aux tempes. | H42: talc, synthetic fluorphlogopite, nylon-12, lauroyl lysine, magnesium myristate, octyldodecyl stearoyl stearate, ethylhexyl palmitate, hydrogenated polyisobutene, boron nitride, silica, pentaerythrityl tetraisostearate, polymethylsilsesquioxane, zinc stearate, dimethicone, sodium dehydroacetate, parfum, caprylyl glycol, pentylene glycol, tocopherol, alpha-isomethyl ionone, benzyl benzoate, linalool, benzyl alcohol, limonene, amyl cinnamal, geraniol, bht | I42: boîtier | J42: 6 g | K42: france
A43: teint divin - poudre de teint unifiante | B43: so'bio etic | C43: maquillage | D43: visage,zone t,cou | E43: foundation,powder | F43: tous types de peaux,toutes carnations,convient aux peaux sensibles/réactives | G43: 1. à l’aide d’un pinceau, prélever de la poudre de teint unifiante certifiée bio so’bio étic®. 2. tapoter le pinceau pour enlever l’excédent. 3. balayer largement sur l’ensemble du visage. insister sur la zone t, plus productrice de sébum (le nez, le menton, et le front). 4. elle peut s’utiliser en retouches matité à tout moment de la journée. | H43: mica, calcium carbonate, tapioca starch, sunflower seed oil, kaolin, lauroyl lysine, hydrogenated castor oil, cellulose, hydrogenated olive oil, mango seed butter, parfum, rubus idaeus (raspberry) seed oil, glycolipids, tocopherol, aloe barbadensis leaf extract, rice powder*, magnesium stearate, jojoba esters | I43: boîtier | J43: 8 g | K43: france
A44: météorites pearl dust palette - palette illuminatrice sur mesure | B44: guerlain | C44: maquillage | D44: visage,yeux,paupières | E44: highlighter,powder,compact | F44: tous types de peaux,toutes carnations | G44: en enlumineur : à l'aide d'un pinceau, appliquez la poudre sur les zones à illuminer: le haut des pommettes, l'arête du nez, l'arc de cupidon et le menton. pour un éclat plus intense, appliquez la poudre à l'aide de votre doigt et estomper. en blush : à l'aide d'un pinceau, appliquez la poudre sur l'ensemble de la pommette. en fard à paupière : au pinceau ou au doigt, appliquez la poudre sur l'ensemble de la paupière mobile pour unifier et dans le coin interne de l'oeil pour illuminer. | H44: synthetic fluorphlogopite, talc, corn starch, triisostearin, octyldodecanol, boron nitride, magnesium aluminum silicate, dimethicone, water, ethylhexylglycerin, 1-2-hexanediol, caprylyl glycol, parfum, alpha-isomethyl ionone, benzyl benzoate, butylene glycol, linalool, benzyl alcohol, ci 77861, limonene, amyl cinnamal, geraniol, bht, cinnamyl alcohol, tocopherol, aluminum hydroxide, hydrolyzed conchiolin protein, hydrated silica, hydrogen dimethicone | I44: boîtier | J44: 8,5 g | K44: italie
A45: powder pop - flower highlighter | B45: clinique | C45: maquillage | D45: visage | E45: highlighter,powder | F45: toutes carnations | G45: appliquer au doigt ou à l’aide d’un pinceau sur une peau nue ou maquillée pour illuminer légèrement l'arête du nez, donner du relief aux pommettes et/ou donner de l'éclat à toute autre zone du visage. | H45: mica, cetearyl ethylhexanoate, c12-20 acid peg-8 ester, hdi/trimethylol hexyllactone crosspolymer, squalane, glycerin, ethylhexylglycerin, caprylyl glycol, carrageenan, dicalcium phosphate, 1-2-hexanediol, polysorbate 80, silica, synthetic fluorphlogopite | I45: boîtier | J45: 9 g | K45: italie
A46: les beiges - poudre belle mine illuminatrice | B46: chanel | C46: maquillage | D46: visage | E46: highlighter,powder | F46: toutes carnations | G46: pour un look naturel lumineux, appliquer la poudre en finition de votre fond de teint sur les zones du visage qui reflètent la lumière.pour un résultat plus léger, réaliser de larges mouvements afin d’appliquer la poudre sur l’ensemble du visage, de l’intérieur vers l’extérieur. | H46: talc, synthetic fluorphlogopite, polyamide-5, stearyl/ppg-3 myristyl ether dimer dilinoleate, boron nitride, synthetic wax, ppg-2 myristyl ether propionate, paraffinum liquidum (mineral oil, silica, kalanchoe pinnata leaf extract, ammonium silver zinc aluminum silicate, cera microcristallina (microcrystalline wax), aluminum dimyristate, methylparaben, beeswax, paraffin, parfum, chlorphenesin, tocopheryl acetate, ci 77861, maltodextrin | I46: boîtier | J46: 10 g | K46: france
A47: couleurs nature - rayonnant jeunesse - duo enlumineur | B47: yves rocher | C47: maquillage | D47: visage | E47: highlighter,powder | F47: tous types de peaux,toutes carnations | H47: mica, talc, synthetic fluorphlogopite, dimethicone, nylon-12, octyldodecyl stearoyl stearate, isopropyl palmitate, polysorbate 20, magnesium aluminum silicate, caprylyl glycol, sorbitan stearate, phenoxyethanol, sodium dehydroacetate, acrylamide/sodium acryloyldimethyltaurate copolymer, jojoba oil, lauroyl lysine, isohexadecane, tocopheryl acetate, hexylene glycol, polysorbate 80, sorbitan oleate, calcium sodium borosilicate, calcium aluminum borosilicate, magnesium oxide, alumina, silica, ci 77861 | I47: boîtier | J47: 6 g | K47: italie
A48: terracotta nude - poudre éclat naturel | B48: guerlain | C48: maquillage | D48: visage,cou | E48: highlighter,powder | F48: toutes carnations | G48: le bon geste pour illuminer et réchauffer naturellement l'ensemble du visage : un secret guerlain, la gestuelle du "3". appliquez la poudre terracotta nude au pinceau en dessinant une 3 de chaque côté du visage : du front aux pommettes, puis des pommettes au menton, et enfin en redescendant le long du cou. terminez, en effleurant le centre du visage, du front au menton. | H48: mica, talc, lauroyl lysine, cellulose, zinc stearate, diisostearyl malate, octyldodecyl stearoyl stearate, parfum, sodium dehydroacetate, ethylene brassylate, caprylyl glycol, ethylhexylglycerin, limonene, magnesium aspartate, tocopheryl acetate, prunus armeniaca (apricot) kernel oil, triethoxycaprylylsilane, manganese gluconate, linalool, hexyl cinnamal, ascorbyl palmitate, alpha-isomethyl ionone, coumarin, citral, eugenol, geraniol, hydroxycitronellal, solanum lycopersicum (tomato) fruit/leaf/stem extract, tocopherol, sunflower seed oil, rosmarinus officinalis (rosemary) leaf extract | I48: boîtier | J48: 10 g | K48: france
A49: terracotta matte - poudre sculptante | B49: guerlain | C49: maquillage | D49: visage,cou | E49: highlighter,powder | F49: toutes carnations | G49: le bon geste pour sculpter le teint en 3 secondes ou ensoleiller le visage sans brillance : un secret guerlain, la gestuelle du "3". appliquez la poudre sculptante en dessinant un "3" de chaque côté du visage : du front aux bas des pommettes, puis du bas des pommettes au menton, enfin en redescendant le long du cou. | H49: talc, silica, lauroyl lysine, kaolin, bis-behenyl/isostearyl/phytosteryl dimer dilinoleyl dimer dilinoleate, ethylhexyl palmitate, octyldodecyl stearoyl stearate, caprylyl glycol, parfum, pentaerythrityl tetraethylhexanoate, pentylene glycol, zinc stearate, sodium dehydroacetate, ethylene brassylate, limonene, magnesium aspartate, tocopheryl acetate, prunus armeniaca (apricot) kernel oil, manganese gluconate, linalool, hexyl cinnamal, tocopherol, ascorbyl palmitate, alpha-isomethyl ionone, coumarin, citral, eugenol, geraniol, alumina, magnesium oxide, hydroxycitronellal, solanum lycopersicum (tomato) fruit/leaf/stem extract, sunflower seed oil, rosmarinus officinalis (rosemary) leaf extract, ci 77491, ci 77492, ci 77499 , titanium dioxide | I49: boîtier | J49: 10 g | K49: france
A50: éclat du désert - poudre illuminatrice | B50: chanel | C50: maquillage | D50: visage | E50: highlighter,powder | F50: tous types de peaux | G50: les astuces de lucia pica : c’est la touche finale pour apporter un supplément de lumière au visage. s’applique sur peau nue ou déjà maquillée sur les zones reliefs du visage : commencer de la pommette et étirer vers les tempes, puis illuminer l’arête du nez et l’arc de cupidon pour un effet sensuel. estomper grâce à l’applicateur. | H50: synthetic fluorphlogopite, boron nitride, magnesium carbonate, diisostearyl malate, trihydroxystearin, dimethicone, silica, ethylhexyl palmitate, paraffinum liquidum (mineral oil, polymethyl methacrylate, ammonium silver zinc aluminum silicate, sucrose tetrastearate triacetate, cera microcristallina (microcrystalline wax), magnesium stearate, tocopheryl acetate, potassium sorbate, paraffin, chlorphenesin, ci 77861, sorbitan isostearate, talc | I50: boîtier | J50: 11 g | K50: france
A51: high glass - illuminating powder | B51: nyx professional makeup | C51: maquillage | D51: visage | E51: highlighter,powder | F51: toutes carnations | G51: rehausse les points saillants de ton visage grâce à notre high glass illuminating powder brush. | H51: dimethicone, caprylic/capric triglyceride, trimethylsiloxyphenyl dimethicone, polybutene, dimethicone crosspolymer, zinc oxide [nano], lauroyl lysine, water, caprylyl glycol, phenoxyethanol | I51: boîtier | J51: 4 g | K51: taiwan
A52: éclat magnétique de chanel - poudre illuminatrice | B52: chanel | C52: maquillage | D52: visage | E52: highlighter,powder | F52: tous types de peaux | G52: appliquez sur le haut des pommettes et estomper jusqu’à ce que la matière s’estompe au profit de la lumière. créez un halo étincelant autour des yeux, avant ou après l’application de l’ombre à paupières. déposez un léger voile de poudre sur l’ensemble du visage comme une subtile pluie de lumière, et insistez plus spécialement sur les pommettes, l’arête du nez et l’arcade sourcilière. peut s’appliquer sur un maquillage poudre ou crème. | H52: dicaprylyl carbonate, dimethicone, cellulose, magnesium stearate, synthetic fluorphlogopite, paraffinum liquidum (mineral oil, magnesium silicate, cera microcristallina (microcrystalline wax), lauryl peg-9 polydimethylsiloxyethyl dimethicone, paraffin, chlorphenesin, silica, ci 77861, tocopherol | I52: boîtier | J52: 10 g | K52: france
A53: duo de camélias - illuminating powder duo | B53: chanel | C53: maquillage | D53: visage | E53: highlighter,powder | F53: tous types de peaux | G53: sweep onto center of forehead, tops of cheekbones, brow bones and cupid’s bow. or, apply all over for a subtly radiant look. | H53: alumina, synthetic fluorphlogopite, cetearyl ethylhexanoate, glycerin, squalane, c12-20 acid peg-8 ester, hdi/trimethylol hexyllactone crosspolymer, ci 77861, silica, caprylyl glycol, polysorbate 80, ethylhexylglycerin, 1-2-hexanediol, chondrus crispus extract, xanthan gum, pentaerythrityl tetra-di-t-butyl hydroxyhydrocinnamate, calcium chloride, dicalcium phosphate | I53: boîtier | J53: 8,5 g
A54: o !mega glaze all-over foil luminizer | B54: marc jacobs beauty | C54: maquillage | D54: visage,corps | E54: highlighter,powder | F54: tous types de peaux,toutes carnations | G54: appliquez-le pour illuminer vos pommettes, le haut de vos épaules, vos jambes ou n'importe quelle zone où vous souhaitez apporter une touche de lumière. | H54: mica, calcium aluminum borosilicate, caprylic/capric triglyceride, microcrystalline cellulose, bis-diglyceryl polyacyladipate-2, diisostearyl malate, phenyl trimethicone, dimethicone, dimethicone/vinyl dimethicone crosspolymer, caprylyl glycol, ethylhexylglycerin, ci 77861, sodium dehydroacetate, water, tocopherol, calcium sodium borosilicate, synthetic fluorphlogopite, silica, titanium dioxide, ci 77491, ci 77492, ci 77499 | I54: boîtier | J54: 10 g | K54: canada
A55: highlighter - poudre visage illuminatrice | B55: guerlain | C55: maquillage | D55: visage | E55: highlighter,powder | F55: tous types de peaux | G55: pour un éclat boosté, illuminez les parties bombées du visages. dessinez un g du centre du front vers les tempes, les pommettes et le haut du nez en redescendant jusqu'à la pointe du menton. | H55: synthetic fluorphlogopite, mica, limnanthes alba (meadowfoam) seed oil, hydrogenated vegetable oil, caprylic/capric triglyceride, hectorite, polymethylsilsesquioxane, parfum, soybean glycerides, caprylyl glycol, phenethyl alcohol, shea butter, shea butter, alpha-isomethyl ionone, oleic/linoleic/linolenic polyglycerides, benzyl benzoate, sorbitan tristearate, linalool, benzyl alcohol, limonene, diamond powder, amyl cinnamal, geraniol, bht, cinnamyl alcohol, eugenol, ascorbyl palmitate, tocopherol, citric acid | I55: boîtier | J55: 6 g | K55: italie
A56: météorites goldenland - perles de poudre révélatrices de lumière | B56: guerlain | C56: maquillage | D56: visage | E56: highlighter,pearls,powder | F56: toutes carnations | G56: utiliser le pinceau météorites, conçu pour prélever la juste mesure de poudre et appliquer météorites goldenland uniformément sur l’ensemble du visage finaliser le maquillage. pour un éclat boosté, illuminer les parties bombées : dessiner un g du centre du front vers les tempes, les pommettes et le haut du nez en redescendant jusqu’à la pointe du menton. | H56: synthetic fluorphlogopite, talc, nylon-12, magnesium myristate, distarch, silica, magnesium carbonate, triticum vulgare (triticum vulgare (wheat) starch, hydrated silica, pentylene glycol, polymethylsilsesquioxane, mica, parfum, sodium dehydroacetate, glyceryl stearate, caprylyl glycol, sorbic acid, alpha-isomethyl ionone, benzyl benzoate, tocopherol, linalool, benzyl alcohol, diamond powder, limonene, amyl cinnamal, geraniol, bht, cinnamyl alcohol | I56: boîtier | J56: 25 g | K56: france
A57: poudre minérale haute définition | B57: couleur caramel | C57: maquillage | D57: visage | E57: foundation,powder,compact | F57: toutes carnations | G57: utiliser le pinceau poudre n°1 pour une diffusion parfaite sur l'ensemble du visage. | H57: mica, corn starch, zinc stearate, ricinus communis (castor) seed oil, squalane, octyldodecanol, silica, glycerin, lecithin, argania spinosa kernel oil, prunus armeniaca (apricot) kernel oil, sodium anisate, sodium levulinate, tocopherol, ascorbyl palmitate, water, citric acid | I57: boîtier | J57: 7,5 g | K57: italie
A58: bounce & blur - blush fard à joues | B58: bareminerals | C58: maquillage | D58: visage | E58: blush,powder | F58: tous types de peaux,toutes carnations | G58: prélevez le produit avec votre doigt en effectuant de petits mouvements circulaires et tapotez la couleur sur la paupière, en estompant du bout des doigts. pas besoin d'appuyer pour prélever le produit. il s'agit d'une formule souple et fragile qui peut parfois glisser à l'intérieur de l'emballage pendant le transport. si tel est le cas, elle peut être délicatement replacée dans la palette afin de tenir toutes ses promesses. | H58: dimethicone, silica, ethylhexyl isononanoate, boron nitride, diisostearyl malate, trimethylsiloxysilicate, dimethicone crosspolymer, bht, imperata cylindrica root extract, lycopodium clavatum extract, calcium aluminum borosilicate, ethylhexylglycerin, glycerin, methicone, nylon-12, pyridoxine cyclic phosphate, sodium hyaluronate, ci 77861, phenoxyethanol | I58: boîtier | J58: 5,9 g | K58: canada
A59: perfection powder - fond de teint compact ultra léger | B59: marc jacobs beauty | C59: maquillage | D59: visage | E59: foundation,compact,powder | F59: tous types de peaux,toutes carnations | G59: éponge double face - utilisez le côté lisse pour appliquer la poudre et le côté floqué pour lisser et moduler la couvrance. peut aussi être utilisé comme une poudre de finition avec le fond de teint genius gel. pour une application optimale utiliser the face ii - pinceau fond de teint poudre | H59: mica, silica, cetearyl ethylhexanoate, zinc stearate, polyglyceryl-10 myristate, dimethicone, sorbitan isostearate, polysorbate 20, octyldodecyl stearoyl stearate, caprylyl glycol, ethylhexylglycerin, 1-2-hexanediol, hydrogenated lecithin, diisostearoyl polyglyceryl-3 dimer dilinoleate, xanthan gum, carrageenan | I59: boîtier | J59: 11 g | K59: italie
A60: joli blush - blush couleur & éclat longue tenue | B60: clarins | C60: maquillage | D60: joues | E60: blush,powder | F60: tous types de peaux,toutes carnations | G60: à appliquer à tout moment de la journée ou de la soirée ! | H60: talc, mica, titanium dioxide, octyldodecyl stearoyl stearate, synthetic fluorphlogopite, zinc stearate, dimethicone, ci 19140, ci 73360, ci 77007, citric acid, lauroyl lysine, phenoxyethanol, water, corylus avellana (hazel) seed oil, ci 77499, silica, parfum, ci 45380, tocopheryl acetate, butylene glycol, ci 77491, camellia sinensis leaf extract, calcium sodium borosilicate, calcium aluminum borosilicate, lapsana communis flower/leaf/stem extract, ci 77861 | I60: boîtier | J60: 5 g | K60: italie
A61: diorskin mineral nude matte - poudre perfectrice mate naturelle | B61: dior | C61: maquillage | D61: visage | E61: highlighter,powder | F61: tous types de peaux,toutes carnations | G61: 1. pour un teint naturellement mat et flouté, appliquer la poudre de finition uniformément sur l'ensemble du visage à l'aide d'un pinceau kabuki. 2. pour corriger l'excès de brillance, insister sur la zone t délimitée par le front et le nez pour matifier le teint et diminuer l'apparence des pores. appliquer au cours de la journée pour rafraîchir instantanément le teint et le sublimer d'un éclat mat lumineux. | H61: talc, nylon-12, zinc stearate, polymethylsilsesquioxane, mica, hdi/trimethylol hexyllactone crosspolymer, polyethylene, lauroyl lysine, silica, dimethicone, isostearyl isostearate, ethylhexyl isononanoate, ethylhexyl palmitate, phenyl trimethicone, octyldodecyl stearoyl stearate, caprylyl glycol, ethylhexylglycerin, water, sodium dehydroacetate, sodium benzoate, dimethicone/peg-10/15 crosspolymer, parfum, ascorbyl glucoside, magnesium aspartate, zinc gluconate, linalool, limonene, tocopherol, citronellol, rhodochrosite extract, phenoxyethanol, sodium citrate, sorbic acid, bht | I61: boîtier | J61: 7 g | K61: france
A62: defence sun - fond de teint solaire compact spf 50 | B62: bionike | C62: solaire,maquillage | D62: visage | E62: sunscreen,foundation,powder,compact | F62: peaux sensibles/très sensibles,peaux claires | G62: appliquer le produit à l’aide de l'éponge et l’estomper sur l'ensemble du visage, en partant du centre et en l’étirant vers l’extérieur. renouveler l’application en cours d’exposition au soleil. | H62: mica, talc, zinc oxide, titanium dioxide, silica, polymethyl methacrylate, dimethicone, ethylene/acrylic acid copolymer, trimethylsiloxyphenyl dimethicone, magnesium myristate, caprylyl glycol, sorbitan sesquioleate, dimethiconol, capryloyl glycine, polysorbate 20, undecylenoyl glycine, c12-15 alkyl benzoate, p-anisic acid, tocopheryl acetate, diisostearyl malate, niacinamide, carnosine, sodium carboxymethyl beta-glucan, disodium edta, pentylene glycol, hydrogen dimethicone, water | I62: boîtier,applicateur éponge | J62: 10 g | K62: italie
A63: blur expert - voile poudre perfecteur lissant | B63: sisley | C63: maquillage | D63: visage | E63: blurrer,powder | F63: toutes carnations,tous types de peaux | G63: prélever à l’aide d’un gros pinceau* et appliquer sur l'ensemble du visage. pour plus de couvrance insister sur les zones à flouter. peut s'utiliser sur peau nue, seul ou après une base de maquillage pour un résultat lumineux, frais et naturel. peut s'appliquer après le fond de teint pour parfaire le maquillage.en retouches au cours de la journée pour matifier, lisser et embellir.*pinceau poudre sisley ou kabuki phyto-touches rétractable | H63: mica, titanium dioxide, synthetic fluorphlogopite, ci 77163, pentaerythrityl tetraisostearate, ci 77492, diphenyl dimethicone/vinyl diphenyl dimethicone/silsesquioxane crosspolymer, peg-12 dimethicone, sorbitan isostearate, methyl methacrylate crosspolymer, ci 77491, glycerin, hydrogenated lecithin, caprylyl glycol, ethylhexylglycerin, silica, 1-2-hexanediol, carrageenan, xanthan gum, peg-10 dimethicone, ci 77499 | I63: boîtier | J63: 11 g | K63: italie
A64: accomplice instant blurring beauty powder with brush | B64: marc jacobs beauty | C64: maquillage | D64: visage | E64: concealer,highlighter,powder,compact | F64: toutes carnations | H64: talc, mica, isononyl isononanoate, rice starch, dimethicone, corn starch, synthetic fluorphlogopite, zinc stearate, caprylyl glycol, phenoxyethanol, hexylene glycol, octyldodecyl stearoyl stearate, polymethylsilsesquioxane, silica, trimethylsiloxysilicate, ci 77491, ci 77492, ci 77007, titanium dioxide | I64: boîtier | J64: 10 g | K64: usa
A65: bronzing compact - poudre soleil sculptante | B65: clarins | C65: maquillage | D65: visage | E65: highlighter,powder,compact | F65: tous types de peaux | G65: appliquer sur la peau du visage. | H65: talc, octyldodecyl stearoyl stearate, nylon-12, diisostearyl malate, hdi/trimethylol hexyllactone crosspolymer, zinc stearate, glycerin, empetrum nigrum fruit juice, boron nitride, parfum, lauroyl lysine, tocopheryl acetate, water, butylene glycol, dimethicone, hydroxyethyl urea, phenoxyethanol, camellia sinensis leaf extract, algin, potassium sorbate, acacia senegal gum, lapsana communis flower/leaf/stem extract | I65: boîtier | J65: 18 g | K65: italie
A66: diorskin mineral nude - bronze wild earth - poudre bonne mine ensoleillée | B66: dior | C66: maquillage | D66: visage | E66: highlighter,powder | F66: toutes carnations,tous types de peaux | G66: 1. à appliquer à l'aide du pinceau kabubi n° 17, spécialement conçu pour une application facile et modulable à l'envie, 2. appliquer en forme de 3, des tempes vers les pommettes en terminant le long des maxillaires pour un effet bonne mine ensoleillée déroutant de naturel. | H66: talc, nylon-12, lauroyl lysine, polymethylsilsesquioxane, boron nitride, silica, dimethicone, octyldodecyl stearoyl stearate, ethylhexyl palmitate, hydrogenated polyisobutene, magnesium myristate, pentaerythrityl tetraisostearate, sodium dehydroacetate, synthetic fluorphlogopite, caprylyl glycol, pentylene glycol, zinc stearate, parfum, ascorbyl glucoside, magnesium aspartate, zinc gluconate, linalool, limonene, citronellol, bht, tocopherol | I66: boîtier | J66: 8 g | K66: france
A67: 5 couleurs wild earth - palette regard couture couleurs & effets haute fidelité | B67: dior | C67: maquillage | D67: paupières | E67: eyeshadow,powder | F67: tous types de peaux | G67: pour un regard naturel 1. appliquer la teinte moyenne sur l'ensemble de la paupière mobile à l'aide de l'embout mousse rond pour ouvrir le regard, puis la teinte la plus foncée au ras des cils avec l'embout liner pour le définir. 2. illuminer en appliquant la teinte la plus claire sous l'arcade sourcilière et dans le coin interne de l'œil avec le pinceau pour agrandir le regard. pour un regard sophistiqué 1. appliquer la teinte moyenne sur l'ensemble de la paupière mobile à l'aide de l'embout mousse rond pour ouvrir le regard, puis la teinte la plus foncée au ras des cils avec l'embout liner pour le définir. 2. estomper sur l'ensemble de la paupière mobile et vers l'extérieur en utilisant le pinceau. 3. illuminer avec la teinte la plus claire sous l'arcade sourcilière et dans le coin interne de l'oeil avec l'embout mousse rond pour un contraste encore plus intense afin de structurer le regard. | H67: mica, alumina, synthetic fluorphlogopite, cetearyl ethylhexanoate, hdi/trimethylol hexyllactone crosspolymer, squalane, octyldodecyl stearoyl stearate, glycerin, ci 77861, silica, polysorbate 80, caprylyl glycol, ethylhexylglycerin, 1-2-hexanediol, chondrus crispus extract, xanthan gum, pentaerythrityl tetra-di-t-butyl hydroxyhydrocinnamate, cetearyl alcohol, dicalcium phosphate, calcium titanium borosilicate, tocopherol | I67: boîtier,applicateur mousse,applicateur pinceau | J67: 3 g | K67: italie
A68: les beiges - poudre belle mine naturelle | B68: chanel | C68: maquillage | D68: visage | E68: highlighter,powder | F68: toutes carnations | G68: pour un résultat léger, appliquer au pinceau demi-lune. réaliser de larges mouvements sur l’ensemble du visage, de l’intérieur vers l’extérieur. pour modeler les reliefs, utiliser l’extrémité du pinceau demi-lune. balayer sur le haut du front, le menton et l’arête du nez. seule, la poudre permet un maquillage du teint naturel. sur le fond de teint, elle joue le rôle de touche éclat. choisir une teinte en ton sur ton, ou légèrement plus intense que la carnation pour un effet ensoleillé. | H68: talc, nylon-12, octyldodecyl neopentanoate, boron nitride, microcrystalline cellulose, trihydroxystearin, magnesium carbonate, triethylhexanoin, dimethicone, silica, gossypium herbaceum (cotton) extract, rose extract, shea butter, aluminum dimyristate, potassium sorbate, parfum, sodium dehydroacetate, chlorphenesin, tocopheryl acetate, citric acid | I68: boîtier | J68: 12 g | K68: france
A69: sun stalk'r - face + eye bronzer & highlighter palette | B69: fenty beauty | C69: maquillage | D69: visage | E69: bronzing,highlighter,powder | F69: tous types de peaux,toutes carnations | G69: sun stalk'r bronzer for an instant all-over bronzed glow, apply sun stalk'r bronzer with the cheek-hugging bronzer brush 190. for a more targeted application, contour with the sculpting bronzer brush 195. artistry pro tip: sun stalk’r bronzer is great for warming up not necessarily deepening your skin tone, giving it life! it has the right pigments to bring out the warmth in even the deepest skin tones. layer two shades for extra bronzed-out dimension. try a lighter bronzer shade for all-over glow, then add a deeper shade to sculpt cheekbones, jawline, temples, and the sides of your nose. | H69: mica, synthetic fluorphlogopite, dimethicone, caprylic/capric triglyceride, octyldodecyl stearoyl stearate, isostearyl alcohol, dimethicone/vinyl dimethicone crosspolymer, zinc stearate, caprylyl glycol, silica, phenoxyethanol, hexylene glycol, calcium sodium borosilicate, calcium aluminum borosilicate, ci 77861 | I69: boîtier | J69: 2 x 1,13 g|5 x 2,55 g | K69: usa
A70: boom, boom bloom poudre lumière | B70: mac cosmetics | C70: maquillage | D70: visage | E70: highlighter,powder | F70: tous types de peaux | G70: appliquez avec un pinceau pour un rendu lumineux. illuminez les zones bombées du visage avec le pinceau pour les joues 133s. | H70: talc, corn starch, dimethicone, octyldodecyl stearoyl stearate, zinc stearate, pentaerythrityl tetraisostearate, rosa canina (rose hips) fruit extract, ginkgo biloba leaf extract, acrylates/octylacrylamide copolymer, isostearyl alcohol, zea mays (corn) oil, tetrasodium edta, potassium sorbate, chlorphenesin | I70: boîtier | J70: 9 g | K70: italie
A71: fond de teint compact protecteur uv spf 30 | B71: shiseido | C71: maquillage,solaire | D71: visage | E71: foundation,powder,compact | F71: tous types de peaux | G71: appliquer à l’éponge sèche ou humide suivant le fini recherché. préservez votre peau, apprenez à la protéger contre l’impact nocif des rayons uv. notre tutoriel vous montre comment appliquer notre fond de teint compact protecteur uv avec une éponge. une routine anti-âge pour une beauté durable ! apprenez à appliquer le fond de teint compact protecteur uv avec notre pinceau parfait, pour une peau protégée des facteurs de stress externes. | H71: mica, titanium dioxide [nano], synthetic fluorphlogopite, titanium dioxide, ethylhexyl methoxycinnamate, dimethicone, octocrylene, ci 77492, silica, nylon-12, vinyl dimethicone/methicone silsesquioxane crosspolymer, petrolatum, methicone, ci 77491, triethylhexanoin, zinc oxide, sorbitan sesquiisostearate, hydrogen dimethicone, chlorphenesin, aluminum hydroxide, ci 77499, water, peg/ppg-14/7 dimethyl ether, polysilicone-2, alcohol, sodium magnesium silicate, hydrated silica, parfum, triethoxycaprylylsilane, aluminum distearate, butylene glycol, glycerin, tocopherol, tocopheryl acetate, limonene, saxifraga sarmentosa extract, bht, linalool, distearyldimonium chloride, butylphenyl methylpropional, benzyl benzoate, hexyl cinnamal, syzygium jambos leaf extract, ci 77861, sodium hyaluronate, sophora angustifolia root extract | I71: boîtier | J71: 12 g | K71: usa | L71: 0170559777026
A72: voyage de chanel - palette de voyage visage blush et poudres illuminatrices | B72: chanel | C72: maquillage | D72: visage | E72: blush,highlighter,powder | F72: tous types de peaux | G72: paris : appliquer la teinte paris sur les pommettes, puis estomper progressivement par des mouvements circulaires de manière uniforme pour un effet bonne mine. utiliser en duo avec la teinte london pour rehausser davantage le teint.london : appliquer la teinte london sur les pommettes, puis estomper progressivement par des mouvements circulaires de manière uniforme pour un effet bonne mine. utiliser en duo avec la teinte paris pour apporter une touche d'éclat au teint.new york : pour un teint ensoleillé et naturel, appliquer la teinte new york sur les zones où le soleil est le plus susceptible de hâler le teint : les pommettes, le front et l'arête du nez, puis estomper. ajouter une touche de couleur paris pour un fini rosé éclatant.tokyo : appliquer la poudre illuminatrice tokyo sur les zones du visage qui captent la lumière (pommettes, arête du nez, arc de cupidon). mélanger la teinte avec les blush paris ou london pour leur donner plus de luminosité. | H72: synthetic fluorphlogopite, boron nitride, diisostearyl malate, magnesium carbonate, dimethicone, silica, ethylhexyl palmitate, trihydroxystearin, paraffinum liquidum (mineral oil, polymethyl methacrylate, ammonium silver zinc aluminum silicate, sucrose tetrastearate triacetate, cera microcristallina (microcrystalline wax), tocopheryl acetate, talc, potassium sorbate, methylparaben, paraffin, chlorphenesin, propylparaben, sorbitan isostearate, ci 77861 | I72: boîtier | J72: 11 g | K72: france
A73: terracotta contour & glow palette - palette visage contour et éclat | B73: guerlain | C73: maquillage | D73: visage | E73: bronzing,blush,highlighter,powder | F73: toutes carnations | G73: ce nouvel allié bonne mine s'applique en 3 étapes, à l'aide du pinceau poudre terracotta, après le fond de teint ou à même la peau : 1. utiliser la teinte mate foncée pour ombrer et sculpter le teint : appliquer dans le creux des joues, sur les bords du front et le long de la mâchoire.2. appliquer la poudre bronzante en dessinant un 3, du milieu du front au bas des pommettes, et du bas des pommettes au menton. 3. rehausser le teint en appliquant le blush sur les pommettes. 4. terminer avec la poudre enlumineur à appliquer sur le haut des arcades sourcilières, le haut des pommettes, l'arête du nez et sur l'arc de cupidon. chaque étape peut être appliquée seule pour une infinité de looks. | H73: talc, nylon-12, lauroyl lysine, magnesium myristate, synthetic fluorphlogopite, octyldodecyl stearoyl stearate, ethylhexyl palmitate, hydrogenated polyisobutene, boron nitride, mica, dimethicone, zinc stearate, pentaerythrityl tetraethylhexanoate, pentylene glycol, serine, parfum, sodium dehydroacetate, ethylene brassylate, allantoin, caprylyl glycol, octyldodeceth-16, linalool, benzyl salicylate, tocopherol, geraniol, sodium hyaluronate, alpha-isomethyl ionone, hydroxycitronellal, citronellol, coumarin, limonene, bht | I73: boîtier | J73: 20 g
A74: météorites highlighter duo - poudre holographique | B74: guerlain | C74: maquillage | D74: visage | E74: highlighter,powder | F74: tous types de peaux | G74: appliquer au pinceau l'highlighter duo météorites sur les zones à illuminer : les bombés des pommettes et l'arcade sourcilière. appliquez une seule teinte ou un mélange des deux, à votre convenance. | H74: mica, cetearyl ethylhexanoate, hdi/trimethylol hexyllactone crosspolymer, squalane, octyldodecyl stearoyl stearate, glycerin, polysorbate 80, ethylhexylglycerin, caprylyl glycol, 1-2-hexanediol, chondrus crispus extract, xanthan gum, pentaerythrityl tetra-di-t-butyl hydroxyhydrocinnamate, silica, cetearyl alcohol, dicalcium phosphate, synthetic fluorphlogopite, tocopherol | I74: boîtier | J74: 9 g | K74: italie
A75: blush subtil - poudre blush | B75: lancôme | C75: maquillage | D75: visage,joues | E75: blush,powder | F75: tous types de peaux,toutes carnations | G75: 1. prenez un pinceau et placez le côté plat dans la poudre. 2. enlevez l'excédent en le tapotant sur le dos de votre main. 3. appliquez blush subtil sur les pommettes et vers les tempes pour allonger le visage, souligner ses contours et le structurer. | H75: talc, hdi/trimethylol hexyllactone crosspolymer, isononyl isononanoate, ptfe, lauroyl lysine, dimethicone, methicone, magnesium stearate, synthetic fluorphlogopite, ci 77861, calcium aluminum borosilicate, calcium sodium borosilicate, diphenylsiloxy phenyl trimethicone, silica, alumina, caprylyl glycol, parfum, linalool, geraniol, citronellol, benzyl alcohol, benzyl salicylate | I75: boîtier | J75: 6 g
A76: diorskin nude luminizer rising stars | B76: dior | C76: maquillage | D76: visage | E76: highlighter,powder | F76: tous types de peaux | G76: 1. à l'aide du kabuki n°17, appliquer par touche sur les zones bombées du visage. 2. finaliser par une touche sur l'arc de cupidon pour un effet brillant. | H76: mica, cetearyl ethylhexanoate, hdi/trimethylol hexyllactone crosspolymer, squalane, octyldodecyl stearoyl stearate, glycerin, polysorbate 80, ethylhexylglycerin, caprylyl glycol, parfum, 1-2-hexanediol, ethylene brassylate, chondrus crispus extract, xanthan gum, pentaerythrityl tetra-di-t-butyl hydroxyhydrocinnamate, silica, cetearyl alcohol, dicalcium phosphate, synthetic fluorphlogopite, linalool, limonene, citronellol, bht, tocopherol | I76: boîtier | J76: 6 g | K76: italie
A77: diorskin nude luminizer lolli'glow | B77: dior | C77: maquillage | D77: visage | E77: highlighter,powder | F77: toutes carnations | G77: 1. à l'aide du kabuki n°17, appliquer par touche sur les zones bombées du visage. 2. finaliser par une touche sur l'arc de cupidon pour un effet brillant. | H77: mica, calcium titanium borosilicate, cetearyl ethylhexanoate, hdi/trimethylol hexyllactone crosspolymer, squalane, octyldodecyl stearoyl stearate, glycerin, polysorbate 80, ethylhexylglycerin, caprylyl glycol, parfum, 1-2-hexanediol, ethylene brassylate, chondrus crispus extract, xanthan gum, pentaerythrityl tetra-di-t-butyl hydroxyhydrocinnamate, ci 77861, silica, cetearyl alcohol, dicalcium phosphate, synthetic fluorphlogopite, linalool, limonene, citronellol, bht, tocopherol | I77: boîtier | J77: 6 g | K77: italie
A78: météorites compact - poudre compact anti-brillance et illuminatrice | B78: guerlain | C78: maquillage | D78: visage | E78: highlighter,powder,compact | F78: toutes carnations | G78: touche finale de votre routine maquillage ou retouches au cours de la journée, utilisez la poudre compact météorites pour améliorer la tenue de votre maquillage tout en embellissant votre teint. les 4 teintes peuvent être appliquées ensemble pour unifier et apporter de la lumière au visage ou séparément pour corriger les imperfections chromatiques. pour un éclat boosté, illuminez les parties bombées : à l’aide du pinceau météorites, dessinez un g du centre du front vers les tempes, les pommettes et le haut du nez en redescendant jusqu’à la pointe du menton. | H78: talc, synthetic fluorphlogopite, polyethylene, hdi/trimethylol hexyllactone crosspolymer, zinc stearate, dimethicone, polymethylsilsesquioxane, calcium sodium borosilicate, phenyl trimethicone, dimethicone/vinyl dimethicone crosspolymer, lauroyl lysine, caprylyl glycol, parfum, sodium dehydroacetate, ethylhexylglycerin, silica, ci 77861, alpha-isomethyl ionone, benzyl benzoate, linalool, benzyl alcohol, diamond powder, limonene, amyl cinnamal, geraniol, bht, cinnamyl alcohol, tocopherol | I78: boîtier | J78: 8 g
A79: ladies in all climates - poudre lumière universelle | B79: guerlain | C79: maquillage | D79: visage | E79: highlighter,powder | F79: tous types de peaux | G79: pour un résultat matifiant et perfecteur, appliquer la poudre par tapotements sur l’ensemble du visage en commençant par la zone médiane. pour avoir l’effet d’un voile de finition unifiant et transparent, balayer délicatement l’ensemble du visage. | H79: talc, lauroyl lysine, nylon-12, octyldodecyl stearoyl stearate, magnesium myristate, synthetic fluorphlogopite, silica, ethylhexyl isononanoate, ethylhexyl palmitate, dimethicone, pentylene glycol, sodium dehydroacetate, caprylyl glycol, parfum, cellulose, alpha-isomethyl ionone, benzyl benzoate, linalool, dimethylmethoxy chromanol, benzyl alcohol, limonene, bht, tocopherol | I79: boîtier,rechargeable | J79: 10 g | K79: france | L79: 3346470427563
A80: mystic glow powder - enlumineur visage et yeux wet & dry | B80: givenchy | C80: maquillage | D80: visage,yeux | E80: highlighter,powder | F80: tous types de peaux,toutes carnations | G80: à appliquer par touche sur le visage pour faire naître des points de lumière. elle s’utilise aussi bien sèche sur les joues que humide sur les paupières pour illuminer le visage en lui donnant un coup d’éclat immédiat. résultat : des effets make up à moduler à l’infini, du plus naturel au plus intense. | H80: calcium aluminum borosilicate, cetearyl ethylhexanoate, glycerin, hdi/trimethylol hexyllactone crosspolymer, silica, squalane, octyldodecyl stearoyl stearate, polysorbate 80, ethylhexylglycerin, caprylyl glycol, 1-2-hexanediol, ci 77861, chondrus crispus extract, xanthan gum, pentaerythrityl tetra-di-t-butyl hydroxyhydrocinnamate, cetearyl alcohol, dicalcium phosphate, synthetic fluorphlogopite, tocopherol, mica, titanium dioxide, ci 77491 | I80: boîtier | J80: 4 g | K80: italie
A81: ombre première - ombre à paupières poudre longue tenue, fini métallique | B81: chanel | C81: maquillage | D81: paupières | E81: eyeshadow,powder | F81: convient aux porteurs de lentilles | G81: déposer l'ombre à l'aide de l'applicateur mousse et estomper avec l'applicateur pinceau.avec ombre première, lucia pica, global creative designer pour le maquillage et la couleur de chanel, dévoile sa technique signature inspirée par son expérience de makeup artist : le layering*. pour un résultat subtil et profond très longue tenue, appliquer ombre première crème sur toute la paupière mobile afin de l'habiller et l'unifier. puis, pour révéler et intensifier le regard, superposer ombre première poudre en jouant sur les associations de couleurs.*superposition | H81: alumina, synthetic fluorphlogopite, cetearyl ethylhexanoate, glycerin, squalane, ci 77861, silica, caprylyl glycol, polysorbate 80, ethylhexylglycerin, 1-2-hexanediol, calcium chloride, chondrus crispus extract, xanthan gum, pentaerythrityl tetra-di-t-butyl hydroxyhydrocinnamate | I81: boîtier | J81: 2,2 g | K81: italie
A82: rouge blush midnight wish - couleur couture - blush poudre lumière d'or | B82: dior | C82: maquillage | D82: visage | E82: blush,powder | F82: toutes carnations | G82: 1. à l'aide du pinceau blush n°16, appliquer rouge blush du haut vers le bas de la pommette. 2. dégrader le blush sur la bosse du sourire, par mouvements circulaires. 3. pour un effet illuminateur sculptant, appliquer le blush sur le haut de la pommette, estomper vers les tempes puis étirer au-dessus de l'arcade sourcillière. | H82: mica, cetearyl ethylhexanoate, hdi/trimethylol hexyllactone crosspolymer, alumina, squalane, octyldodecyl stearoyl stearate, glycerin, polysorbate 80, ethylhexylglycerin, caprylyl glycol, 1-2-hexanediol, silica, ci 77861, chondrus crispus extract, xanthan gum, pentaerythrityl tetra-di-t-butyl hydroxyhydrocinnamate, cetearyl alcohol, dicalcium phosphate, synthetic fluorphlogopite, tocopherol | I82: boîtier | J82: 4 g | K82: italie
A83: 5 couleurs midnight wish - palette regard couture couleurs & effets haute fidélité | B83: dior | C83: maquillage | D83: paupières | E83: eyeshadow,powder,compact | G83: tuto maquillage pour un regard naturel : 1. appliquer la teinte moyenne sur l'ensemble de la paupière mobile à l'aide de l'embout mousse rond pour ouvrir le regard, puis la teinte la plus foncée au ras des cils avec l'embout liner pour le définir. 2. illuminer en appliquant la teinte la plus claire sous l'arcade sourcilière et dans le coin interne de l'œil avec le pinceau pour agrandir le regard.tuto maquillage pour un regard sophistiqué : 1. appliquer la teinte moyenne sur l'ensemble de la paupière mobile à l'aide de l'embout mousse rond pour ouvrir le regard, puis la teinte la plus foncée au ras des cils avec l'embout liner pour le définir. 2. estomper sur l'ensemble de la paupière mobile et vers l'extérieur en utilisant le pinceau. 3. illuminer en appliquantla teinte la plus claire sous l'arcade sourcilière et dans le coin interne de l'oeil avec l'embout mousse rond pour un contraste encore plus intense afin de structurer le regard. | H83: alumina, synthetic fluorphlogopite, cetearyl ethylhexanoate, hdi/trimethylol hexyllactone crosspolymer, squalane, octyldodecyl stearoyl stearate, glycerin, mica, silica, ci 77861, polysorbate 80, ethylhexylglycerin, caprylyl glycol, 1-2-hexanediol, chondrus crispus extract, xanthan gum, pentaerythrityl tetra-di-t-butyl hydroxyhydrocinnamate, cetearyl alcohol, dicalcium phosphate, tocopherol | I83: boîtier | J83: 3 g
A84: le lion de chanel - poudre illuminatrice visage | B84: chanel | C84: maquillage | D84: visage | E84: highlighter,powder | F84: toutes carnations | G84: prélever un peu de poudre avec l’applicateur. appliquer par effleurage, du coin externe du sourcil jusque sur le haut des pommettes en formant un « c ». répéter la gestuelle pour intensifier l’éclat. | H84: cetearyl ethylhexanoate, c12-20 acid peg-8 ester, hdi/trimethylol hexyllactone crosspolymer, squalane, glycerin, caprylyl glycol, polysorbate 80, ethylhexylglycerin, ci 77861, 1-2-hexanediol, chondrus crispus extract, xanthan gum, calcium chloride, pentaerythrityl tetra-di-t-butyl hydroxyhydrocinnamate, silica, dicalcium phosphate, synthetic fluorphlogopite | I84: boîtier | J84: 8 g | K84: italie
A85: 0.09 touch au ginseng - compact crémeux poudre effet velouté, perfecteur de peau spf 20 | B85: erborian | C85: maquillage | D85: visage | E85: foundation,compact,powder,cream/emulsion | F85: toutes carnations | G85: appliquer sur tout le visage avec l’éponge fournie pour un teint comme uniforme. | H85: mica, titanium dioxide, dimethicone, hydrogenated polyisobutene, diphenylsiloxy phenyl trimethicone, polymethyl methacrylate, dimethicone/vinyl dimethicone crosspolymer, ethylhexyl methoxycinnamate, glycyrrhiza glabra (licorice) root extract, panax ginseng root extract, dioscorea villosa (wild yam) root extract, kigelia africana fruit extract, equisetum giganteum extract, centella asiatica extract, water, glyceryl caprylate, lauroyl lysine, 1-2-hexanediol, methicone, triethoxycaprylylsilane, butylene glycol, ci 77499, ci 77491, ci 77492 | I85: boîtier,applicateur éponge | J85: 8 g | K85: corée
A86: flash-nude poudre - poudre invisible pro-perfection | B86: laboratoires filorga | C86: maquillage | D86: visage | E86: highlighter,powder | F86: tous types de peaux,peaux mixtes,toutes carnations | G86: appliquer après les soins quotidiens et/ou maquillage sur l’ensemble du visage à l’aide d’un pinceau. peut également s’utiliser en retouche au cours de la journée pour une mise en beauté flash. | H86: synthetic fluorphlogopite, polymethylsilsesquioxane, dimethicone/vinyl dimethicone crosspolymer, silica, dimethicone, zinc stearate, phenyl trimethicone, phenoxyethanol, water, caprylyl glycol, peg-8 caprylic/capric glycerides, parfum, maltodextrin, octyldodeceth-25, sodium chloride, sodium hyaluronate, moringa pterygosperma seed extract, saccharide isomerate, glucose, propylene glycol, potassium chloride, caesalpinia spinosa fruit extract, calcium chloride, decylene glycol, magnesium sulfate, glutamine, sodium phosphate, sunflower sprout extract, ascorbic acid, sodium acetate, lysine hcl, arginine hcl, alanine, histidine hcl, valine, leucine, threonine, isoleucine, tryptophan, phenylalanine, tyrosine, glycine, polysorbate 80, serine, cystine, cyanocobalamin, glutathione, asparagine, aspartic acid, ornithine hcl, glutamic acid, nicotinamide adenine dinucleotide, proline, methionine, taurine, hydroxyproline, glucosamine hcl, coenzyme a, sodium glucuronate, thiamine diphosphate, retinyl acetate, inositol, niacin, niacinamide, pyridoxine hcl, biotin, calcium pantothenate, riboflavin, sodium tocopheryl phosphate, thiamine hcl, folic acid | I86: boîtier | J86: 6,2 g | K86: france
A87: couture blush - poudre fusionselle couleur sans effet matière intensité modulable | B87: yves saint laurent | C87: maquillage | D87: visage | E87: blush,powder | F87: toutes carnations | G87: - pour un effet bonne mine naturel : souriez et appliquez à l'aide du pinceau sur la partie bombée des pommettes jusqu'aux tempes. - pour un effet sculptant sophistiqué : appliquez au niveau du creux des joues pour structurer le visage. | H87: synthetic fluorphlogopite, talc, lauroyl lysine, octyldodecanol, sorbitan isostearate, isotridecyl isononanoate, dimethicone, corn starch, dipentaerythrityl tetrahydroxystearate/tetraisostearate, dimethicone/vinyl dimethicone crosspolymer, caprylyl glycol, petrolatum, polysorbate 80, water, argilla/magnesium aluminum silicate, acrylonitrile/methyl methacrylate/vinylidene chloride copolymer, xanthan gum, alumina, silica, phenoxyethanol, calcium sodium borosilicate, calcium aluminum borosilicate, parfum, ci 77861, isobutane, disodium stearoyl glutamate, laureth-4, aluminum hydroxide | I87: boîtier | J87: 3 g | K87: france
A88: innerglow cheekpowder | B88: shiseido | C88: maquillage | D88: joues | E88: blush,powder | F88: toutes carnations,tous types de peaux | G88: à l’aide du pinceau maru fude multi face brush, appliquez au centre du visage et estompez le long de pommettes. | H88: talc, mica, titanium dioxide, cetearyl ethylhexanoate, isononyl isononanoate, silica, zinc stearate, ethylhexylglycerin, caprylyl glycol, ci 77861 | I88: boîtier | J88: 4 g | K88: italie
